Workbook
Name ALL: #REF!
Name ALLP: #REF!
Name COST: #REF!
Name Markets: #REF!
Name MAT: #REF!
Name Print_Area_MI: #REF!
Name PUR: #REF!
Name SUM: #REF!

Sheet P
B1: 1-100 MATERIALS | C1: 2-100 LABOR | D1: 4-100 SUBCONTRACTOR | E1: 7-100 AIRLINE EXPENSES | F1: 7-200 HOTEL EXPENSES | G1: 7-300 AUTO RENTAL | H1: 7-400 MILEAGE/FUEL EXPENSE | I1: 7-600 PARKING / TOLLS | J1: 7-750 PER DIEM (TRAVEL DAYS) | K1: 7-760 PER DIEM (WORK DAYS) | L1: 7-770 TRAVEL PAY | M1: 5-000 OTHER COSTS | N1: 5-100 FREIGHT | O1: 5-100 RETURN FREIGHT | P1: 5-300 RENTALS | Q1: CA LITIGATION FUND | R1: 5-900 MISC. EXPENSES | S1: 5-901 CONTINGENCY | T1: TAX % | U1: Total | V1: MARK UP $ | X1: Product # | Y1: Description | Z1: Cost | AA1: Unit Size | AB1: Weight | AC1: Color | AD1: B:B | AE1: C:C | AF1: D:D | AG1: L:L | AH1: M:M | AI1: N:N | AJ1: Total Qty | AK1: USD | AL1: USD | AM1: 1 | AN1: Product # | AO1: Description | AP1: Cost | AQ1: Unit Size | AR1: Weight | AS1: Color | AT1: PRODUCT | AU1: UOM | AV1: LOOKUP COMBO | AW1: PRICE | AY1: PROD ID | AZ1: PRODUCT | BA1: COLOR | BB1: UOM | BC1: PRICE | BD1: PRODUCT | BE1: COLOR | BF1: UOM | BG1: CATEGORY | BH1: PATCH | BI1: 1/2 GAL | BJ1: DESCRIPTION | BK1: CATEGORY | BL1: DESCRIPTION | BM1: CATEGORY | BN1: DESCRIPTION | BO1: CATEGORY
A2: RIO | B2: =IFERROR(VLOOKUP(B$1,SGC!$C:$D,2,FALSE),0) -> 0 | C2: =IFERROR(VLOOKUP(C$1,SGC!$C:$D,2,FALSE),0) -> 0 | D2: =IFERROR(VLOOKUP(D$1,SGC!$C:$D,2,FALSE),0) -> 0 | E2: =IFERROR(VLOOKUP(E$1,SGC!$C:$D,2,FALSE),0) -> 0 | F2: =IFERROR(VLOOKUP(F$1,SGC!$C:$D,2,FALSE),0) -> 0 | G2: =IFERROR(VLOOKUP(G$1,SGC!$C:$D,2,FALSE),0) -> 0 | H2: =IFERROR(VLOOKUP(H$1,SGC!$C:$D,2,FALSE),0) -> 0 | I2: =IFERROR(VLOOKUP(I$1,SGC!$C:$D,2,FALSE),0) -> 0 | J2: =IFERROR(VLOOKUP(J$1,SGC!$F:$H,3,FALSE),0) -> 0 | K2: =IFERROR(VLOOKUP(K$1,SGC!$F:$H,3,FALSE),0) -> 0 | L2: =IFERROR(VLOOKUP(L$1,SGC!$F:$H,3,FALSE),0) -> 0 | M2: =IFERROR(VLOOKUP(M$1,SGC!$F:$H,3,FALSE),0) -> 0 | N2: =IFERROR(VLOOKUP(N$1,SGC!$F:$H,3,FALSE),0) -> 0 | O2: =IFERROR(VLOOKUP(O$1,SGC!$F:$H,3,FALSE),0) -> 0 | P2: =IFERROR(VLOOKUP(P$1,SGC!$F:$H,3,FALSE),0) -> 0 | Q2: =IFERROR(VLOOKUP(Q$1,SGC!$C:$D,2,FALSE),0) -> 0 | R2: =IFERROR(VLOOKUP(R$1,SGC!$F:$H,3,FALSE),0) -> 0 | S2: =IFERROR(VLOOKUP(S$1,SGC!$F:$H,3,FALSE),0) -> 0 | T2: =SUM(SGC!N78:O80) -> 0 | U2: =VLOOKUP("CUSTOMER BID AMOUNT*",SGC!$M:$Q,5,FALSE) -> 0 | V2: =IFERROR(VLOOKUP(V$1,SGC!$P:$R,3,FALSE),0) -> 0 | W2: RS88 | X2: FIBERTAPE | Y2: FIBERGLASS TAPE 6"X75 FT | Z2: =Table1[[#This Row],[D:D]] -> 33.1782 | AA2: Roll | AD2: RIO | AE2: 30.162 | AF2: =Table1[[#This Row],[C:C]]*1.1 -> 33.1782 | AI2: =IFERROR(VLOOKUP(X2,#REF!,8,FALSE),0) -> 0 | AK2: CAD | AL2: #VALUE! | AM2: {=_FV(AL2,"Price")} -> 1.3733 | AN2: =PROD_ID_TABLE[[#This Row],[PROD ID]] -> 3500 EPOXYN//A1/2 | AO2: =_xlfn.CONCAT(BD2:BF2) -> RESUFLOR 3500 EPOXY QUICK PATCH (FAST)N/A1/2 GAL | AP2: =BC2 -> 97.69 | AQ2: =BF2 -> 1/2 GAL | AS2: =BE2 -> N/A | AT2: RESUFLOR 3500 EPOXY QUICK PATCH (FAST) | AU2: 1/2 GAL | AV2: =AT2&AU2 -> RESUFLOR 3500 EPOXY QUICK PATCH (FAST)1/2 GAL | AW2: 97.69 | AY2: =_xlfn.CONCAT(AZ2:BB2) -> 3500 EPOXYN//A1/2 | AZ2: =MID(BD2,10,10) -> 3500 EPOXY | BA2: =LEFT(BE2,2)&RIGHT(BE2,2) -> N//A | BB2: =LEFT(BF2,3) -> 1/2 | BC2: =IFERROR(VLOOKUP(BD2&BF2,AV:AW,2,FALSE),0) -> 97.69 | BD2: RESUFLOR 3500 EPOXY QUICK PATCH (FAST) | BE2: N/A | BF2: 1/2 GAL | BG2: PATCH | BH2: GRAY | BI2: 2 GAL | BJ2: ACCELERA 4850 GROUT/TOPCOAT POLYASPARTIC | BK2: POLY | BL2: RESUPRIME 3477 EPOXY WATER PRIMER/SEALER | BM2: PRIMER | BN2: RESUTILE 4638 HS POLYURETHANE FLOOR ENAMEL | BO2: URETHANE
A3: SIKA | B3: =IFERROR(VLOOKUP(B$1,SIKA!$C:$D,2,FALSE),0) -> 0 | C3: =IFERROR(VLOOKUP(C$1,SIKA!$C:$D,2,FALSE),0) -> 0 | D3: =IFERROR(VLOOKUP(D$1,SIKA!$C:$D,2,FALSE),0) -> 0 | E3: =IFERROR(VLOOKUP(E$1,SIKA!$C:$D,2,FALSE),0) -> 0 | F3: =IFERROR(VLOOKUP(F$1,SIKA!$C:$D,2,FALSE),0) -> 0 | G3: =IFERROR(VLOOKUP(G$1,SIKA!$C:$D,2,FALSE),0) -> 0 | H3: =IFERROR(VLOOKUP(H$1,SIKA!$C:$D,2,FALSE),0) -> 0 | I3: =IFERROR(VLOOKUP(I$1,SIKA!$C:$D,2,FALSE),0) -> 0 | J3: =IFERROR(VLOOKUP(J$1,SIKA!$F:$H,3,FALSE),0) -> 0 | K3: =IFERROR(VLOOKUP(K$1,SIKA!$F:$H,3,FALSE),0) -> 0 | L3: =IFERROR(VLOOKUP(L$1,SIKA!$F:$H,3,FALSE),0) -> 0 | M3: =IFERROR(VLOOKUP(M$1,SIKA!$F:$H,3,FALSE),0) -> 0 | N3: =IFERROR(VLOOKUP(N$1,SIKA!$F:$H,3,FALSE),0) -> 0 | O3: =IFERROR(VLOOKUP(O$1,SIKA!$F:$H,3,FALSE),0) -> 0 | P3: =IFERROR(VLOOKUP(P$1,SIKA!$F:$H,3,FALSE),0) -> 0 | Q3: =IFERROR(VLOOKUP(Q$1,SIKA!$C:$D,2,FALSE),0) -> 0 | R3: =IFERROR(VLOOKUP(R$1,SIKA!$F:$H,3,FALSE),0) -> 0 | S3: =IFERROR(VLOOKUP(S$1,SIKA!$F:$H,3,FALSE),0) -> 0 | T3: =SUM(SIKA!N69:O71) -> 0 | U3: =VLOOKUP("CUSTOMER BID AMOUNT*",SIKA!$M:$Q,5,FALSE) -> 0 | V3: =IFERROR(VLOOKUP(V$1,SIKA!$P:$R,3,FALSE),0) -> 0 | W3: 600UV GA | X3: JS4C | Y3: 600UV Joint Filler Pigment | Z3: =Table1[[#This Row],[D:D]] -> 22 | AA3: Pack | AD3: RIO | AE3: 20 | AF3: =Table1[[#This Row],[C:C]]*1.1 -> 22 | AI3: =IFERROR(VLOOKUP(X3,#REF!,8,FALSE),0) -> 0 | AK3: MXN | AL3: #VALUE! | AM3: {=_FV(AL3,"Price")} -> 17.7247 | AN3: =PROD_ID_TABLE[[#This Row],[PROD ID]] -> M. URETHAN//A44 | AO3: =_xlfn.CONCAT(BD3:BF3) -> CEMLACK UM. URETHANE CEMENT PATCH 1:1:1N/A44 LBS | AP3: =BC3 -> 47.67 | AQ3: =BF3 -> 44 LBS | AS3: =BE3 -> N/A | AT3: RESUFLOR 3513 SCRATCH COAT MASTIC (THICK/SLOW) | AU3: 2 GAL | AV3: =AT3&AU3 -> RESUFLOR 3513 SCRATCH COAT MASTIC (THICK/SLOW)2 GAL | AW3: 104.75 | AY3: =_xlfn.CONCAT(AZ3:BB3) -> M. URETHAN//A44 | AZ3: =MID(BD3,10,10) -> M. URETHA | BA3: =LEFT(BE3,2)&RIGHT(BE3,2) -> N//A | BB3: =LEFT(BF3,3) -> 44 | BC3: =IFERROR(VLOOKUP(BD3&BF3,AV:AW,2,FALSE),0) -> 47.67 | BD3: CEMLACK UM. URETHANE CEMENT PATCH 1:1:1 | BE3: N/A | BF3: 44 LBS | BG3: PATCH | BH3: WHITE | BJ3: RESUDECK FLA CLEAR ALIPHATIC POLYASPARTIC TOPCOAT | BK3: POLY | BL3: RESUPRIME 3504 HIGH SOLID CLEAR PRIMER/SEALER | BM3: PRIMER | BN3: RESUTILE 4640 HTS 100 HS HIGH TRAFFIC URETHANE ENAMEL | BO3: URETHANE
A4: SW | B4: =IFERROR(VLOOKUP(B$1,SW!$C:$D,2,FALSE),0) -> 0 | C4: =IFERROR(VLOOKUP(C$1,SW!$C:$D,2,FALSE),0) -> 0 | D4: =IFERROR(VLOOKUP(D$1,SW!$C:$D,2,FALSE),0) -> 0 | E4: =IFERROR(VLOOKUP(E$1,SW!$C:$D,2,FALSE),0) -> 0 | F4: =IFERROR(VLOOKUP(F$1,SW!$C:$D,2,FALSE),0) -> 0 | G4: =IFERROR(VLOOKUP(G$1,SW!$C:$D,2,FALSE),0) -> 0 | H4: =IFERROR(VLOOKUP(H$1,SW!$C:$D,2,FALSE),0) -> 0 | I4: =IFERROR(VLOOKUP(I$1,SW!$C:$D,2,FALSE),0) -> 0 | J4: =IFERROR(VLOOKUP(J$1,SW!$F:$H,3,FALSE),0) -> 0 | K4: =IFERROR(VLOOKUP(K$1,SW!$F:$H,3,FALSE),0) -> 0 | L4: =IFERROR(VLOOKUP(L$1,SW!$F:$H,3,FALSE),0) -> 0 | M4: =IFERROR(VLOOKUP(M$1,SW!$F:$H,3,FALSE),0) -> 0 | N4: =IFERROR(VLOOKUP(N$1,SW!$F:$H,3,FALSE),0) -> 0 | O4: =IFERROR(VLOOKUP(O$1,SW!$F:$H,3,FALSE),0) -> 0 | P4: =IFERROR(VLOOKUP(P$1,SW!$F:$H,3,FALSE),0) -> 0 | Q4: =IFERROR(VLOOKUP(Q$1,SW!$C:$D,2,FALSE),0) -> 0 | R4: =IFERROR(VLOOKUP(R$1,SW!$F:$H,3,FALSE),0) -> 0 | S4: =IFERROR(VLOOKUP(S$1,SW!$F:$H,3,FALSE),0) -> 0 | T4: =SUM(SW!N92:O94) -> 0 | U4: =VLOOKUP("CUSTOMER BID AMOUNT*",SW!$M:$Q,5,FALSE) -> 0 | V4: =IFERROR(VLOOKUP(V$1,SW!$P:$R,3,FALSE),0) -> 0 | W4: 600UV CG | X4: JS4U | Y4: 600UV Joint Filler | Z4: =Table1[[#This Row],[D:D]] -> 125.4 | AA4: Box | AD4: RIO | AE4: 114 | AF4: =Table1[[#This Row],[C:C]]*1.1 -> 125.4 | AI4: =IFERROR(VLOOKUP(X4,#REF!,8,FALSE),0) -> 0 | AN4: =PROD_ID_TABLE[[#This Row],[PROD ID]] -> 3513 SCRATGRAY2 G | AO4: =_xlfn.CONCAT(BD4:BF4) -> RESUFLOR 3513 SCRATCH COAT MASTIC (THICK/SLOW)GRAY2 GAL | AP4: =BC4 -> 104.75 | AQ4: =BF4 -> 2 GAL | AS4: =BE4 -> GRAY | AT4: RESUPRIME 3477 EPOXY WATER PRIMER/SEALER | AU4: 3 GAL | AV4: =AT4&AU4 -> RESUPRIME 3477 EPOXY WATER PRIMER/SEALER3 GAL | AW4: 217.16 | AY4: =_xlfn.CONCAT(AZ4:BB4) -> 3513 SCRATGRAY2 G | AZ4: =MID(BD4,10,10) -> 3513 SCRAT | BA4: =LEFT(BE4,2)&RIGHT(BE4,2) -> GRAY | BB4: =LEFT(BF4,3) -> 2 G | BC4: =IFERROR(VLOOKUP(BD4&BF4,AV:AW,2,FALSE),0) -> 104.75 | BD4: RESUFLOR 3513 SCRATCH COAT MASTIC (THICK/SLOW) | BE4: GRAY | BF4: 2 GAL | BG4: PATCH | BH4: N/A | BJ4: ACCELERA EXT SMALL 1R:1H | BL4: RESUPRIME 3579 HIGH SOLID EPOXY PRIMER/BINDER | BM4: PRIMER | BN4: RESUTILE 4641 HPS 100 HS ALIPHATIC URETHANE TOPCOAT | BO4: URETHANE
X5: JS4U-CG | Y5: 600UV Joint Filler - Chateau Gray | Z5: =Table1[[#This Row],[D:D]] -> 125.4 | AA5: Box | AD5: RIO | AE5: 114 | AF5: =Table1[[#This Row],[C:C]]*1.1 -> 125.4 | AI5: =IFERROR(VLOOKUP(X5,#REF!,8,FALSE),0) -> 0 | AN5: =PROD_ID_TABLE[[#This Row],[PROD ID]] -> 3513 SCRATWHTE2 G | AO5: =_xlfn.CONCAT(BD5:BF5) -> RESUFLOR 3513 SCRATCH COAT MASTIC (THICK/SLOW)WHITE2 GAL | AP5: =BC5 -> 104.75 | AQ5: =BF5 -> 2 GAL | AS5: =BE5 -> WHITE | AT5: RESUPRIME 3477 EPOXY WATER PRIMER/SEALER | AU5: 15 GAL | AV5: =AT5&AU5 -> RESUPRIME 3477 EPOXY WATER PRIMER/SEALER15 GAL | AW5: 1034.58 | AY5: =_xlfn.CONCAT(AZ5:BB5) -> 3513 SCRATWHTE2 G | AZ5: =MID(BD5,10,10) -> 3513 SCRAT | BA5: =LEFT(BE5,2)&RIGHT(BE5,2) -> WHTE | BB5: =LEFT(BF5,3) -> 2 G | BC5: =IFERROR(VLOOKUP(BD5&BF5,AV:AW,2,FALSE),0) -> 104.75 | BD5: RESUFLOR 3513 SCRATCH COAT MASTIC (THICK/SLOW) | BE5: WHITE | BF5: 2 GAL | BG5: PATCH | BH5: PRIMER | BJ5: ACCELERA ONE RESIN (SEE MIX CHART) | BL5: RESUPRIME 3831 MVB MOISTURE EPOXY PRIMER | BM5: PRIMER | BN5: RESUTILE AQUA 4410 WB ALIPHATIC URETHANE - COLOR | BO5: URETHANE
A6: BLANK | B6: =IFERROR(VLOOKUP(B$1,BLANK!$M:$N,2,FALSE),0) -> 0 | C6: =IFERROR(VLOOKUP(C$1,BLANK!$M:$N,2,FALSE),0) -> 0 | D6: =IFERROR(VLOOKUP(D$1,BLANK!$M:$N,2,FALSE),0) -> 0 | E6: =IFERROR(VLOOKUP(E$1,BLANK!$M:$N,2,FALSE),0) -> 0 | F6: =IFERROR(VLOOKUP(F$1,BLANK!$M:$N,2,FALSE),0) -> 0 | G6: =IFERROR(VLOOKUP(G$1,BLANK!$M:$N,2,FALSE),0) -> 0 | H6: =IFERROR(VLOOKUP(H$1,BLANK!$M:$N,2,FALSE),0) -> 0 | I6: =IFERROR(VLOOKUP(I$1,BLANK!$M:$N,2,FALSE),0) -> 0 | J6: =IFERROR(VLOOKUP(J$1,BLANK!$P:$R,3,FALSE),0) -> 0 | K6: =IFERROR(VLOOKUP(K$1,BLANK!$P:$R,3,FALSE),0) -> 0 | L6: =IFERROR(VLOOKUP(L$1,BLANK!$P:$R,3,FALSE),0) -> 0 | M6: =IFERROR(VLOOKUP(M$1,BLANK!$P:$R,3,FALSE),0) -> 0 | N6: =IFERROR(VLOOKUP(N$1,BLANK!$P:$R,3,FALSE),0) -> 0 | O6: =IFERROR(VLOOKUP(O$1,BLANK!$P:$R,3,FALSE),0) -> 0 | P6: =IFERROR(VLOOKUP(P$1,BLANK!$P:$R,3,FALSE),0) -> 0 | Q6: =IFERROR(VLOOKUP(Q$1,BLANK!$M:$N,2,FALSE),0) -> 0 | R6: =IFERROR(VLOOKUP(R$1,BLANK!$P:$R,3,FALSE),0) -> 0 | S6: =IFERROR(VLOOKUP(S$1,BLANK!$P:$R,3,FALSE),0) -> 0 | T6: =VLOOKUP("TAX*",BLANK!$M:$Q,5,FALSE) -> 0 | U6: =VLOOKUP("CUSTOMER BID AMOUNT*",BLANK!$M:$Q,5,FALSE) -> 0 | V6: =IFERROR(VLOOKUP(V$1,BLANK!$P:$R,3,FALSE),0) -> 0 | X6: JS4U-GA | Y6: 600UV Joint Filler - Gray Area | Z6: =Table1[[#This Row],[D:D]] -> 125.4 | AA6: Box | AD6: RIO | AE6: 114 | AF6: =Table1[[#This Row],[C:C]]*1.1 -> 125.4 | AI6: =IFERROR(VLOOKUP(X6,#REF!,8,FALSE),0) -> 0 | AN6: =PROD_ID_TABLE[[#This Row],[PROD ID]] -> 3477 EPOXN//A3 G | AO6: =_xlfn.CONCAT(BD6:BF6) -> RESUPRIME 3477 EPOXY WATER PRIMER/SEALERN/A3 GAL | AP6: =BC6 -> 217.16 | AQ6: =BF6 -> 3 GAL | AS6: =BE6 -> N/A | AT6: RESUPRIME 3504 HIGH SOLID CLEAR PRIMER/SEALER | AU6: 2 GAL | AV6: =AT6&AU6 -> RESUPRIME 3504 HIGH SOLID CLEAR PRIMER/SEALER2 GAL | AW6: 168.31 | AY6: =_xlfn.CONCAT(AZ6:BB6) -> 3477 EPOXN//A3 G | AZ6: =MID(BD6,10,10) -> 3477 EPOX | BA6: =LEFT(BE6,2)&RIGHT(BE6,2) -> N//A | BB6: =LEFT(BF6,3) -> 3 G | BC6: =IFERROR(VLOOKUP(BD6&BF6,AV:AW,2,FALSE),0) -> 217.16 | BD6: RESUPRIME 3477 EPOXY WATER PRIMER/SEALER | BE6: N/A | BF6: 3 GAL | BG6: PRIMER | BH6: N/A | BJ6: ACCELERA ONE HARDENER (SEE MIX CHART) | BL6: RESUPRIME 5531 OIL STOP PRIMER | BM6: PRIMER | BN6: RESUTILE AQUA 4411 WB ALIPHATIC URETHANE - CLEAR | BO6: URETHANE
A7: POLISH | X7: R-CSB-25 | Y7: RIO Sandy Beige Colorant | Z7: =Table1[[#This Row],[D:D]] -> 440 | AA7: 25 Pint | AD7: RIO | AE7: 400 | AF7: =Table1[[#This Row],[C:C]]*1.1 -> 440 | AI7: =IFERROR(VLOOKUP(X7,#REF!,8,FALSE),0) -> 0 | AN7: =PROD_ID_TABLE[[#This Row],[PROD ID]] -> 3477 EPOXN//A15 | AO7: =_xlfn.CONCAT(BD7:BF7) -> RESUPRIME 3477 EPOXY WATER PRIMER/SEALERN/A15 GAL | AP7: =BC7 -> 1034.58 | AQ7: =BF7 -> 15 GAL | AS7: =BE7 -> N/A | AT7: RESUPRIME 3504 HIGH SOLID CLEAR PRIMER/SEALER | AU7: 10 GAL | AV7: =AT7&AU7 -> RESUPRIME 3504 HIGH SOLID CLEAR PRIMER/SEALER10 GAL | AW7: 800.36 | AY7: =_xlfn.CONCAT(AZ7:BB7) -> 3477 EPOXN//A15 | AZ7: =MID(BD7,10,10) -> 3477 EPOX | BA7: =LEFT(BE7,2)&RIGHT(BE7,2) -> N//A | BB7: =LEFT(BF7,3) -> 15 | BC7: =IFERROR(VLOOKUP(BD7&BF7,AV:AW,2,FALSE),0) -> 1034.58 | BD7: RESUPRIME 3477 EPOXY WATER PRIMER/SEALER | BE7: N/A | BF7: 15 GAL | BG7: PRIMER | BH7: CLEAR | BJ7: ACCELERA 5 66% SOLIDS 1:1 | BL7: RESUPRIME MVP EPOXY PRIMER | BM7: PRIMER
X8: JS4U-SG | Y8: 600UV Joint Filler - Standard Gray | Z8: =Table1[[#This Row],[D:D]] -> 125.4 | AA8: Box | AD8: RIO | AE8: 114 | AF8: =Table1[[#This Row],[C:C]]*1.1 -> 125.4 | AI8: =IFERROR(VLOOKUP(X8,#REF!,8,FALSE),0) -> 0 | AN8: =PROD_ID_TABLE[[#This Row],[PROD ID]] -> 3504 HIGHCLAR2 G | AO8: =_xlfn.CONCAT(BD8:BF8) -> RESUPRIME 3504 HIGH SOLID CLEAR PRIMER/SEALERCLEAR2 GAL | AP8: =BC8 -> 168.31 | AQ8: =BF8 -> 2 GAL | AS8: =BE8 -> CLEAR | AT8: RESUPRIME 3579 HIGH SOLID EPOXY PRIMER/BINDER | AU8: 3 GAL | AV8: =AT8&AU8 -> RESUPRIME 3579 HIGH SOLID EPOXY PRIMER/BINDER3 GAL | AW8: 187.14 | AY8: =_xlfn.CONCAT(AZ8:BB8) -> 3504 HIGHCLAR2 G | AZ8: =MID(BD8,10,10) -> 3504 HIGH | BA8: =LEFT(BE8,2)&RIGHT(BE8,2) -> CLAR | BB8: =LEFT(BF8,3) -> 2 G | BC8: =IFERROR(VLOOKUP(BD8&BF8,AV:AW,2,FALSE),0) -> 168.31 | BD8: RESUPRIME 3504 HIGH SOLID CLEAR PRIMER/SEALER | BE8: CLEAR | BF8: 2 GAL | BG8: PRIMER | BH8: GRAY | BM8: PRIMER
B9: =SUM(B2:B8) -> 0 | C9: =SUM(C2:C8) -> 0 | D9: =SUM(D2:D8) -> 0 | E9: =SUM(E2:E8) -> 0 | F9: =SUM(F2:F8) -> 0 | G9: =SUM(G2:G8) -> 0 | H9: =SUM(H2:H8) -> 0 | I9: =SUM(I2:I8) -> 0 | ... V9: =SUM(V2:V8) -> 0 | X9: R-EMP-15 | Y9: RIO Coat EMP | Z9: =Table1[[#This Row],[D:D]] -> 973.5 | AA9: 15 gal | AD9: RIO | AE9: 885 | AF9: =Table1[[#This Row],[C:C]]*1.1 -> 973.5 | AI9: =IFERROR(VLOOKUP(X9,#REF!,8,FALSE),0) -> 0 | AN9: =PROD_ID_TABLE[[#This Row],[PROD ID]] -> 3504 HIGHGRAY2 G | AO9: =_xlfn.CONCAT(BD9:BF9) -> RESUPRIME 3504 HIGH SOLID CLEAR PRIMER/SEALERGRAY2 GAL | AP9: =BC9 -> 168.31 | AQ9: =BF9 -> 2 GAL | AS9: =BE9 -> GRAY | AT9: RESUPRIME 3579 HIGH SOLID EPOXY PRIMER/BINDER | AU9: 15 GAL | AV9: =AT9&AU9 -> RESUPRIME 3579 HIGH SOLID EPOXY PRIMER/BINDER15 GAL | AW9: 873.92 | AY9: =_xlfn.CONCAT(AZ9:BB9) -> 3504 HIGHGRAY2 G | AZ9: =MID(BD9,10,10) -> 3504 HIGH | BA9: =LEFT(BE9,2)&RIGHT(BE9,2) -> GRAY | BB9: =LEFT(BF9,3) -> 2 G | BC9: =IFERROR(VLOOKUP(BD9&BF9,AV:AW,2,FALSE),0) -> 168.31 | BD9: RESUPRIME 3504 HIGH SOLID CLEAR PRIMER/SEALER | BE9: GRAY | BF9: 2 GAL | BG9: PRIMER | BH9: WHITE
N10: 5-100 RETURN FREIGHT | X10: R-EMP-3 | Y10: RIO Coat EMP | Z10: =Table1[[#This Row],[D:D]] -> 194.7 | AA10: 3 gal kit | AD10: RIO | AE10: 177 | AF10: =Table1[[#This Row],[C:C]]*1.1 -> 194.7 | AI10: =IFERROR(VLOOKUP(X10,#REF!,8,FALSE),0) -> 0 | AN10: =PROD_ID_TABLE[[#This Row],[PROD ID]] -> 3504 HIGHWHTE2 G | AO10: =_xlfn.CONCAT(BD10:BF10) -> RESUPRIME 3504 HIGH SOLID CLEAR PRIMER/SEALERWHITE2 GAL | AP10: =BC10 -> 168.31 | AQ10: =BF10 -> 2 GAL | AS10: =BE10 -> WHITE | AT10: RESUPRIME 3831 MVB MOISTURE EPOXY PRIMER | AU10: 2 GAL | AV10: =AT10&AU10 -> RESUPRIME 3831 MVB MOISTURE EPOXY PRIMER2 GAL | AW10: 135.36 | AY10: =_xlfn.CONCAT(AZ10:BB10) -> 3504 HIGHWHTE2 G | AZ10: =MID(BD10,10,10) -> 3504 HIGH | BA10: =LEFT(BE10,2)&RIGHT(BE10,2) -> WHTE | BB10: =LEFT(BF10,3) -> 2 G | BC10: =IFERROR(VLOOKUP(BD10&BF10,AV:AW,2,FALSE),0) -> 168.31 | BD10: RESUPRIME 3504 HIGH SOLID CLEAR PRIMER/SEALER | BE10: WHITE | BF10: 2 GAL | BG10: PRIMER | BH10: BLACK
X11: NP-1 | Y11: NP-1 Tubes | Z11: =Table1[[#This Row],[D:D]] -> 9.174 | AA11: Tube | AC11: Aluminum Gray | AD11: RIO | AE11: 8.34 | AF11: =Table1[[#This Row],[C:C]]*1.1 -> 9.174 | AI11: =IFERROR(VLOOKUP(X11,#REF!,8,FALSE),0) -> 0 | AN11: =PROD_ID_TABLE[[#This Row],[PROD ID]] -> 3504 HIGHCLAR10 | AO11: =_xlfn.CONCAT(BD11:BF11) -> RESUPRIME 3504 HIGH SOLID CLEAR PRIMER/SEALERCLEAR10 GAL | AP11: =BC11 -> 800.36 | AQ11: =BF11 -> 10 GAL | AS11: =BE11 -> CLEAR | AT11: RESUPRIME 3831 MVB MOISTURE EPOXY PRIMER | AU11: 10 GAL | AV11: =AT11&AU11 -> RESUPRIME 3831 MVB MOISTURE EPOXY PRIMER10 GAL | AW11: 641.47 | AY11: =_xlfn.CONCAT(AZ11:BB11) -> 3504 HIGHCLAR10 | AZ11: =MID(BD11,10,10) -> 3504 HIGH | BA11: =LEFT(BE11,2)&RIGHT(BE11,2) -> CLAR | BB11: =LEFT(BF11,3) -> 10 | BC11: =IFERROR(VLOOKUP(BD11&BF11,AV:AW,2,FALSE),0) -> 800.36 | BD11: RESUPRIME 3504 HIGH SOLID CLEAR PRIMER/SEALER | BE11: CLEAR | BF11: 10 GAL | BG11: PRIMER | BH11: TILE RED
X12: R-A60-1 | Y12: #60 Grit Clear White Alu Oxide | Z12: =Table1[[#This Row],[D:D]] -> 198 | AA12: Bag | AD12: RIO | AE12: 180 | AF12: =Table1[[#This Row],[C:C]]*1.1 -> 198 | AI12: =IFERROR(VLOOKUP(X12,#REF!,8,FALSE),0) -> 0 | AN12: =PROD_ID_TABLE[[#This Row],[PROD ID]] -> 3504 HIGHGRAY10 | AO12: =_xlfn.CONCAT(BD12:BF12) -> RESUPRIME 3504 HIGH SOLID CLEAR PRIMER/SEALERGRAY10 GAL | AP12: =BC12 -> 800.36 | AQ12: =BF12 -> 10 GAL | AS12: =BE12 -> GRAY | AT12: RESUPRIME MVP EPOXY PRIMER | AU12: 3 GAL | AV12: =AT12&AU12 -> RESUPRIME MVP EPOXY PRIMER3 GAL | AW12: 421.2 | AY12: =_xlfn.CONCAT(AZ12:BB12) -> 3504 HIGHGRAY10 | AZ12: =MID(BD12,10,10) -> 3504 HIGH | BA12: =LEFT(BE12,2)&RIGHT(BE12,2) -> GRAY | BB12: =LEFT(BF12,3) -> 10 | BC12: =IFERROR(VLOOKUP(BD12&BF12,AV:AW,2,FALSE),0) -> 800.36 | BD12: RESUPRIME 3504 HIGH SOLID CLEAR PRIMER/SEALER | BE12: GRAY | BF12: 10 GAL | BG12: PRIMER | BH12: CONCRETE GRAY
A13: DESCRIPTION - EPOXY | B13: DESCRIPTION - POLY | C13: DESCRIPTION - AGG | D13: DESCRIPTION - MMA | E13: DESCRIPTION - JOINT | F13: DESCRIPTION - CRETE | G13: DESCRIPTION - COLOR | I13: PROD ID | J13: LOOKUP | K13: DESCRIPTION | L13: COLOR | M13: UOM | X13: R-CBG-1 | Y13: RIO Battleship Gray | Z13: =Table1[[#This Row],[D:D]] -> 28.05 | AA13: Pint | AD13: RIO | AE13: 25.5 | AF13: =Table1[[#This Row],[C:C]]*1.1 -> 28.05 | AI13: =IFERROR(VLOOKUP(X13,#REF!,8,FALSE),0) -> 0 | AN13: =PROD_ID_TABLE[[#This Row],[PROD ID]] -> 3504 HIGHWHTE10 | AO13: =_xlfn.CONCAT(BD13:BF13) -> RESUPRIME 3504 HIGH SOLID CLEAR PRIMER/SEALERWHITE10 GAL | AP13: =BC13 -> 800.36 | AQ13: =BF13 -> 10 GAL | AS13: =BE13 -> WHITE | AT13: RESUPRIME MVP EPOXY PRIMER | AU13: 15 GAL | AV13: =AT13&AU13 -> RESUPRIME MVP EPOXY PRIMER15 GAL | AW13: 1787.4 | AY13: =_xlfn.CONCAT(AZ13:BB13) -> 3504 HIGHWHTE10 | AZ13: =MID(BD13,10,10) -> 3504 HIGH | BA13: =LEFT(BE13,2)&RIGHT(BE13,2) -> WHTE | BB13: =LEFT(BF13,3) -> 10 | BC13: =IFERROR(VLOOKUP(BD13&BF13,AV:AW,2,FALSE),0) -> 800.36 | BD13: RESUPRIME 3504 HIGH SOLID CLEAR PRIMER/SEALER | BE13: WHITE | BF13: 10 GAL | BG13: PRIMER
A14: SGC DECK BASE COAT 308 | B14: SGC POLYASPARTIC (100% Solid) | C14: FLAKE | D14: SGC SHIELD BODY COAT | E14: NP-1 TUBES (30 TUBE/CASE) | F14: SGC CRETE PART A | G14: POLYASPARTIC COLORANT | I14: S-DEB-5 | J14: =_xlfn.CONCAT(K14:M14) -> SGC DECK BASE COAT 308N/A5 GAL | K14: SGC DECK BASE COAT 308 | L14: N/A | M14: 5 GAL | X14: R-CBG-25 | Y14: RIO Battleship Gray | Z14: =Table1[[#This Row],[D:D]] -> 514.25 | AA14: 25 Pint | AD14: RIO | AE14: 467.5 | AF14: =Table1[[#This Row],[C:C]]*1.1 -> 514.25 | AI14: =IFERROR(VLOOKUP(X14,#REF!,8,FALSE),0) -> 0 | AN14: =PROD_ID_TABLE[[#This Row],[PROD ID]] -> 3579 HIGHCOAY3 G | AO14: =_xlfn.CONCAT(BD14:BF14) -> RESUPRIME 3579 HIGH SOLID EPOXY PRIMER/BINDERCONCRETE GRAY3 GAL | AP14: =BC14 -> 187.14 | AQ14: =BF14 -> 3 GAL | AS14: =BE14 -> CONCRETE GRAY | AT14: RESUPRIME 5531 OIL STOP PRIMER | AU14: 1 QT | AV14: =AT14&AU14 -> RESUPRIME 5531 OIL STOP PRIMER1 QT | AW14: 48.26 | AY14: =_xlfn.CONCAT(AZ14:BB14) -> 3579 HIGHCOAY3 G | AZ14: =MID(BD14,10,10) -> 3579 HIGH | BA14: =LEFT(BE14,2)&RIGHT(BE14,2) -> COAY | BB14: =LEFT(BF14,3) -> 3 G | BC14: =IFERROR(VLOOKUP(BD14&BF14,AV:AW,2,FALSE),0) -> 187.14 | BD14: RESUPRIME 3579 HIGH SOLID EPOXY PRIMER/BINDER | BE14: CONCRETE GRAY | BF14: 3 GAL | BG14: PRIMER | BH14: 2 GAL
A15: SGC SHIELD FLEX | C15: QUARTZ | D15: SGC SHIELD TOP COAT | E15: 600 UV (SSP JS-600 ALIPHATIC POLYUREA) | F15: SGC CRETE PART B | G15: CRETE COLORANT | I15: S-GPR-3 | J15: =_xlfn.CONCAT(K15:M15) -> SGC SHIELD FLEXN/A3 GAL | K15: SGC SHIELD FLEX | L15: N/A | M15: 3 GAL | X15: R-CBK-1 | Y15: RIO Black Colorant | Z15: =Table1[[#This Row],[D:D]] -> 30.855 | AA15: Pint | AD15: RIO | AE15: 28.05 | AF15: =Table1[[#This Row],[C:C]]*1.1 -> 30.855 | AI15: =IFERROR(VLOOKUP(X15,#REF!,8,FALSE),0) -> 0 | AN15: =PROD_ID_TABLE[[#This Row],[PROD ID]] -> 3579 HIGHWHTE3 G | AO15: =_xlfn.CONCAT(BD15:BF15) -> RESUPRIME 3579 HIGH SOLID EPOXY PRIMER/BINDERWHITE3 GAL | AP15: =BC15 -> 187.14 | AQ15: =BF15 -> 3 GAL | AS15: =BE15 -> WHITE | AT15: RESUPRIME 5531 OIL STOP PRIMER | AU15: 5 GAL | AV15: =AT15&AU15 -> RESUPRIME 5531 OIL STOP PRIMER5 GAL | AW15: 123 | AY15: =_xlfn.CONCAT(AZ15:BB15) -> 3579 HIGHWHTE3 G | AZ15: =MID(BD15,10,10) -> 3579 HIGH | BA15: =LEFT(BE15,2)&RIGHT(BE15,2) -> WHTE | BB15: =LEFT(BF15,3) -> 3 G | BC15: =IFERROR(VLOOKUP(BD15&BF15,AV:AW,2,FALSE),0) -> 187.14 | BD15: RESUPRIME 3579 HIGH SOLID EPOXY PRIMER/BINDER | BE15: WHITE | BF15: 3 GAL | BG15: PRIMER | BH15: 10 GAL
A16: FIBERGLASS TAPE | C16: TROWEL QUARTZ | D16: SGC BPO CATALYST | E16: RS88 (12 TUBES / CASE) | F16: SL - PART C | G16: CRETE COLORANT - LARGE | I16: FIBERTAPE | J16: =_xlfn.CONCAT(K16:M16) -> FIBERGLASS TAPEN/AROLL | K16: FIBERGLASS TAPE | L16: N/A | M16: ROLL | X16: R-CCB-1 | Y16: CB - Part C | Z16: =Table1[[#This Row],[D:D]] -> 18.359 | AA16: 28lb bag | AC16: PIGMENTED | AD16: RIO | AE16: 16.69 | AF16: =Table1[[#This Row],[C:C]]*1.1 -> 18.359 | AI16: =IFERROR(VLOOKUP(X16,#REF!,8,FALSE),0) -> 0 | AN16: =PROD_ID_TABLE[[#This Row],[PROD ID]] -> 3579 HIGHBLCK3 G | AO16: =_xlfn.CONCAT(BD16:BF16) -> RESUPRIME 3579 HIGH SOLID EPOXY PRIMER/BINDERBLACK3 GAL | AP16: =BC16 -> 187.14 | AQ16: =BF16 -> 3 GAL | AS16: =BE16 -> BLACK | AT16: POLY-CRETE TF PLUS PRIMER/TOPCOAT | AU16: KIT | AV16: =AT16&AU16 -> POLY-CRETE TF PLUS PRIMER/TOPCOATKIT | AW16: 53.55 | AY16: =_xlfn.CONCAT(AZ16:BB16) -> 3579 HIGHBLCK3 G | AZ16: =MID(BD16,10,10) -> 3579 HIGH | BA16: =LEFT(BE16,2)&RIGHT(BE16,2) -> BLCK | BB16: =LEFT(BF16,3) -> 3 G | BC16: =IFERROR(VLOOKUP(BD16&BF16,AV:AW,2,FALSE),0) -> 187.14 | BD16: RESUPRIME 3579 HIGH SOLID EPOXY PRIMER/BINDER | BE16: BLACK | BF16: 3 GAL | BG16: PRIMER | BH16: 3 GAL
A17: RIO COAT EPT | C17: ALUMINUM OXIDE | D17: SGC COAT MMA CLEANER | E17: RS65 (12 TUBES / CASE) | F17: SF - PART C | I17: R-EPT-3 | J17: =_xlfn.CONCAT(K17:M17) -> RIO COAT EPTN/A3 GAL | K17: RIO COAT EPT | L17: N/A | M17: 3 GAL | X17: R-CMG-1 | Y17: RIO Medium Gray Colorant | Z17: =Table1[[#This Row],[D:D]] -> 28.05 | AA17: Pint | AD17: RIO | AE17: 25.5 | AF17: =Table1[[#This Row],[C:C]]*1.1 -> 28.05 | AI17: =IFERROR(VLOOKUP(X17,#REF!,8,FALSE),0) -> 0 | AN17: =PROD_ID_TABLE[[#This Row],[PROD ID]] -> 3579 HIGHTIED3 G | AO17: =_xlfn.CONCAT(BD17:BF17) -> RESUPRIME 3579 HIGH SOLID EPOXY PRIMER/BINDERTILE RED3 GAL | AP17: =BC17 -> 187.14 | AQ17: =BF17 -> 3 GAL | AS17: =BE17 -> TILE RED | AT17: POLY-CRETE TF PLUS PRIMER/TOPCOAT | AU17: KIT | AV17: =AT17&AU17 -> POLY-CRETE TF PLUS PRIMER/TOPCOATKIT | AW17: 190.67 | AY17: =_xlfn.CONCAT(AZ17:BB17) -> 3579 HIGHTIED3 G | AZ17: =MID(BD17,10,10) -> 3579 HIGH | BA17: =LEFT(BE17,2)&RIGHT(BE17,2) -> TIED | BB17: =LEFT(BF17,3) -> 3 G | BC17: =IFERROR(VLOOKUP(BD17&BF17,AV:AW,2,FALSE),0) -> 187.14 | BD17: RESUPRIME 3579 HIGH SOLID EPOXY PRIMER/BINDER | BE17: TILE RED | BF17: 3 GAL | BG17: PRIMER | BH17: 15 GAL | BJ17: RESUFLOR 3500 EPOXY QUICK PATCH (FAST) | BK17: PATCH | BL17: CRYLAFLOR P-101 PRIMER | BM17: MMA | BN17: RESUFLOR 3725 STATIC CONTROL EPOXY | BO17: EPOXY
A18: ROADWARE 10 MIN CONCRETE MENDER | C18: RIO TROWEL CLAD SAND | D18: SGC MMA PRIMER | F18: CB - PART C | I18: R-EPT-15 | J18: =_xlfn.CONCAT(K18:M18) -> RIO COAT EPTN/A15 GAL | K18: RIO COAT EPT | L18: N/A | M18: 15 GAL | X18: R-CMG-25 | Y18: RIO Medium Gray Colorant | Z18: =Table1[[#This Row],[D:D]] -> 440 | AA18: 25 Pint | AD18: RIO | AE18: 400 | AF18: =Table1[[#This Row],[C:C]]*1.1 -> 440 | AI18: =IFERROR(VLOOKUP(X18,#REF!,8,FALSE),0) -> 0 | AN18: =PROD_ID_TABLE[[#This Row],[PROD ID]] -> 3579 HIGHCOAY15 | AO18: =_xlfn.CONCAT(BD18:BF18) -> RESUPRIME 3579 HIGH SOLID EPOXY PRIMER/BINDERCONCRETE GRAY15 GAL | AP18: =BC18 -> 873.92 | AQ18: =BF18 -> 15 GAL | AS18: =BE18 -> CONCRETE GRAY | AT18: POLY-CRETE SL HS SELF LEVELING URETHANE | AU18: KIT | AV18: =AT18&AU18 -> POLY-CRETE SL HS SELF LEVELING URETHANEKIT | AW18: 102.4 | AY18: =_xlfn.CONCAT(AZ18:BB18) -> 3579 HIGHCOAY15 | AZ18: =MID(BD18,10,10) -> 3579 HIGH | BA18: =LEFT(BE18,2)&RIGHT(BE18,2) -> COAY | BB18: =LEFT(BF18,3) -> 15 | BC18: =IFERROR(VLOOKUP(BD18&BF18,AV:AW,2,FALSE),0) -> 873.92 | BD18: RESUPRIME 3579 HIGH SOLID EPOXY PRIMER/BINDER | BE18: CONCRETE GRAY | BF18: 15 GAL | BG18: PRIMER | BH18: 1 QT | BJ18: RESUFLOR 3513 SCRATCH COAT MASTIC (THICK/SLOW) | BK18: PATCH | BL18: CRYLAFLOR G-201 BINDER | BM18: MMA | BN18: RESUFLOR 3741 CHEMICAL RESISTANT NOVOLAC | BO18: EPOXY
A19: RIO COAT EMP | D19: RIO MMA BONDING ADDITIVE | F19: TC - PART C | I19: ROAD10600 | J19: =_xlfn.CONCAT(K19:M19) -> ROADWARE 10 MIN CONCRETE MENDERN/A600ML | K19: ROADWARE 10 MIN CONCRETE MENDER | L19: N/A | M19: 600ML | X19: R-CRR-1 | Y19: RIO Rotunda Red Colorant | Z19: =Table1[[#This Row],[D:D]] -> 33 | AA19: Pint | AD19: RIO | AE19: 30 | AF19: =Table1[[#This Row],[C:C]]*1.1 -> 33 | AI19: =IFERROR(VLOOKUP(X19,#REF!,8,FALSE),0) -> 0 | AN19: =PROD_ID_TABLE[[#This Row],[PROD ID]] -> 3579 HIGHWHTE15 | AO19: =_xlfn.CONCAT(BD19:BF19) -> RESUPRIME 3579 HIGH SOLID EPOXY PRIMER/BINDERWHITE15 GAL | AP19: =BC19 -> 873.92 | AQ19: =BF19 -> 15 GAL | AS19: =BE19 -> WHITE | AT19: POLY-CRETE MD HS URETHANE CONCRETE COATING | AU19: KIT | AV19: =AT19&AU19 -> POLY-CRETE MD HS URETHANE CONCRETE COATINGKIT | AW19: 116.52 | AY19: =_xlfn.CONCAT(AZ19:BB19) -> 3579 HIGHWHTE15 | AZ19: =MID(BD19,10,10) -> 3579 HIGH | BA19: =LEFT(BE19,2)&RIGHT(BE19,2) -> WHTE | BB19: =LEFT(BF19,3) -> 15 | BC19: =IFERROR(VLOOKUP(BD19&BF19,AV:AW,2,FALSE),0) -> 873.92 | BD19: RESUPRIME 3579 HIGH SOLID EPOXY PRIMER/BINDER | BE19: WHITE | BF19: 15 GAL | BG19: PRIMER | BH19: 5 GAL | BJ19: CEMLACK UM. URETHANE CEMENT PATCH 1:1:1 | BK19: PATCH | BL19: CRYLAFLOR T-301 TOPCOAT | BM19: MMA | BN19: RESUFLOR 3746 HIGH PERFORMANCE EPOXY | BO19: EPOXY
F20: SGC SPEED | I20: S-SPS-2.5 | J20: =_xlfn.CONCAT(K20:M20) -> SGC POLYASPARTIC (100% Solid)N/A2.5 GAL | K20: SGC POLYASPARTIC (100% Solid) | L20: N/A | M20: 2.5 GAL | X20: R-CSB-1 | Y20: RIO Sandy Beige Colorant | Z20: =Table1[[#This Row],[D:D]] -> 28.05 | AA20: Pint | AD20: RIO | AE20: 25.5 | AF20: =Table1[[#This Row],[C:C]]*1.1 -> 28.05 | AI20: =IFERROR(VLOOKUP(X20,#REF!,8,FALSE),0) -> 0 | AN20: =PROD_ID_TABLE[[#This Row],[PROD ID]] -> 3579 HIGHBLCK15 | AO20: =_xlfn.CONCAT(BD20:BF20) -> RESUPRIME 3579 HIGH SOLID EPOXY PRIMER/BINDERBLACK15 GAL | AP20: =BC20 -> 873.92 | AQ20: =BF20 -> 15 GAL | AS20: =BE20 -> BLACK | AT20: POLY-CRETE TF PLUS COVE VERTICAL APPLICATIONS | AU20: KIT | AV20: =AT20&AU20 -> POLY-CRETE TF PLUS COVE VERTICAL APPLICATIONSKIT | AW20: 31.8 | AY20: =_xlfn.CONCAT(AZ20:BB20) -> 3579 HIGHBLCK15 | AZ20: =MID(BD20,10,10) -> 3579 HIGH | BA20: =LEFT(BE20,2)&RIGHT(BE20,2) -> BLCK | BB20: =LEFT(BF20,3) -> 15 | BC20: =IFERROR(VLOOKUP(BD20&BF20,AV:AW,2,FALSE),0) -> 873.92 | BD20: RESUPRIME 3579 HIGH SOLID EPOXY PRIMER/BINDER | BE20: BLACK | BF20: 15 GAL | BG20: PRIMER | BJ20: HPF UNIVERSAL COLORANT | BK20: PATCH | BL20: CRYLAFLOR T-303 FLEXIBLE TOPCOAT | BM20: MMA | BN20: RESUFLOR 3760 MPE MULTI-PURPOSE EPOXY | BO20: EPOXY
I21: S-SPS-25 | J21: =_xlfn.CONCAT(K21:M21) -> SGC POLYASPARTIC (100% Solid)N/A25 GAL | K21: SGC POLYASPARTIC (100% Solid) | L21: N/A | M21: 25 GAL | X21: R-CSF-1 | Y21: SF - Part C | Z21: =Table1[[#This Row],[D:D]] -> 11.825 | AA21: 35lb bag | AD21: RIO | AE21: 10.75 | AF21: =Table1[[#This Row],[C:C]]*1.1 -> 11.825 | AI21: =IFERROR(VLOOKUP(X21,#REF!,8,FALSE),0) -> 0 | AN21: =PROD_ID_TABLE[[#This Row],[PROD ID]] -> 3831 MVB N//A2 G | AO21: =_xlfn.CONCAT(BD21:BF21) -> RESUPRIME 3831 MVB MOISTURE EPOXY PRIMERN/A2 GAL | AP21: =BC21 -> 135.36 | AQ21: =BF21 -> 2 GAL | AS21: =BE21 -> N/A | AT21: POLY-CRETE HF HS URETHANE CONCRETE COATING | AU21: KIT | AV21: =AT21&AU21 -> POLY-CRETE HF HS URETHANE CONCRETE COATINGKIT | AW21: 79.45 | AY21: =_xlfn.CONCAT(AZ21:BB21) -> 3831 MVB N//A2 G | AZ21: =MID(BD21,10,10) -> 3831 MVB | BA21: =LEFT(BE21,2)&RIGHT(BE21,2) -> N//A | BB21: =LEFT(BF21,3) -> 2 G | BC21: =IFERROR(VLOOKUP(BD21&BF21,AV:AW,2,FALSE),0) -> 135.36 | BD21: RESUPRIME 3831 MVB MOISTURE EPOXY PRIMER | BE21: N/A | BF21: 2 GAL | BG21: PRIMER | BL21: CRYLAFLOR COVE | BM21: MMA | BN21: RESUFLOR AQUA 3460 WB EPOXY PRIMER, BINDER, TOPCOAT | BO21: EPOXY
I22: S-QBS-1 | J22: =_xlfn.CONCAT(K22:M22) -> FLAKEASH40LB | K22: FLAKE | L22: ASH | M22: 40LB | X22: R-CSL-1 | Y22: SL - Part C | Z22: =Table1[[#This Row],[D:D]] -> 8.338 | AA22: 20lb bag | AD22: RIO | AE22: 7.58 | AF22: =Table1[[#This Row],[C:C]]*1.1 -> 8.338 | AI22: =IFERROR(VLOOKUP(X22,#REF!,8,FALSE),0) -> 0 | AN22: =PROD_ID_TABLE[[#This Row],[PROD ID]] -> 3831 MVB N//A10 | AO22: =_xlfn.CONCAT(BD22:BF22) -> RESUPRIME 3831 MVB MOISTURE EPOXY PRIMERN/A10 GAL | AP22: =BC22 -> 641.47 | AQ22: =BF22 -> 10 GAL | AS22: =BE22 -> N/A | AT22: POLY-CRETE COLOR-FAST | AU22: KIT | AV22: =AT22&AU22 -> POLY-CRETE COLOR-FASTKIT | AW22: 154.78 | AY22: =_xlfn.CONCAT(AZ22:BB22) -> 3831 MVB N//A10 | AZ22: =MID(BD22,10,10) -> 3831 MVB | BA22: =LEFT(BE22,2)&RIGHT(BE22,2) -> N//A | BB22: =LEFT(BF22,3) -> 10 | BC22: =IFERROR(VLOOKUP(BD22&BF22,AV:AW,2,FALSE),0) -> 641.47 | BD22: RESUPRIME 3831 MVB MOISTURE EPOXY PRIMER | BE22: N/A | BF22: 10 GAL | BG22: PRIMER | BL22: CRYLAFLOR CURE (BPO) | BM22: MMA | BN22: RESUFLOR AQUA 3461 HIGH SOLIDS WB EPOXY GROUT/TOPCOAT | BO22: EPOXY
I23: S-QMT-1 | J23: =_xlfn.CONCAT(K23:M23) -> QUARTZMALT50LB | K23: QUARTZ | L23: MALT | M23: 50LB | X23: R-CTC-1 | Y23: TC - Part C | Z23: =Table1[[#This Row],[D:D]] -> 11.22 | AA23: 6.5 lb bag | AC23: PIGMENTED | AD23: RIO | AE23: 10.2 | AF23: =Table1[[#This Row],[C:C]]*1.1 -> 11.22 | AI23: =IFERROR(VLOOKUP(X23,#REF!,8,FALSE),0) -> 0 | AN23: =PROD_ID_TABLE[[#This Row],[PROD ID]] -> MVP EPOXYN//A3 G | AO23: =_xlfn.CONCAT(BD23:BF23) -> RESUPRIME MVP EPOXY PRIMERN/A3 GAL | AP23: =BC23 -> 421.2 | AQ23: =BF23 -> 3 GAL | AS23: =BE23 -> N/A | AT23: POLY-CRETE COLOR-FAST | AU23: KIT | AV23: =AT23&AU23 -> POLY-CRETE COLOR-FASTKIT | AW23: 264.24 | AY23: =_xlfn.CONCAT(AZ23:BB23) -> MVP EPOXYN//A3 G | AZ23: =MID(BD23,10,10) -> MVP EPOXY | BA23: =LEFT(BE23,2)&RIGHT(BE23,2) -> N//A | BB23: =LEFT(BF23,3) -> 3 G | BC23: =IFERROR(VLOOKUP(BD23&BF23,AV:AW,2,FALSE),0) -> 421.2 | BD23: RESUPRIME MVP EPOXY PRIMER | BE23: N/A | BF23: 3 GAL | BG23: PRIMER | BI23: {=IF(B3="","",IF(B3=P!BL3,P!BE$8:BE$10,IF(B3=P!BL$4,P!BE$14:BE$17,P!BE$6)))} -> N/A | BL23: CRYLAFLOR COLOR - BACKGROUND ONLY | BM23: MMA | BN23: RESUTILE 4638 HS POLYURETHANE FLOOR ENAMEL
I24: S-QSM-1 | J24: =_xlfn.CONCAT(K24:M24) -> QUARTZGRAY50LB | K24: QUARTZ | L24: GRAY | M24: 50LB | X24: R-CTR-1 | Y24: RIO Tile Red Colorant | Z24: =Table1[[#This Row],[D:D]] -> 28.05 | AA24: Pint | AD24: RIO | AE24: 25.5 | AF24: =Table1[[#This Row],[C:C]]*1.1 -> 28.05 | AI24: =IFERROR(VLOOKUP(X24,#REF!,8,FALSE),0) -> 0 | AN24: =PROD_ID_TABLE[[#This Row],[PROD ID]] -> MVP EPOXYN//A15 | AO24: =_xlfn.CONCAT(BD24:BF24) -> RESUPRIME MVP EPOXY PRIMERN/A15 GAL | AP24: =BC24 -> 1787.4 | AQ24: =BF24 -> 15 GAL | AS24: =BE24 -> N/A | AT24: POLY-CRETE WR COVE BASE, SLOPE/PATCHING | AU24: KIT | AV24: =AT24&AU24 -> POLY-CRETE WR COVE BASE, SLOPE/PATCHINGKIT | AW24: 57.67 | AY24: =_xlfn.CONCAT(AZ24:BB24) -> MVP EPOXYN//A15 | AZ24: =MID(BD24,10,10) -> MVP EPOXY | BA24: =LEFT(BE24,2)&RIGHT(BE24,2) -> N//A | BB24: =LEFT(BF24,3) -> 15 | BC24: =IFERROR(VLOOKUP(BD24&BF24,AV:AW,2,FALSE),0) -> 1787.4 | BD24: RESUPRIME MVP EPOXY PRIMER | BE24: N/A | BF24: 15 GAL | BG24: PRIMER | BI24: {=IF(B3="","",IF(B3=$BL$3,$BE$8:$BE$10,IF(B3=$BL$4,$BE$14:$BE$17,$BE$6)))} -> N/A | BL24: CRYLAFLOR BOND ENHANCER TO P-101 | BM24: MMA | BN24: RESUFLOR PT 250 THICKENED EPOXY 2:1
I25: S-QSA-1 | J25: =_xlfn.CONCAT(K25:M25) -> QUARTZASH50LB | K25: QUARTZ | L25: ASH | M25: 50LB | X25: R-CYL-1 | Y25: RIO Yellow Colorant | Z25: =Table1[[#This Row],[D:D]] -> 28.05 | AA25: Pint | AD25: RIO | AE25: 25.5 | AF25: =Table1[[#This Row],[C:C]]*1.1 -> 28.05 | AI25: =IFERROR(VLOOKUP(X25,#REF!,8,FALSE),0) -> 0 | AN25: =PROD_ID_TABLE[[#This Row],[PROD ID]] -> 5531 OIL N//A1 Q | AO25: =_xlfn.CONCAT(BD25:BF25) -> RESUPRIME 5531 OIL STOP PRIMERN/A1 QT | AP25: =BC25 -> 48.26 | AQ25: =BF25 -> 1 QT | AS25: =BE25 -> N/A | AT25: POLY-CRETE HF ACCELERATOR LOW TEMPERATURE AID | AU25: 1 Qt | AV25: =AT25&AU25 -> POLY-CRETE HF ACCELERATOR LOW TEMPERATURE AID1 Qt | AW25: 43.8 | AY25: =_xlfn.CONCAT(AZ25:BB25) -> 5531 OIL N//A1 Q | AZ25: =MID(BD25,10,10) -> 5531 OIL | BA25: =LEFT(BE25,2)&RIGHT(BE25,2) -> N//A | BB25: =LEFT(BF25,3) -> 1 Q | BC25: =IFERROR(VLOOKUP(BD25&BF25,AV:AW,2,FALSE),0) -> 48.26 | BD25: RESUPRIME 5531 OIL STOP PRIMER | BE25: N/A | BF25: 1 QT | BG25: PRIMER | BI25: {=IF(B22="","",IF(B22=P!$BD$2,P!$BE$2,P!$BE$4:$BE$5))} | BL25: CRYLAFLOR SL FILLER BLEND TO G-201 | BM25: MMA | BN25: GP 3555 EPOFLEX 1:1
I26: S-QST-1 | J26: =_xlfn.CONCAT(K26:M26) -> TROWEL QUARTZGRAY50LB | K26: TROWEL QUARTZ | L26: GRAY | M26: 50LB | X26: R-EPT-15 | Y26: RIO Coat EPT 15 Gal Kit | Z26: =Table1[[#This Row],[D:D]] -> 825 | AA26: 15 gal | AD26: RIO | AE26: 750 | AF26: =Table1[[#This Row],[C:C]]*1.1 -> 825 | AI26: =IFERROR(VLOOKUP(X26,#REF!,8,FALSE),0) -> 0 | AN26: =PROD_ID_TABLE[[#This Row],[PROD ID]] -> 5531 OIL N//A5 G | AO26: =_xlfn.CONCAT(BD26:BF26) -> RESUPRIME 5531 OIL STOP PRIMERN/A5 GAL | AP26: =BC26 -> 123 | AQ26: =BF26 -> 5 GAL | AS26: =BE26 -> N/A | AT26: CRYLAFLOR BOND ENHANCER TO P-101 | AU26: KIT | AV26: =AT26&AU26 -> CRYLAFLOR BOND ENHANCER TO P-101KIT | AW26: 30 | AY26: =_xlfn.CONCAT(AZ26:BB26) -> 5531 OIL N//A5 G | AZ26: =MID(BD26,10,10) -> 5531 OIL | BA26: =LEFT(BE26,2)&RIGHT(BE26,2) -> N//A | BB26: =LEFT(BF26,3) -> 5 G | BC26: =IFERROR(VLOOKUP(BD26&BF26,AV:AW,2,FALSE),0) -> 123 | BD26: RESUPRIME 5531 OIL STOP PRIMER | BE26: N/A | BF26: 5 GAL | BG26: PRIMER | BH26: CRETE | BL26: CRYLAFLOR BOND MT METAL/TILE ENHANCER | BM26: MMA | BN26: RESUFLOR 3760 RCE RAPID CURE EPOXY
I27: S-AST-1 | J27: =_xlfn.CONCAT(K27:M27) -> TROWEL QUARTZASH50LB | K27: TROWEL QUARTZ | L27: ASH | M27: 50LB | X27: R-EPT-3 | Y27: RIO Coat EPT 3 Gal Kit | Z27: =Table1[[#This Row],[D:D]] -> 198 | AA27: 3 gal kit | AD27: RIO | AE27: 180 | AF27: =Table1[[#This Row],[C:C]]*1.1 -> 198 | AI27: =IFERROR(VLOOKUP(X27,#REF!,8,FALSE),0) -> 0 | AN27: E TF PLUS BLUE1.7 | AO27: =_xlfn.CONCAT(BD27:BF27) -> POLY-CRETE TF PLUS PRIMER/TOPCOATBLUEKIT | AP27: =BC27 -> 53.55 | AQ27: =BF27 -> KIT | AS27: =BE27 -> BLUE | AT27: CRYLAFLOR P-101 PRIMER | AU27: 5 GAL KIT | AV27: =AT27&AU27 -> CRYLAFLOR P-101 PRIMER5 GAL KIT | AW27: 323 | AY27: =_xlfn.CONCAT(AZ27:BB27) -> E TF PLUS BLUEKIT | AZ27: =MID(BD27,10,10) -> E TF PLUS | BA27: =LEFT(BE27,2)&RIGHT(BE27,2) -> BLUE | BB27: =LEFT(BF27,3) -> KIT | BC27: =IFERROR(VLOOKUP(BD27&BF27,AV:AW,2,FALSE),0) -> 53.55 | BD27: POLY-CRETE TF PLUS PRIMER/TOPCOAT | BE27: BLUE | BF27: KIT | BG27: CRETE | BH27: BLUE | BL27: CRYLAFLOR LTC ADDITIVE LOW TEMPERATURE | BM27: MMA
C28: {=_xlfn.SWITCH(SGC!M23,P!$C$17,P!$C$12,P!$C$14,P!$L$22,P!$C$15,P!$L$23:$L$25,P!$C$16,P!$L$26:$L$27)} -> ASH | D28: {=_xlfn.SWITCH(SGC!M38,P!$D$14,P!$M$44:$M$45,P!$D$15,P!$M$46:$M$47,P!$D$16,P!$M$33,P!$D$17,P!$M$34,P!$D$18,P!$M$35,P!$D$19,P!$M$36)} -> 5 GAL | E28: {=_xlfn.SWITCH(SGC!M58,P!$E$14,P!$L$37,P!$E$15,P!$L$38:$L$40,P!$E$16,P!$L$41:$L$43)} -> #N/A | F28: {=_xlfn.SWITCH(K3,P!$F$14,P!$M$44:$M$45,P!$F$15,P!$M$46:$M$47,P!$F$16,P!$M$48,P!$F$17,P!$M$49,P!$F$18,P!$M$50,P!$F$19,P!$M$51,P!$F$20,P!$M$52)} -> #N/A | G28: {=_xlfn.SWITCH(B21,P!$G$14,P!$L$53:$L$54,P!$G$15,P!$L$55:$L$63,P!$G$16,P!$L$64:$L$68)} -> #N/A | I28: R-A60-1 | J28: =_xlfn.CONCAT(K28:M28) -> ALUMINUM OXIDE60#50LB | K28: ALUMINUM OXIDE | L28: 60# | M28: 50LB | X28: R-ETM-C50 | Y28: RIO Trowel Clad Sand | Z28: =Table1[[#This Row],[D:D]] -> 19.8 | AA28: 50lb bag | AD28: RIO | AE28: 18 | AF28: =Table1[[#This Row],[C:C]]*1.1 -> 19.8 | AI28: =IFERROR(VLOOKUP(X28,#REF!,8,FALSE),0) -> 0 | AN28: E TF PLUS CHAL1.7 | AO28: =_xlfn.CONCAT(BD28:BF28) -> POLY-CRETE TF PLUS PRIMER/TOPCOATCHARCOALKIT | AP28: =BC28 -> 53.55 | AQ28: =BF28 -> KIT | AS28: =BE28 -> CHARCOAL | AT28: CRYLAFLOR G-201 BINDER | AU28: 5 GAL KIT | AV28: =AT28&AU28 -> CRYLAFLOR G-201 BINDER5 GAL KIT | AW28: 341.92 | AY28: =_xlfn.CONCAT(AZ28:BB28) -> E TF PLUS CHALKIT | AZ28: =MID(BD28,10,10) -> E TF PLUS | BA28: =LEFT(BE28,2)&RIGHT(BE28,2) -> CHAL | BB28: =LEFT(BF28,3) -> KIT | BC28: =IFERROR(VLOOKUP(BD28&BF28,AV:AW,2,FALSE),0) -> 53.55 | BD28: POLY-CRETE TF PLUS PRIMER/TOPCOAT | BE28: CHARCOAL | BF28: KIT | BG28: CRETE | BH28: CHARCOAL | BL28: CRYLAFLOR CLEAN SOLVENT TO CLEAN TOOLS | BM28: MMA
A29: {=_xlfn.SWITCH(SGC!C6,P!$A$14,P!$M$14,P!$A$15,P!$M$15,P!$A$16,P!$M$16,P!$A$17,P!$M$17:$M$18,P!$A$18,P!$M$19)} -> 5 GAL | B29: {=_xlfn.IFS(SGC!C38=P!$B$14,P!$M$20:$M$21)} -> 2.5 GAL | C29: =IF(SGC!M23=P!$C$14,P!$M$22,P!$M$23) -> 40LB | D29: 50 GAL | F29: CLEAR | G29: =IF(SGC!C23=P!$G$16,P!$M$64,P!$M$53) -> PINT | I29: R-MMB-5 | J29: =_xlfn.CONCAT(K29:M29) -> SGC SHIELD BODY COATN/A5 GAL | K29: SGC SHIELD BODY COAT | L29: N/A | M29: 5 GAL | X29: R-MBP-10 | Y29: SGC MMA BPO Catalyst 10 lbs | Z29: =Table1[[#This Row],[D:D]] -> 264 | AA29: 10lb box | AD29: RIO | AE29: 240 | AF29: =Table1[[#This Row],[C:C]]*1.1 -> 264 | AI29: =IFERROR(VLOOKUP(X29,#REF!,8,FALSE),0) -> 0 | AN29: E TF PLUS CHUT1.7 | AO29: =_xlfn.CONCAT(BD29:BF29) -> POLY-CRETE TF PLUS PRIMER/TOPCOATCHESTNUTKIT | AP29: =BC29 -> 53.55 | AQ29: =BF29 -> KIT | AS29: =BE29 -> CHESTNUT | AT29: CRYLAFLOR T-301 TOPCOAT | AU29: 5 GAL KIT | AV29: =AT29&AU29 -> CRYLAFLOR T-301 TOPCOAT5 GAL KIT | AW29: 329.56 | AY29: =_xlfn.CONCAT(AZ29:BB29) -> E TF PLUS CHUTKIT | AZ29: =MID(BD29,10,10) -> E TF PLUS | BA29: =LEFT(BE29,2)&RIGHT(BE29,2) -> CHUT | BB29: =LEFT(BF29,3) -> KIT | BC29: =IFERROR(VLOOKUP(BD29&BF29,AV:AW,2,FALSE),0) -> 53.55 | BD29: POLY-CRETE TF PLUS PRIMER/TOPCOAT | BE29: CHESTNUT | BF29: KIT | BG29: CRETE | BH29: CHESTNUT
B30: 25 GAL | F30: PIGMENTED | I30: R-MMB-50 | J30: =_xlfn.CONCAT(K30:M30) -> SGC SHIELD BODY COATN/A50 GAL | K30: SGC SHIELD BODY COAT | L30: N/A | M30: 50 GAL | X30: R-MMA-5 | Y30: RIO MMA Bonding Additive | Z30: =Table1[[#This Row],[D:D]] -> 341 | AA30: 5 gal | AD30: RIO | AE30: 310 | AF30: =Table1[[#This Row],[C:C]]*1.1 -> 341 | AI30: =IFERROR(VLOOKUP(X30,#REF!,8,FALSE),0) -> 0 | AN30: E TF PLUS COAY1.7 | AO30: =_xlfn.CONCAT(BD30:BF30) -> POLY-CRETE TF PLUS PRIMER/TOPCOATCONCRETE GRAYKIT | AP30: =BC30 -> 53.55 | AQ30: =BF30 -> KIT | AS30: =BE30 -> CONCRETE GRAY | AT30: CRYLAFLOR T-303 FLEXIBLE TOPCOAT | AU30: 5 GAL KIT | AV30: =AT30&AU30 -> CRYLAFLOR T-303 FLEXIBLE TOPCOAT5 GAL KIT | AW30: 424.9 | AY30: =_xlfn.CONCAT(AZ30:BB30) -> E TF PLUS COAYKIT | AZ30: =MID(BD30,10,10) -> E TF PLUS | BA30: =LEFT(BE30,2)&RIGHT(BE30,2) -> COAY | BB30: =LEFT(BF30,3) -> KIT | BC30: =IFERROR(VLOOKUP(BD30&BF30,AV:AW,2,FALSE),0) -> 53.55 | BD30: POLY-CRETE TF PLUS PRIMER/TOPCOAT | BE30: CONCRETE GRAY | BF30: KIT | BG30: CRETE | BH30: CONCRETE GRAY
B31: 3 GAL | E31: =IF(SGC!M58=P!$E$15,P!$M$38,P!$M$41) -> TUBE | I31: R-MMT-5 | J31: =_xlfn.CONCAT(K31:M31) -> SGC SHIELD TOP COATN/A5 GAL | K31: SGC SHIELD TOP COAT | L31: N/A | M31: 5 GAL | X31: R-MMB-5 | Y31: SGC Shield Body Coat 5 Gal | Z31: =Table1[[#This Row],[D:D]] -> 302.5 | AA31: 5 gal | AD31: RIO | AE31: 275 | AF31: =Table1[[#This Row],[C:C]]*1.1 -> 302.5 | AI31: =IFERROR(VLOOKUP(X31,#REF!,8,FALSE),0) -> 0 | AN31: E TF PLUS DAAY1.7 | AO31: =_xlfn.CONCAT(BD31:BF31) -> POLY-CRETE TF PLUS PRIMER/TOPCOATDARK GRAYKIT | AP31: =BC31 -> 53.55 | AQ31: =BF31 -> KIT | AS31: =BE31 -> DARK GRAY | AT31: CRYLAFLOR COVE | AU31: 1 GAL KIT | AV31: =AT31&AU31 -> CRYLAFLOR COVE1 GAL KIT | AW31: 117.7 | AY31: =_xlfn.CONCAT(AZ31:BB31) -> E TF PLUS DAAYKIT | AZ31: =MID(BD31,10,10) -> E TF PLUS | BA31: =LEFT(BE31,2)&RIGHT(BE31,2) -> DAAY | BB31: =LEFT(BF31,3) -> KIT | BC31: =IFERROR(VLOOKUP(BD31&BF31,AV:AW,2,FALSE),0) -> 53.55 | BD31: POLY-CRETE TF PLUS PRIMER/TOPCOAT | BE31: DARK GRAY | BF31: KIT | BG31: CRETE | BH31: DARK GRAY
E32: CASE | I32: R-MMT-50 | J32: =_xlfn.CONCAT(K32:M32) -> SGC SHIELD TOP COATN/A50 GAL | K32: SGC SHIELD TOP COAT | L32: N/A | M32: 50 GAL | X32: R-MMB-50 | Y32: SGC Shield Body Coat 50 Gal | Z32: =Table1[[#This Row],[D:D]] -> 2915 | AA32: 50 gal | AD32: RIO | AE32: 2650 | AF32: =Table1[[#This Row],[C:C]]*1.1 -> 2915 | AI32: =IFERROR(VLOOKUP(X32,#REF!,8,FALSE),0) -> 0 | AN32: E TF PLUS GREN1.7 | AO32: =_xlfn.CONCAT(BD32:BF32) -> POLY-CRETE TF PLUS PRIMER/TOPCOATGREENKIT | AP32: =BC32 -> 53.55 | AQ32: =BF32 -> KIT | AS32: =BE32 -> GREEN | AT32: CRYLAFLOR CURE (BPO) | AU32: 5 LB KIT | AV32: =AT32&AU32 -> CRYLAFLOR CURE (BPO)5 LB KIT | AW32: 122.41 | AY32: =_xlfn.CONCAT(AZ32:BB32) -> E TF PLUS GRENKIT | AZ32: =MID(BD32,10,10) -> E TF PLUS | BA32: =LEFT(BE32,2)&RIGHT(BE32,2) -> GREN | BB32: =LEFT(BF32,3) -> KIT | BC32: =IFERROR(VLOOKUP(BD32&BF32,AV:AW,2,FALSE),0) -> 53.55 | BD32: POLY-CRETE TF PLUS PRIMER/TOPCOAT | BE32: GREEN | BF32: KIT | BG32: CRETE | BH32: GREEN
I33: R-MBP-10 | J33: =_xlfn.CONCAT(K33:M33) -> SGC BPO CATALYSTN/A10LB BOX | K33: SGC BPO CATALYST | L33: N/A | M33: 10LB BOX | X33: R-MMC-5 | Y33: SGC Coat MMA Cleaner 5 Gal | Z33: =Table1[[#This Row],[D:D]] -> 264 | AA33: 5 gal | AD33: RIO | AE33: 240 | AF33: =Table1[[#This Row],[C:C]]*1.1 -> 264 | AI33: =IFERROR(VLOOKUP(X33,#REF!,8,FALSE),0) -> 0 | AN33: E TF PLUS GRAY1.7 | AO33: =_xlfn.CONCAT(BD33:BF33) -> POLY-CRETE TF PLUS PRIMER/TOPCOATGRAYKIT | AP33: =BC33 -> 53.55 | AQ33: =BF33 -> KIT | AS33: =BE33 -> GRAY | AT33: CRYLAFLOR COLOR - BACKGROUND ONLY | AU33: KIT | AV33: =AT33&AU33 -> CRYLAFLOR COLOR - BACKGROUND ONLYKIT | AW33: 112.8 | AY33: =_xlfn.CONCAT(AZ33:BB33) -> E TF PLUS GRAYKIT | AZ33: =MID(BD33,10,10) -> E TF PLUS | BA33: =LEFT(BE33,2)&RIGHT(BE33,2) -> GRAY | BB33: =LEFT(BF33,3) -> KIT | BC33: =IFERROR(VLOOKUP(BD33&BF33,AV:AW,2,FALSE),0) -> 53.55 | BD33: POLY-CRETE TF PLUS PRIMER/TOPCOAT | BE33: GRAY | BF33: KIT | BG33: CRETE | BH33: GRAY
D34: =UPPER(B15) | I34: R-MMC-5 | J34: =_xlfn.CONCAT(K34:M34) -> SGC COAT MMA CLEANERN/A5 GAL | K34: SGC COAT MMA CLEANER | L34: N/A | M34: 5 GAL | X34: R-MMP-5 | Y34: SGC MMA Primer | Z34: =Table1[[#This Row],[D:D]] -> 330 | AA34: 5 gal | AD34: RIO | AE34: 300 | AF34: =Table1[[#This Row],[C:C]]*1.1 -> 330 | AI34: =IFERROR(VLOOKUP(X34,#REF!,8,FALSE),0) -> 0 | AN34: E TF PLUS REED1.7 | AO34: =_xlfn.CONCAT(BD34:BF34) -> POLY-CRETE TF PLUS PRIMER/TOPCOATREDKIT | AP34: =BC34 -> 53.55 | AQ34: =BF34 -> KIT | AS34: =BE34 -> RED | AT34: CRYLAFLOR BOND MT METAL/TILE ENHANCER | AU34: KIT | AV34: =AT34&AU34 -> CRYLAFLOR BOND MT METAL/TILE ENHANCERKIT | AW34: 85.8 | AY34: =_xlfn.CONCAT(AZ34:BB34) -> E TF PLUS REEDKIT | AZ34: =MID(BD34,10,10) -> E TF PLUS | BA34: =LEFT(BE34,2)&RIGHT(BE34,2) -> REED | BB34: =LEFT(BF34,3) -> KIT | BC34: =IFERROR(VLOOKUP(BD34&BF34,AV:AW,2,FALSE),0) -> 53.55 | BD34: POLY-CRETE TF PLUS PRIMER/TOPCOAT | BE34: RED | BF34: KIT | BG34: CRETE | BH34: RED
I35: R-MMP-5 | J35: =_xlfn.CONCAT(K35:M35) -> SGC MMA PRIMERN/A5 GAL | K35: SGC MMA PRIMER | L35: N/A | M35: 5 GAL | X35: R-MMT-5 | Y35: SGC Shield Topcoat 5 Gal | Z35: =Table1[[#This Row],[D:D]] -> 330 | AA35: 5 gal | AD35: RIO | AE35: 300 | AF35: =Table1[[#This Row],[C:C]]*1.1 -> 330 | AI35: =IFERROR(VLOOKUP(X35,#REF!,8,FALSE),0) -> 0 | AN35: E TF PLUS BLUE0.4 | AO35: =_xlfn.CONCAT(BD35:BF35) -> POLY-CRETE TF PLUS PRIMER/TOPCOATBLUEKIT | AP35: =BC35 -> 53.55 | AQ35: =BF35 -> KIT | AS35: =BE35 -> BLUE | AT35: CRYLAFLOR CLEAN SOLVENT TO CLEAN TOOLS | AU35: KIT | AV35: =AT35&AU35 -> CRYLAFLOR CLEAN SOLVENT TO CLEAN TOOLSKIT | AW35: 37.8 | AY35: =_xlfn.CONCAT(AZ35:BB35) -> E TF PLUS BLUEKIT | AZ35: =MID(BD35,10,10) -> E TF PLUS | BA35: =LEFT(BE35,2)&RIGHT(BE35,2) -> BLUE | BB35: =LEFT(BF35,3) -> KIT | BC35: =IFERROR(VLOOKUP(BD35&BF35,AV:AW,2,FALSE),0) -> 53.55 | BD35: POLY-CRETE TF PLUS PRIMER/TOPCOAT | BE35: BLUE | BF35: KIT | BG35: CRETE | BH35: N/A
I36: R-MMA-5 | J36: =_xlfn.CONCAT(K36:M36) -> RIO MMA BONDING ADDITIVEN/A5 GAL | K36: RIO MMA BONDING ADDITIVE | L36: N/A | M36: 5 GAL | X36: R-MMT-50 | Y36: SGC Shield Topcoat 50 Gal | Z36: =Table1[[#This Row],[D:D]] -> 2915 | AA36: 50 gal | AD36: RIO | AE36: 2650 | AF36: =Table1[[#This Row],[C:C]]*1.1 -> 2915 | AI36: =IFERROR(VLOOKUP(X36,#REF!,8,FALSE),0) -> 0 | AN36: E TF PLUS CHAL0.4 | AO36: =_xlfn.CONCAT(BD36:BF36) -> POLY-CRETE TF PLUS PRIMER/TOPCOATCHARCOALKIT | AP36: =BC36 -> 53.55 | AQ36: =BF36 -> KIT | AS36: =BE36 -> CHARCOAL | AT36: CRYLAFLOR LTC ADDITIVE LOW TEMPERATURE | AU36: KIT | AV36: =AT36&AU36 -> CRYLAFLOR LTC ADDITIVE LOW TEMPERATUREKIT | AW36: 46.8 | AY36: =_xlfn.CONCAT(AZ36:BB36) -> E TF PLUS CHALKIT | AZ36: =MID(BD36,10,10) -> E TF PLUS | BA36: =LEFT(BE36,2)&RIGHT(BE36,2) -> CHAL | BB36: =LEFT(BF36,3) -> KIT | BC36: =IFERROR(VLOOKUP(BD36&BF36,AV:AW,2,FALSE),0) -> 53.55 | BD36: POLY-CRETE TF PLUS PRIMER/TOPCOAT | BE36: CHARCOAL | BF36: KIT | BG36: CRETE | BH36: 3 GAL | BI36: {=IF(C35="","",_xlfn.SWITCH(C35,P!$BJ$36,P!$BH$46:$BH$47,P!$BJ$37,P!$BH$38,P!$BJ$38,P!$BH$45,P!$BJ$39,P!$BH$43,P!$BJ$40,P!$BH$42,P!$BJ$41,P!$BH$44,P!$BJ$42,P!$BH$40:$BH$41,P!$BJ$43,P!$BH$48))} | BJ36: POLY-CRETE COLOR-FAST | BK36: CRETE | BL36: 5115 MORTAR AGGREGATE BLEND | BM36: AGG
I37: NP-1 | J37: =_xlfn.CONCAT(K37:M37) -> NP-1 TUBES (30 TUBE/CASE)N/ATUBE | K37: NP-1 TUBES (30 TUBE/CASE) | L37: N/A | M37: TUBE | X37: ROAD10600 | Y37: Roadware 10 Minute Concrete Mender 600ML | Z37: =Table1[[#This Row],[D:D]] -> 65.219 | AA37: Tube | AD37: RIO | AE37: 59.29 | AF37: =Table1[[#This Row],[C:C]]*1.1 -> 65.219 | AI37: =IFERROR(VLOOKUP(X37,#REF!,8,FALSE),0) -> 0 | AN37: E TF PLUS CHUT0.4 | AO37: =_xlfn.CONCAT(BD37:BF37) -> POLY-CRETE TF PLUS PRIMER/TOPCOATCHESTNUTKIT | AP37: =BC37 -> 53.55 | AQ37: =BF37 -> KIT | AS37: =BE37 -> CHESTNUT | AT37: CRYLAFLOR SL FILLER BLEND TO G-201 | AU37: KIT | AV37: =AT37&AU37 -> CRYLAFLOR SL FILLER BLEND TO G-201KIT | AW37: 23.4 | AY37: =_xlfn.CONCAT(AZ37:BB37) -> E TF PLUS CHUTKIT | AZ37: =MID(BD37,10,10) -> E TF PLUS | BA37: =LEFT(BE37,2)&RIGHT(BE37,2) -> CHUT | BB37: =LEFT(BF37,3) -> KIT | BC37: =IFERROR(VLOOKUP(BD37&BF37,AV:AW,2,FALSE),0) -> 53.55 | BD37: POLY-CRETE TF PLUS PRIMER/TOPCOAT | BE37: CHESTNUT | BF37: KIT | BG37: CRETE | BH37: 15 GAL | BJ37: POLY-CRETE HF ACCELERATOR LOW TEMPERATURE AID | BK37: CRETE | BL37: 7310 PEA GRAVEL 3/16 X 3/8 | BM37: AGG
I38: JS4U-SG | J38: =_xlfn.CONCAT(K38:M38) -> 600 UV (SSP JS-600 ALIPHATIC POLYUREA)STANDARD GRAY1 GAL BOX | K38: 600 UV (SSP JS-600 ALIPHATIC POLYUREA) | L38: STANDARD GRAY | M38: 1 GAL BOX | X38: R-S20-1 | Y38: 20/40 Silica Sand | Z38: =Table1[[#This Row],[D:D]] -> 24.2 | AA38: Bag | AD38: RIO | AE38: 22 | AF38: =Table1[[#This Row],[C:C]]*1.1 -> 24.2 | AI38: =IFERROR(VLOOKUP(X38,#REF!,8,FALSE),0) -> 0 | AN38: E TF PLUS COAY0.4 | AO38: =_xlfn.CONCAT(BD38:BF38) -> POLY-CRETE TF PLUS PRIMER/TOPCOATCONCRETE GRAYKIT | AP38: =BC38 -> 53.55 | AQ38: =BF38 -> KIT | AS38: =BE38 -> CONCRETE GRAY | AT38: RESUDECK FLA CLEAR ALIPHATIC POLYASPARTIC TOPCOAT | AU38: 2 GAL | AV38: =AT38&AU38 -> RESUDECK FLA CLEAR ALIPHATIC POLYASPARTIC TOPCOAT2 GAL | AW38: 215.98 | AY38: =_xlfn.CONCAT(AZ38:BB38) -> E TF PLUS COAYKIT | AZ38: =MID(BD38,10,10) -> E TF PLUS | BA38: =LEFT(BE38,2)&RIGHT(BE38,2) -> COAY | BB38: =LEFT(BF38,3) -> KIT | BC38: =IFERROR(VLOOKUP(BD38&BF38,AV:AW,2,FALSE),0) -> 53.55 | BD38: POLY-CRETE TF PLUS PRIMER/TOPCOAT | BE38: CONCRETE GRAY | BF38: KIT | BG38: CRETE | BH38: 1 QT | BJ38: POLY-CRETE HF HS URETHANE CONCRETE COATING | BK38: CRETE | BL38: F-60 | BM38: AGG
H39: 600 UVGRAY AREA1 GAL BOX | I39: JS4U-GA | J39: =_xlfn.CONCAT(K39:M39) -> 600 UV (SSP JS-600 ALIPHATIC POLYUREA)GRAY AREA1 GAL BOX | K39: 600 UV (SSP JS-600 ALIPHATIC POLYUREA) | L39: GRAY AREA | M39: 1 GAL BOX | X39: S-UPA-3 | Y39: SGC Coat UPA | Z39: =Table1[[#This Row],[D:D]] -> 396 | AA39: 3 gal kit | AD39: RIO | AE39: =120*3 -> 360 | AF39: =Table1[[#This Row],[C:C]]*1.1 -> 396 | AI39: =IFERROR(VLOOKUP(X39,#REF!,8,FALSE),0) -> 0 | AN39: E TF PLUS DAAY0.4 | AO39: =_xlfn.CONCAT(BD39:BF39) -> POLY-CRETE TF PLUS PRIMER/TOPCOATDARK GRAYKIT | AP39: =BC39 -> 53.55 | AQ39: =BF39 -> KIT | AS39: =BE39 -> DARK GRAY | AT39: ACCELERA 4850 GROUT/TOPCOAT POLYASPARTIC | AU39: 3 GAL | AV39: =AT39&AU39 -> ACCELERA 4850 GROUT/TOPCOAT POLYASPARTIC3 GAL | AW39: 466.86 | AY39: =_xlfn.CONCAT(AZ39:BB39) -> E TF PLUS DAAYKIT | AZ39: =MID(BD39,10,10) -> E TF PLUS | BA39: =LEFT(BE39,2)&RIGHT(BE39,2) -> DAAY | BB39: =LEFT(BF39,3) -> KIT | BC39: =IFERROR(VLOOKUP(BD39&BF39,AV:AW,2,FALSE),0) -> 53.55 | BD39: POLY-CRETE TF PLUS PRIMER/TOPCOAT | BE39: DARK GRAY | BF39: KIT | BG39: CRETE | BH39: 5 GAL | BJ39: POLY-CRETE MD HS URETHANE CONCRETE COATING | BK39: CRETE | BL39: 1-16IN DECO FLAKE - 40LB BAG | BM39: AGG
I40: JS4U-CG | J40: =_xlfn.CONCAT(K40:M40) -> 600 UV (SSP JS-600 ALIPHATIC POLYUREA)CHATEAU GRAY1 GAL BOX | K40: 600 UV (SSP JS-600 ALIPHATIC POLYUREA) | L40: CHATEAU GRAY | M40: 1 GAL BOX | X40: R-UHW-1.5 | Y40: RIO Urethane High Wear Kit | Z40: =Table1[[#This Row],[D:D]] -> 374 | AA40: 1.5 Gal | AD40: RIO | AE40: 340 | AF40: =Table1[[#This Row],[C:C]]*1.1 -> 374 | AI40: =IFERROR(VLOOKUP(X40,#REF!,8,FALSE),0) -> 0 | AN40: E TF PLUS GREN0.4 | AO40: =_xlfn.CONCAT(BD40:BF40) -> POLY-CRETE TF PLUS PRIMER/TOPCOATGREENKIT | AP40: =BC40 -> 53.55 | AQ40: =BF40 -> KIT | AS40: =BE40 -> GREEN | AT40: ACCELERA 4850 GROUT/TOPCOAT POLYASPARTIC | AU40: 15 GAL | AV40: =AT40&AU40 -> ACCELERA 4850 GROUT/TOPCOAT POLYASPARTIC15 GAL | AW40: 2126.25 | AY40: =_xlfn.CONCAT(AZ40:BB40) -> E TF PLUS GRENKIT | AZ40: =MID(BD40,10,10) -> E TF PLUS | BA40: =LEFT(BE40,2)&RIGHT(BE40,2) -> GREN | BB40: =LEFT(BF40,3) -> KIT | BC40: =IFERROR(VLOOKUP(BD40&BF40,AV:AW,2,FALSE),0) -> 53.55 | BD40: POLY-CRETE TF PLUS PRIMER/TOPCOAT | BE40: GREEN | BF40: KIT | BG40: CRETE | BH40: 0.44 Gal | BJ40: POLY-CRETE SL HS SELF LEVELING URETHANE | BK40: CRETE | BL40: 1-8IN DECO FLAKE - 40LB BAG | BM40: AGG
B41: RIO | C41: SIKA | D41: SW | E41: BLANK | I41: S-RS88-ARG1 | J41: =_xlfn.CONCAT(K41:M41) -> RS88 (12 TUBES / CASE)GRAY AREATUBE | K41: RS88 (12 TUBES / CASE) | L41: GRAY AREA | M41: TUBE | X41: R-UHW-6 | Y41: RIO Urethane High Wear Kit | Z41: =Table1[[#This Row],[D:D]] -> 1210 | AA41: 6 Gal | AD41: RIO | AE41: 1100 | AF41: =Table1[[#This Row],[C:C]]*1.1 -> 1210 | AI41: =IFERROR(VLOOKUP(X41,#REF!,8,FALSE),0) -> 0 | AN41: E TF PLUS GRAY0.4 | AO41: =_xlfn.CONCAT(BD41:BF41) -> POLY-CRETE TF PLUS PRIMER/TOPCOATGRAYKIT | AP41: =BC41 -> 53.55 | AQ41: =BF41 -> KIT | AS41: =BE41 -> GRAY | AT41: 5115 MORTAR AGGREGATE BLEND | AU41: 50LB BAG | AV41: =AT41&AU41 -> 5115 MORTAR AGGREGATE BLEND50LB BAG | AW41: 10.4 | AY41: =_xlfn.CONCAT(AZ41:BB41) -> E TF PLUS GRAYKIT | AZ41: =MID(BD41,10,10) -> E TF PLUS | BA41: =LEFT(BE41,2)&RIGHT(BE41,2) -> GRAY | BB41: =LEFT(BF41,3) -> KIT | BC41: =IFERROR(VLOOKUP(BD41&BF41,AV:AW,2,FALSE),0) -> 53.55 | BD41: POLY-CRETE TF PLUS PRIMER/TOPCOAT | BE41: GRAY | BF41: KIT | BG41: CRETE | BH41: 1.7 Gal | BJ41: POLY-CRETE TF PLUS COVE VERTICAL APPLICATIONS | BK41: CRETE | BL41: 1-4IN DECO FLAKE - 40LB BAG | BM41: AGG
A42: 7-910 PM AIRLINE EXPENSES | B42: =IFERROR(VLOOKUP($A42,SGC!$C:$D,2,FALSE),0) -> 0 | C42: =IFERROR(VLOOKUP($A42,SIKA!$C:$D,2,FALSE),0) -> 0 | D42: =IFERROR(VLOOKUP($A42,SW!$C:$D,2,FALSE),0) -> 0 | E42: =IFERROR(VLOOKUP($A42,BLANK!$M:$N,2,FALSE),0) -> 0 | G42: =SUM(B42:F42) -> 0 | I42: S-RS88-SG1 | J42: =_xlfn.CONCAT(K42:M42) -> RS88 (12 TUBES / CASE)STANDARD GRAYTUBE | K42: RS88 (12 TUBES / CASE) | L42: STANDARD GRAY | M42: TUBE | X42: S-AST-1 | Y42: SGC Ash Trowel Quartz | Z42: =Table1[[#This Row],[D:D]] -> 33 | AA42: 50lb bag | AD42: RIO | AE42: 30 | AF42: =Table1[[#This Row],[C:C]]*1.1 -> 33 | AI42: =IFERROR(VLOOKUP(X42,#REF!,8,FALSE),0) -> 0 | AN42: E TF PLUS REED0.4 | AO42: =_xlfn.CONCAT(BD42:BF42) -> POLY-CRETE TF PLUS PRIMER/TOPCOATREDKIT | AP42: =BC42 -> 53.55 | AQ42: =BF42 -> KIT | AS42: =BE42 -> RED | AT42: 5310 DRY SILICA SAND - 20/40 | AU42: 50LB BAG | AV42: =AT42&AU42 -> 5310 DRY SILICA SAND - 20/4050LB BAG | AW42: 12.79 | AY42: =_xlfn.CONCAT(AZ42:BB42) -> E TF PLUS REEDKIT | AZ42: =MID(BD42,10,10) -> E TF PLUS | BA42: =LEFT(BE42,2)&RIGHT(BE42,2) -> REED | BB42: =LEFT(BF42,3) -> KIT | BC42: =IFERROR(VLOOKUP(BD42&BF42,AV:AW,2,FALSE),0) -> 53.55 | BD42: POLY-CRETE TF PLUS PRIMER/TOPCOAT | BE42: RED | BF42: KIT | BG42: CRETE | BH42: 3.4 Gal | BJ42: POLY-CRETE TF PLUS PRIMER/TOPCOAT | BK42: CRETE | BL42: RESUFLOR NO SAG
A43: 7-920 PM HOTEL EXPENSES | B43: =IFERROR(VLOOKUP($A43,SGC!$C:$D,2,FALSE),0) -> 0 | C43: =IFERROR(VLOOKUP($A43,SIKA!$C:$D,2,FALSE),0) -> 0 | D43: =IFERROR(VLOOKUP($A43,SW!$C:$D,2,FALSE),0) -> 0 | E43: =IFERROR(VLOOKUP($A43,BLANK!$M:$N,2,FALSE),0) -> 0 | G43: =SUM(B43:F43) -> 0 | I43: S-RS88-CG1 | J43: =_xlfn.CONCAT(K43:M43) -> RS88 (12 TUBES / CASE)CHATEAU GRAYTUBE | K43: RS88 (12 TUBES / CASE) | L43: CHATEAU GRAY | M43: TUBE | X43: S-CBG-1 | Y43: SGC Polyaspartic Battleship Gray Colorant | Z43: =Table1[[#This Row],[D:D]] -> 56.43 | AA43: Pint | AD43: RIO | AE43: 51.3 | AF43: =Table1[[#This Row],[C:C]]*1.1 -> 56.43 | AI43: =IFERROR(VLOOKUP(X43,#REF!,8,FALSE),0) -> 0 | AN43: =PROD_ID_TABLE[[#This Row],[PROD ID]] -> E SL HS SEBLUEKIT | AO43: =_xlfn.CONCAT(BD43:BF43) -> POLY-CRETE SL HS SELF LEVELING URETHANEBLUEKIT | AP43: =BC43 -> 102.4 | AQ43: =BF43 -> KIT | AS43: =BE43 -> BLUE | AT43: 5310 DRY SILICA SAND - 40/60 | AU43: 50LB BAG | AV43: =AT43&AU43 -> 5310 DRY SILICA SAND - 40/6050LB BAG | AW43: 18.85 | AY43: =_xlfn.CONCAT(AZ43:BB43) -> E SL HS SEBLUEKIT | AZ43: =MID(BD43,10,10) -> E SL HS SE | BA43: =LEFT(BE43,2)&RIGHT(BE43,2) -> BLUE | BB43: =LEFT(BF43,3) -> KIT | BC43: =IFERROR(VLOOKUP(BD43&BF43,AV:AW,2,FALSE),0) -> 102.4 | BD43: POLY-CRETE SL HS SELF LEVELING URETHANE | BE43: BLUE | BF43: KIT | BG43: CRETE | BH43: 4.9 Gal | BJ43: POLY-CRETE WR COVE BASE, SLOPE/PATCHING | BK43: CRETE | BL43: Q-ROCK 16 GRIT
A44: 7-930 PM AUTO RENTAL | B44: =IFERROR(VLOOKUP($A44,SGC!$C:$D,2,FALSE),0) -> 0 | C44: =IFERROR(VLOOKUP($A44,SIKA!$C:$D,2,FALSE),0) -> 0 | D44: =IFERROR(VLOOKUP($A44,SW!$C:$D,2,FALSE),0) -> 0 | E44: =IFERROR(VLOOKUP($A44,BLANK!$M:$N,2,FALSE),0) -> 0 | G44: =SUM(B44:F44) -> 0 | I44: S-GCA-5 | J44: =_xlfn.CONCAT(K44:M44) -> SGC CRETE PART AN/A5 GAL | K44: SGC CRETE PART A | L44: N/A | M44: 5 GAL | X44: S-CPG-1 | Y44: SGC Polyaspartic Gray Colorant | Z44: =Table1[[#This Row],[D:D]] -> 56.43 | AA44: Pint | AD44: RIO | AE44: 51.3 | AF44: =Table1[[#This Row],[C:C]]*1.1 -> 56.43 | AI44: =IFERROR(VLOOKUP(X44,#REF!,8,FALSE),0) -> 0 | AN44: =PROD_ID_TABLE[[#This Row],[PROD ID]] -> E SL HS SECHALKIT | AO44: =_xlfn.CONCAT(BD44:BF44) -> POLY-CRETE SL HS SELF LEVELING URETHANECHARCOALKIT | AP44: =BC44 -> 102.4 | AQ44: =BF44 -> KIT | AS44: =BE44 -> CHARCOAL | AT44: 5310 DRY SILICA SAND - 80/120 | AU44: 50LB BAG | AV44: =AT44&AU44 -> 5310 DRY SILICA SAND - 80/12050LB BAG | AW44: 26 | AY44: =_xlfn.CONCAT(AZ44:BB44) -> E SL HS SECHALKIT | AZ44: =MID(BD44,10,10) -> E SL HS SE | BA44: =LEFT(BE44,2)&RIGHT(BE44,2) -> CHAL | BB44: =LEFT(BF44,3) -> KIT | BC44: =IFERROR(VLOOKUP(BD44&BF44,AV:AW,2,FALSE),0) -> 102.4 | BD44: POLY-CRETE SL HS SELF LEVELING URETHANE | BE44: CHARCOAL | BF44: KIT | BG44: CRETE | BH44: 0.23 Gal | BL44: 5310 DRY SILICA SAND - 20/40
A45: 7-940 PM MILEAGE/FUEL EXPENSE | B45: =IFERROR(VLOOKUP($A45,SGC!$F:$H,3,FALSE),0) -> 0 | C45: =IFERROR(VLOOKUP($A45,SIKA!$F:$H,3,FALSE),0) -> 0 | D45: =IFERROR(VLOOKUP($A45,SW!$F:$H,3,FALSE),0) -> 0 | E45: =IFERROR(VLOOKUP($A45,BLANK!$P:$R,3,FALSE),0) -> 0 | G45: =SUM(B45:F45) -> 0 | I45: S-GCA-50 | J45: =_xlfn.CONCAT(K45:M45) -> SGC CRETE PART AN/A50 GAL | K45: SGC CRETE PART A | L45: N/A | M45: 50 GAL | X45: S-CST-1 | Y45: SGC Saddle Tan Colorant | Z45: =Table1[[#This Row],[D:D]] -> 28.05 | AA45: Pint | AD45: RIO | AE45: 25.5 | AF45: =Table1[[#This Row],[C:C]]*1.1 -> 28.05 | AI45: =IFERROR(VLOOKUP(X45,#REF!,8,FALSE),0) -> 0 | AN45: =PROD_ID_TABLE[[#This Row],[PROD ID]] -> E SL HS SECHUTKIT | AO45: =_xlfn.CONCAT(BD45:BF45) -> POLY-CRETE SL HS SELF LEVELING URETHANECHESTNUTKIT | AP45: =BC45 -> 102.4 | AQ45: =BF45 -> KIT | AS45: =BE45 -> CHESTNUT | AT45: 7310 PEA GRAVEL 3/16 X 3/8 | AU45: 50LB BAG | AV45: =AT45&AU45 -> 7310 PEA GRAVEL 3/16 X 3/850LB BAG | AW45: 20.8 | AY45: =_xlfn.CONCAT(AZ45:BB45) -> E SL HS SECHUTKIT | AZ45: =MID(BD45,10,10) -> E SL HS SE | BA45: =LEFT(BE45,2)&RIGHT(BE45,2) -> CHUT | BB45: =LEFT(BF45,3) -> KIT | BC45: =IFERROR(VLOOKUP(BD45&BF45,AV:AW,2,FALSE),0) -> 102.4 | BD45: POLY-CRETE SL HS SELF LEVELING URETHANE | BE45: CHESTNUT | BF45: KIT | BG45: CRETE | BH45: 4 Gal | BI45: {=IF(C5="","",_xlfn.SWITCH(C5,P!$BL$2,P!$BF$6:$BF$7,P!$BL$3,P!$BF$10:$BF$11,P!$BL$4,P!$BF$17:$BF$18,P!$BL$5,P!$BF$21:$BF$22,P!$BL$6,P!$BF$25:$BF$26,P!$BL$7,P!$BF$23:$BF$24))} | BL45: 5310 DRY SILICA SAND - 40/60
A46: 7-950 PM MEALS | B46: =IFERROR(VLOOKUP($A46,SGC!$F:$H,3,FALSE),0) -> 0 | C46: =IFERROR(VLOOKUP($A46,SIKA!$F:$H,3,FALSE),0) -> 0 | D46: =IFERROR(VLOOKUP($A46,SW!$F:$H,3,FALSE),0) -> 0 | E46: =IFERROR(VLOOKUP($A46,BLANK!$P:$R,3,FALSE),0) -> 0 | G46: =SUM(B46:F46) -> 0 | H46: S-GCA-50 | I46: S-GCB-5 | J46: =_xlfn.CONCAT(K46:M46) -> SGC CRETE PART BN/A5 GAL | K46: SGC CRETE PART B | L46: N/A | M46: 5 GAL | X46: S-CST-25 | Y46: SGC Saddle Tan Colorant | Z46: =Table1[[#This Row],[D:D]] -> 308 | AA46: 25 Pint | AD46: RIO | AE46: 280 | AF46: =Table1[[#This Row],[C:C]]*1.1 -> 308 | AI46: =IFERROR(VLOOKUP(X46,#REF!,8,FALSE),0) -> 0 | AN46: =PROD_ID_TABLE[[#This Row],[PROD ID]] -> E SL HS SECOAYKIT | AO46: =_xlfn.CONCAT(BD46:BF46) -> POLY-CRETE SL HS SELF LEVELING URETHANECONCRETE GRAYKIT | AP46: =BC46 -> 102.4 | AQ46: =BF46 -> KIT | AS46: =BE46 -> CONCRETE GRAY | AT46: F-60 | AU46: 50LB BAG | AV46: =AT46&AU46 -> F-6050LB BAG | AW46: 27.3 | AY46: =_xlfn.CONCAT(AZ46:BB46) -> E SL HS SECOAYKIT | AZ46: =MID(BD46,10,10) -> E SL HS SE | BA46: =LEFT(BE46,2)&RIGHT(BE46,2) -> COAY | BB46: =LEFT(BF46,3) -> KIT | BC46: =IFERROR(VLOOKUP(BD46&BF46,AV:AW,2,FALSE),0) -> 102.4 | BD46: POLY-CRETE SL HS SELF LEVELING URETHANE | BE46: CONCRETE GRAY | BF46: KIT | BG46: CRETE | BH46: 0.93 GAL | BL46: 5310 DRY SILICA SAND - 80/120
A47: 7-960 PM PARKING / TOLLS | B47: =IFERROR(VLOOKUP($A47,SGC!$F:$H,3,FALSE),0) -> 0 | C47: =IFERROR(VLOOKUP($A47,SIKA!$F:$H,3,FALSE),0) -> 0 | D47: =IFERROR(VLOOKUP($A47,SW!$F:$H,3,FALSE),0) -> 0 | E47: =IFERROR(VLOOKUP($A47,BLANK!$P:$R,3,FALSE),0) -> 0 | G47: =SUM(B47:F47) -> 0 | I47: S-GCB-50 | J47: =_xlfn.CONCAT(K47:M47) -> SGC CRETE PART BN/A50 GAL | K47: SGC CRETE PART B | L47: N/A | M47: 50 GAL | X47: S-R88-ARG2 | Y47: RS88 Gray Area | Z47: =Table1[[#This Row],[D:D]] -> 462 | AA47: Case | AC47: Gray Area | AD47: RIO | AE47: 420 | AF47: =Table1[[#This Row],[C:C]]*1.1 -> 462 | AI47: =IFERROR(VLOOKUP(X47,#REF!,8,FALSE),0) -> 0 | AN47: =PROD_ID_TABLE[[#This Row],[PROD ID]] -> E SL HS SEDAAYKIT | AO47: =_xlfn.CONCAT(BD47:BF47) -> POLY-CRETE SL HS SELF LEVELING URETHANEDARK GRAYKIT | AP47: =BC47 -> 102.4 | AQ47: =BF47 -> KIT | AS47: =BE47 -> DARK GRAY | AT47: 1-16IN DECO FLAKE - 40LB BAG | AU47: 40LB BAG | AV47: =AT47&AU47 -> 1-16IN DECO FLAKE - 40LB BAG40LB BAG | AW47: 143 | AY47: =_xlfn.CONCAT(AZ47:BB47) -> E SL HS SEDAAYKIT | AZ47: =MID(BD47,10,10) -> E SL HS SE | BA47: =LEFT(BE47,2)&RIGHT(BE47,2) -> DAAY | BB47: =LEFT(BF47,3) -> KIT | BC47: =IFERROR(VLOOKUP(BD47&BF47,AV:AW,2,FALSE),0) -> 102.4 | BD47: POLY-CRETE SL HS SELF LEVELING URETHANE | BE47: DARK GRAY | BF47: KIT | BG47: CRETE | BH47: 1.84 GAL | BL47: HPF COLOR QUARTZ
A48: 5-400 Tools & Small Equipment | B48: =IFERROR(VLOOKUP($A48,SGC!$F:$H,3,FALSE),0) -> 0 | C48: =IFERROR(VLOOKUP($A48,SIKA!$F:$H,3,FALSE),0) -> 0 | D48: =IFERROR(VLOOKUP($A48,SW!$F:$H,3,FALSE),0) -> 0 | E48: =IFERROR(VLOOKUP($A48,BLANK!$P:$R,3,FALSE),0) -> 0 | G48: =SUM(B48:F48) -> 0 | I48: R-CSL-1 | J48: =_xlfn.CONCAT(K48:M48) -> SL - PART CCLEARKIT | K48: SL - PART C | L48: CLEAR | M48: KIT | X48: S-R88-SG2 | Y48: RS88 Standard Gray | Z48: =Table1[[#This Row],[D:D]] -> 462 | AA48: Case | AC48: Standard Gray | AD48: RIO | AE48: 420 | AF48: =Table1[[#This Row],[C:C]]*1.1 -> 462 | AI48: =IFERROR(VLOOKUP(X48,#REF!,8,FALSE),0) -> 0 | AN48: =PROD_ID_TABLE[[#This Row],[PROD ID]] -> E SL HS SEGRENKIT | AO48: =_xlfn.CONCAT(BD48:BF48) -> POLY-CRETE SL HS SELF LEVELING URETHANEGREENKIT | AP48: =BC48 -> 102.4 | AQ48: =BF48 -> KIT | AS48: =BE48 -> GREEN | AT48: RESUFLOR AQUA 3460 WB EPOXY PRIMER, BINDER, TOPCOAT | AU48: 1.25 GAL | AV48: =AT48&AU48 -> RESUFLOR AQUA 3460 WB EPOXY PRIMER, BINDER, TOPCOAT1.25 GAL | AW48: 131.82 | AY48: =_xlfn.CONCAT(AZ48:BB48) -> E SL HS SEGRENKIT | AZ48: =MID(BD48,10,10) -> E SL HS SE | BA48: =LEFT(BE48,2)&RIGHT(BE48,2) -> GREN | BB48: =LEFT(BF48,3) -> KIT | BC48: =IFERROR(VLOOKUP(BD48&BF48,AV:AW,2,FALSE),0) -> 102.4 | BD48: POLY-CRETE SL HS SELF LEVELING URETHANE | BE48: GREEN | BF48: KIT | BG48: CRETE | BH48: 3.3 Gal
A49: 5-500 Consumables Supplies-Box Store | B49: =IFERROR(VLOOKUP($A49,SGC!$C:$D,2,FALSE),0) -> 0 | C49: =IFERROR(VLOOKUP($A49,SIKA!$C:$D,2,FALSE),0) -> 0 | D49: =IFERROR(VLOOKUP($A49,SW!$C:$D,2,FALSE),0) -> 0 | E49: =IFERROR(VLOOKUP($A49,BLANK!$M:$N,2,FALSE),0) -> 0 | G49: =SUM(B49:F49) -> 0 | I49: R-CSF-1 | J49: =_xlfn.CONCAT(K49:M49) -> SF - PART CN/AKIT | K49: SF - PART C | L49: N/A | M49: KIT | X49: S-R88-CG2 | Y49: RS88 Chateau Gray | Z49: =Table1[[#This Row],[D:D]] -> 462 | AA49: Case | AC49: Chateau Gray | AD49: RIO | AE49: 420 | AF49: =Table1[[#This Row],[C:C]]*1.1 -> 462 | AI49: =IFERROR(VLOOKUP(X49,#REF!,8,FALSE),0) -> 0 | AN49: =PROD_ID_TABLE[[#This Row],[PROD ID]] -> E SL HS SEGRAYKIT | AO49: =_xlfn.CONCAT(BD49:BF49) -> POLY-CRETE SL HS SELF LEVELING URETHANEGRAYKIT | AP49: =BC49 -> 102.4 | AQ49: =BF49 -> KIT | AS49: =BE49 -> GRAY | AT49: RESUFLOR AQUA 3460 WB EPOXY PRIMER, BINDER, TOPCOAT | AU49: 25 GAL | AV49: =AT49&AU49 -> RESUFLOR AQUA 3460 WB EPOXY PRIMER, BINDER, TOPCOAT25 GAL | AW49: 2139 | AY49: =_xlfn.CONCAT(AZ49:BB49) -> E SL HS SEGRAYKIT | AZ49: =MID(BD49,10,10) -> E SL HS SE | BA49: =LEFT(BE49,2)&RIGHT(BE49,2) -> GRAY | BB49: =LEFT(BF49,3) -> KIT | BC49: =IFERROR(VLOOKUP(BD49&BF49,AV:AW,2,FALSE),0) -> 102.4 | BD49: POLY-CRETE SL HS SELF LEVELING URETHANE | BE49: GRAY | BF49: KIT | BG49: CRETE
A50: 5-550 PO Consumables Supplies | B50: =IFERROR(VLOOKUP($A50,SGC!$C:$D,2,FALSE),0) -> 0 | C50: =IFERROR(VLOOKUP($A50,SIKA!$C:$D,2,FALSE),0) -> 0 | D50: =IFERROR(VLOOKUP($A50,SW!$C:$D,2,FALSE),0) -> 0 | E50: =IFERROR(VLOOKUP($A50,BLANK!$M:$N,2,FALSE),0) -> 0 | G50: =SUM(B50:F50) -> 0 | I50: R-CCB-1 | J50: =_xlfn.CONCAT(K50:M50) -> CB - PART CPIGMENTEDKIT | K50: CB - PART C | L50: PIGMENTED | M50: KIT | X50: S-DEB-5 | Y50: SGC Deck Base Coat 308 Kit (4:1) | Z50: =Table1[[#This Row],[D:D]] -> 396 | AA50: 5 gal | AD50: RIO | AE50: 360 | AF50: =Table1[[#This Row],[C:C]]*1.1 -> 396 | AI50: =IFERROR(VLOOKUP(X50,#REF!,8,FALSE),0) -> 0 | AN50: =PROD_ID_TABLE[[#This Row],[PROD ID]] -> E SL HS SEREEDKIT | AO50: =_xlfn.CONCAT(BD50:BF50) -> POLY-CRETE SL HS SELF LEVELING URETHANEREDKIT | AP50: =BC50 -> 102.4 | AQ50: =BF50 -> KIT | AS50: =BE50 -> RED | AT50: RESUFLOR AQUA 3461 HIGH SOLIDS WB EPOXY GROUT/TOPCOAT | AU50: 3 GAL | AV50: =AT50&AU50 -> RESUFLOR AQUA 3461 HIGH SOLIDS WB EPOXY GROUT/TOPCOAT3 GAL | AW50: 318 | AY50: =_xlfn.CONCAT(AZ50:BB50) -> E SL HS SEREEDKIT | AZ50: =MID(BD50,10,10) -> E SL HS SE | BA50: =LEFT(BE50,2)&RIGHT(BE50,2) -> REED | BB50: =LEFT(BF50,3) -> KIT | BC50: =IFERROR(VLOOKUP(BD50&BF50,AV:AW,2,FALSE),0) -> 102.4 | BD50: POLY-CRETE SL HS SELF LEVELING URETHANE | BE50: RED | BF50: KIT | BG50: CRETE
A51: 5-600 In-House Equipment Cost | B51: =IFERROR(VLOOKUP($A51,SGC!$F:$H,3,FALSE),0) -> 0 | C51: =IFERROR(VLOOKUP($A51,SIKA!$F:$H,3,FALSE),0) -> 0 | D51: =IFERROR(VLOOKUP($A51,SW!$F:$H,3,FALSE),0) -> 0 | E51: =IFERROR(VLOOKUP($A51,BLANK!$P:$R,3,FALSE),0) -> 0 | G51: =SUM(B51:F51) -> 0 | I51: R-CTC-1 | J51: =_xlfn.CONCAT(K51:M51) -> TC - PART CPIGMENTEDKIT | K51: TC - PART C | L51: PIGMENTED | M51: KIT | X51: S-GCA-5 | Y51: SGC Crete A - 5 gal | Z51: =Table1[[#This Row],[D:D]] -> 231 | AA51: 5 gal | AD51: RIO | AE51: 210 | AF51: =Table1[[#This Row],[C:C]]*1.1 -> 231 | AI51: =IFERROR(VLOOKUP(X51,#REF!,8,FALSE),0) -> 0 | AN51: =PROD_ID_TABLE[[#This Row],[PROD ID]] -> E MD HS URBLUEKIT | AO51: =_xlfn.CONCAT(BD51:BF51) -> POLY-CRETE MD HS URETHANE CONCRETE COATINGBLUEKIT | AP51: =BC51 -> 116.52 | AQ51: =BF51 -> KIT | AS51: =BE51 -> BLUE | AT51: RESUFLOR AQUA 3461 HIGH SOLIDS WB EPOXY GROUT/TOPCOAT | AU51: 15 GAL | AV51: =AT51&AU51 -> RESUFLOR AQUA 3461 HIGH SOLIDS WB EPOXY GROUT/TOPCOAT15 GAL | AW51: 1617 | AY51: =_xlfn.CONCAT(AZ51:BB51) -> E MD HS URBLUEKIT | AZ51: =MID(BD51,10,10) -> E MD HS UR | BA51: =LEFT(BE51,2)&RIGHT(BE51,2) -> BLUE | BB51: =LEFT(BF51,3) -> KIT | BC51: =IFERROR(VLOOKUP(BD51&BF51,AV:AW,2,FALSE),0) -> 116.52 | BD51: POLY-CRETE MD HS URETHANE CONCRETE COATING | BE51: BLUE | BF51: KIT | BG51: CRETE
I52: S-SCS-1 | J52: =_xlfn.CONCAT(K52:M52) -> SGC SPEED N/A32 OZ | K52: SGC SPEED | L52: N/A | M52: 32 OZ | X52: S-GCA-50 | Y52: SGC Crete A - 50 gal | Z52: =Table1[[#This Row],[D:D]] -> 2211 | AA52: Drum | AD52: RIO | AE52: 2010 | AF52: =Table1[[#This Row],[C:C]]*1.1 -> 2211 | AI52: =IFERROR(VLOOKUP(X52,#REF!,8,FALSE),0) -> 0 | AN52: =PROD_ID_TABLE[[#This Row],[PROD ID]] -> E MD HS URCHALKIT | AO52: =_xlfn.CONCAT(BD52:BF52) -> POLY-CRETE MD HS URETHANE CONCRETE COATINGCHARCOALKIT | AP52: =BC52 -> 116.52 | AQ52: =BF52 -> KIT | AS52: =BE52 -> CHARCOAL | AT52: RESUFLOR 3760 MPE MULTI-PURPOSE EPOXY | AU52: 3 GAL | AV52: =AT52&AU52 -> RESUFLOR 3760 MPE MULTI-PURPOSE EPOXY3 GAL | AW52: 177.73 | AY52: =_xlfn.CONCAT(AZ52:BB52) -> E MD HS URCHALKIT | AZ52: =MID(BD52,10,10) -> E MD HS UR | BA52: =LEFT(BE52,2)&RIGHT(BE52,2) -> CHAL | BB52: =LEFT(BF52,3) -> KIT | BC52: =IFERROR(VLOOKUP(BD52&BF52,AV:AW,2,FALSE),0) -> 116.52 | BD52: POLY-CRETE MD HS URETHANE CONCRETE COATING | BE52: CHARCOAL | BF52: KIT | BG52: CRETE
I53: S-CBG-1 | J53: =_xlfn.CONCAT(K53:M53) -> POLYASPARTIC COLORANTBATTLESHIP GRAYPINT | K53: POLYASPARTIC COLORANT | L53: BATTLESHIP GRAY | M53: PINT | X53: S-GCB-5 | Y53: SGC Crete B - 5 gal | Z53: =Table1[[#This Row],[D:D]] -> 231 | AA53: 5 gal | AD53: RIO | AE53: 210 | AF53: =Table1[[#This Row],[C:C]]*1.1 -> 231 | AI53: =IFERROR(VLOOKUP(X53,#REF!,8,FALSE),0) -> 0 | AN53: =PROD_ID_TABLE[[#This Row],[PROD ID]] -> E MD HS URCHUTKIT | AO53: =_xlfn.CONCAT(BD53:BF53) -> POLY-CRETE MD HS URETHANE CONCRETE COATINGCHESTNUTKIT | AP53: =BC53 -> 116.52 | AQ53: =BF53 -> KIT | AS53: =BE53 -> CHESTNUT | AT53: RESUFLOR 3760 MPE MULTI-PURPOSE EPOXY | AU53: 15 GAL | AV53: =AT53&AU53 -> RESUFLOR 3760 MPE MULTI-PURPOSE EPOXY15 GAL | AW53: 847.44 | AY53: =_xlfn.CONCAT(AZ53:BB53) -> E MD HS URCHUTKIT | AZ53: =MID(BD53,10,10) -> E MD HS UR | BA53: =LEFT(BE53,2)&RIGHT(BE53,2) -> CHUT | BB53: =LEFT(BF53,3) -> KIT | BC53: =IFERROR(VLOOKUP(BD53&BF53,AV:AW,2,FALSE),0) -> 116.52 | BD53: POLY-CRETE MD HS URETHANE CONCRETE COATING | BE53: CHESTNUT | BF53: KIT | BG53: CRETE
B54: M | C54: F | D54: R | E54: CS-M | F54: N-M | I54: S-CPG-1 | J54: =_xlfn.CONCAT(K54:M54) -> POLYASPARTIC COLORANTMEDIUM GRAYPINT | K54: POLYASPARTIC COLORANT | L54: MEDIUM GRAY | M54: PINT | X54: S-GCB-50 | Y54: SGC Crete B - 50 gal | Z54: =Table1[[#This Row],[D:D]] -> 2211 | AA54: Drum | AD54: RIO | AE54: 2010 | AF54: =Table1[[#This Row],[C:C]]*1.1 -> 2211 | AI54: =IFERROR(VLOOKUP(X54,#REF!,8,FALSE),0) -> 0 | AN54: =PROD_ID_TABLE[[#This Row],[PROD ID]] -> E MD HS URCOAYKIT | AO54: =_xlfn.CONCAT(BD54:BF54) -> POLY-CRETE MD HS URETHANE CONCRETE COATINGCONCRETE GRAYKIT | AP54: =BC54 -> 116.52 | AQ54: =BF54 -> KIT | AS54: =BE54 -> CONCRETE GRAY | AT54: RESUFLOR 3746 HIGH PERFORMANCE EPOXY | AU54: 3 GAL | AV54: =AT54&AU54 -> RESUFLOR 3746 HIGH PERFORMANCE EPOXY3 GAL | AW54: 205.98 | AY54: =_xlfn.CONCAT(AZ54:BB54) -> E MD HS URCOAYKIT | AZ54: =MID(BD54,10,10) -> E MD HS UR | BA54: =LEFT(BE54,2)&RIGHT(BE54,2) -> COAY | BB54: =LEFT(BF54,3) -> KIT | BC54: =IFERROR(VLOOKUP(BD54&BF54,AV:AW,2,FALSE),0) -> 116.52 | BD54: POLY-CRETE MD HS URETHANE CONCRETE COATING | BE54: CONCRETE GRAY | BF54: KIT | BG54: CRETE | BH54: POLY-CRETE TF PLUS PRIMER/TOPCOAT | BI54: 0.44 Gal
A55: AL | B55: X | I55: R-CBG-1 | J55: =_xlfn.CONCAT(K55:M55) -> CRETE COLORANTBATTLESHIP GRAYPINT | K55: CRETE COLORANT | L55: BATTLESHIP GRAY | M55: PINT | X55: S-GPR-3 | Y55: SGC ShieldFlex 3 Gal Kit | Z55: =Table1[[#This Row],[D:D]] -> 178.112 | AA55: 3 gal kit | AD55: RIO | AE55: 161.92 | AF55: =Table1[[#This Row],[C:C]]*1.1 -> 178.112 | AI55: =IFERROR(VLOOKUP(X55,#REF!,8,FALSE),0) -> 0 | AN55: =PROD_ID_TABLE[[#This Row],[PROD ID]] -> E MD HS URDAAYKIT | AO55: =_xlfn.CONCAT(BD55:BF55) -> POLY-CRETE MD HS URETHANE CONCRETE COATINGDARK GRAYKIT | AP55: =BC55 -> 116.52 | AQ55: =BF55 -> KIT | AS55: =BE55 -> DARK GRAY | AT55: RESUFLOR 3746 HIGH PERFORMANCE EPOXY | AU55: 15 GAL | AV55: =AT55&AU55 -> RESUFLOR 3746 HIGH PERFORMANCE EPOXY15 GAL | AW55: 982.21 | AY55: =_xlfn.CONCAT(AZ55:BB55) -> E MD HS URDAAYKIT | AZ55: =MID(BD55,10,10) -> E MD HS UR | BA55: =LEFT(BE55,2)&RIGHT(BE55,2) -> DAAY | BB55: =LEFT(BF55,3) -> KIT | BC55: =IFERROR(VLOOKUP(BD55&BF55,AV:AW,2,FALSE),0) -> 116.52 | BD55: POLY-CRETE MD HS URETHANE CONCRETE COATING | BE55: DARK GRAY | BF55: KIT | BG55: CRETE | BH55: POLY-CRETE TF PLUS PRIMER/TOPCOAT | BI55: 1.7 Gal
A56: AK | I56: R-CBK-1 | J56: =_xlfn.CONCAT(K56:M56) -> CRETE COLORANTBLACKPINT | K56: CRETE COLORANT | L56: BLACK | M56: PINT | X56: S-GRY-1 | Y56: SGC Gray Pigment | Z56: =Table1[[#This Row],[D:D]] -> 28.05 | AA56: Pint | AD56: RIO | AE56: 25.5 | AF56: =Table1[[#This Row],[C:C]]*1.1 -> 28.05 | AI56: =IFERROR(VLOOKUP(X56,#REF!,8,FALSE),0) -> 0 | AN56: =PROD_ID_TABLE[[#This Row],[PROD ID]] -> E MD HS URGRENKIT | AO56: =_xlfn.CONCAT(BD56:BF56) -> POLY-CRETE MD HS URETHANE CONCRETE COATINGGREENKIT | AP56: =BC56 -> 116.52 | AQ56: =BF56 -> KIT | AS56: =BE56 -> GREEN | AT56: RESUFLOR 3741 CHEMICAL RESISTANT NOVOLAC | AU56: 3 GAL | AV56: =AT56&AU56 -> RESUFLOR 3741 CHEMICAL RESISTANT NOVOLAC3 GAL | AW56: 388.66 | AY56: =_xlfn.CONCAT(AZ56:BB56) -> E MD HS URGRENKIT | AZ56: =MID(BD56,10,10) -> E MD HS UR | BA56: =LEFT(BE56,2)&RIGHT(BE56,2) -> GREN | BB56: =LEFT(BF56,3) -> KIT | BC56: =IFERROR(VLOOKUP(BD56&BF56,AV:AW,2,FALSE),0) -> 116.52 | BD56: POLY-CRETE MD HS URETHANE CONCRETE COATING | BE56: GREEN | BF56: KIT | BG56: CRETE | BH56: POLY-CRETE SL HS SELF LEVELING URETHANE | BI56: 3.4 Gal
A57: AZ | C57: X | D57: X | E57: X | I57: R-CMG-1 | J57: =_xlfn.CONCAT(K57:M57) -> CRETE COLORANTMEDIUM GRAYPINT | K57: CRETE COLORANT | L57: MEDIUM GRAY | M57: PINT | X57: S-GRY-25 | Y57: SGC Gray Pigment | Z57: =Table1[[#This Row],[D:D]] -> 484 | AA57: 25 Pint | AD57: RIO | AE57: 440 | AF57: =Table1[[#This Row],[C:C]]*1.1 -> 484 | AI57: =IFERROR(VLOOKUP(X57,#REF!,8,FALSE),0) -> 0 | AN57: =PROD_ID_TABLE[[#This Row],[PROD ID]] -> E MD HS URGRAYKIT | AO57: =_xlfn.CONCAT(BD57:BF57) -> POLY-CRETE MD HS URETHANE CONCRETE COATINGGRAYKIT | AP57: =BC57 -> 116.52 | AQ57: =BF57 -> KIT | AS57: =BE57 -> GRAY | AT57: RESUFLOR 3741 CHEMICAL RESISTANT NOVOLAC | AU57: 15 GAL | AV57: =AT57&AU57 -> RESUFLOR 3741 CHEMICAL RESISTANT NOVOLAC15 GAL | AW57: 1900.58 | AY57: =_xlfn.CONCAT(AZ57:BB57) -> E MD HS URGRAYKIT | AZ57: =MID(BD57,10,10) -> E MD HS UR | BA57: =LEFT(BE57,2)&RIGHT(BE57,2) -> GRAY | BB57: =LEFT(BF57,3) -> KIT | BC57: =IFERROR(VLOOKUP(BD57&BF57,AV:AW,2,FALSE),0) -> 116.52 | BD57: POLY-CRETE MD HS URETHANE CONCRETE COATING | BE57: GRAY | BF57: KIT | BG57: CRETE | BH57: POLY-CRETE MD HS URETHANE CONCRETE COATING | BI57: 4.9 Gal
A58: AR | D58: X | F58: X | I58: R-CRR-1 | J58: =_xlfn.CONCAT(K58:M58) -> CRETE COLORANTROTUNDA REDPINT | K58: CRETE COLORANT | L58: ROTUNDA RED | M58: PINT | X58: S-QBS-1 | Y58: Ash Flake | Z58: =Table1[[#This Row],[D:D]] -> 198 | AA58: 40lb bag | AC58: Ash | AD58: RIO | AE58: 180 | AF58: =Table1[[#This Row],[C:C]]*1.1 -> 198 | AI58: =IFERROR(VLOOKUP(X58,#REF!,8,FALSE),0) -> 0 | AN58: =PROD_ID_TABLE[[#This Row],[PROD ID]] -> E MD HS URREEDKIT | AO58: =_xlfn.CONCAT(BD58:BF58) -> POLY-CRETE MD HS URETHANE CONCRETE COATINGREDKIT | AP58: =BC58 -> 116.52 | AQ58: =BF58 -> KIT | AS58: =BE58 -> RED | AT58: RESUFLOR 3725 STATIC CONTROL EPOXY | AU58: 3 GAL | AV58: =AT58&AU58 -> RESUFLOR 3725 STATIC CONTROL EPOXY3 GAL | AW58: 790.2 | AY58: =_xlfn.CONCAT(AZ58:BB58) -> E MD HS URREEDKIT | AZ58: =MID(BD58,10,10) -> E MD HS UR | BA58: =LEFT(BE58,2)&RIGHT(BE58,2) -> REED | BB58: =LEFT(BF58,3) -> KIT | BC58: =IFERROR(VLOOKUP(BD58&BF58,AV:AW,2,FALSE),0) -> 116.52 | BD58: POLY-CRETE MD HS URETHANE CONCRETE COATING | BE58: RED | BF58: KIT | BG58: CRETE | BH58: POLY-CRETE TF PLUS COVE VERTICAL APPLICATIONS | BI58: 0.23 Gal
A59: CA | B59: X | D59: X | I59: R-CSB-1 | J59: =_xlfn.CONCAT(K59:M59) -> CRETE COLORANTSANDY BEIGEPINT | K59: CRETE COLORANT | L59: SANDY BEIGE | M59: PINT | X59: S-CSL-SB | Y59: SL - PART C | Z59: 8.338 | AA59: 20lb bag | AC59: CLEAR | AD59: RIO | AE59: 521.3 | AF59: =Table1[[#This Row],[C:C]]*1.1 -> 573.43 | AI59: =IFERROR(VLOOKUP(X59,#REF!,8,FALSE),0) -> 0 | AN59: =PROD_ID_TABLE[[#This Row],[PROD ID]] -> E TF PLUS N//AKIT | AO59: =_xlfn.CONCAT(BD59:BF59) -> POLY-CRETE TF PLUS COVE VERTICAL APPLICATIONSN/AKIT | AP59: =BC59 -> 31.8 | AQ59: =BF59 -> KIT | AS59: =BE59 -> N/A | AT59: RESUFLOR 3725 STATIC CONTROL EPOXY | AU59: 15 GAL | AV59: =AT59&AU59 -> RESUFLOR 3725 STATIC CONTROL EPOXY15 GAL | AW59: 3606 | AY59: =_xlfn.CONCAT(AZ59:BB59) -> E TF PLUS N//AKIT | AZ59: =MID(BD59,10,10) -> E TF PLUS | BA59: =LEFT(BE59,2)&RIGHT(BE59,2) -> N//A | BB59: =LEFT(BF59,3) -> KIT | BC59: =IFERROR(VLOOKUP(BD59&BF59,AV:AW,2,FALSE),0) -> 31.8 | BD59: POLY-CRETE TF PLUS COVE VERTICAL APPLICATIONS | BE59: N/A | BF59: KIT | BG59: CRETE | BH59: POLY-CRETE HF HS URETHANE CONCRETE COATING | BI59: 4 Gal
A60: CO | B60: X | D60: X | I60: R-CTR-1 | J60: =_xlfn.CONCAT(K60:M60) -> CRETE COLORANTTILE REDPINT | K60: CRETE COLORANT | L60: TILE RED | M60: PINT | X60: S-CSL-GRY | Y60: SL - PART C | Z60: 8.338 | AA60: 20lb bag | AC60: PIGMENTED | AD60: RIO | AE60: 521.3 | AF60: =Table1[[#This Row],[C:C]]*1.1 -> 573.43 | AI60: =IFERROR(VLOOKUP(X60,#REF!,8,FALSE),0) -> 0 | AN60: =PROD_ID_TABLE[[#This Row],[PROD ID]] -> E HF HS URCHALKIT | AO60: =_xlfn.CONCAT(BD60:BF60) -> POLY-CRETE HF HS URETHANE CONCRETE COATINGCHARCOALKIT | AP60: =BC60 -> 79.45 | AQ60: =BF60 -> KIT | AS60: =BE60 -> CHARCOAL | AT60: RESUTILE 4638 HS POLYURETHANE FLOOR ENAMEL | AU60: 3 GAL | AV60: =AT60&AU60 -> RESUTILE 4638 HS POLYURETHANE FLOOR ENAMEL3 GAL | AW60: 305.43 | AY60: =_xlfn.CONCAT(AZ60:BB60) -> E HF HS URCHALKIT | AZ60: =MID(BD60,10,10) -> E HF HS UR | BA60: =LEFT(BE60,2)&RIGHT(BE60,2) -> CHAL | BB60: =LEFT(BF60,3) -> KIT | BC60: =IFERROR(VLOOKUP(BD60&BF60,AV:AW,2,FALSE),0) -> 79.45 | BD60: POLY-CRETE HF HS URETHANE CONCRETE COATING | BE60: CHARCOAL | BF60: KIT | BG60: CRETE | BH60: POLY-CRETE COLOR-FAST | BI60: 0.93 GAL
A61: CT | B61: X | C61: X | D61: X | I61: R-CYL-1 | J61: =_xlfn.CONCAT(K61:M61) -> CRETE COLORANTYELLOWPINT | K61: CRETE COLORANT | L61: YELLOW | M61: PINT | X61: S-CSF-5 | Y61: SGC CRETE SF | Z61: 574.2 | AA61: 10 KITS MIN | AC61: N/A | AD61: RIO | AE61: 522 | AF61: =Table1[[#This Row],[C:C]]*1.1 -> 574.2 | AI61: =IFERROR(VLOOKUP(X61,#REF!,8,FALSE),0) -> 0 | AN61: =PROD_ID_TABLE[[#This Row],[PROD ID]] -> E HF HS URCHUTKIT | AO61: =_xlfn.CONCAT(BD61:BF61) -> POLY-CRETE HF HS URETHANE CONCRETE COATINGCHESTNUTKIT | AP61: =BC61 -> 79.45 | AQ61: =BF61 -> KIT | AS61: =BE61 -> CHESTNUT | AT61: RESUTILE 4638 HS POLYURETHANE FLOOR ENAMEL | AU61: 15 GAL | AV61: =AT61&AU61 -> RESUTILE 4638 HS POLYURETHANE FLOOR ENAMEL15 GAL | AW61: 1456.54 | AY61: =_xlfn.CONCAT(AZ61:BB61) -> E HF HS URCHUTKIT | AZ61: =MID(BD61,10,10) -> E HF HS UR | BA61: =LEFT(BE61,2)&RIGHT(BE61,2) -> CHUT | BB61: =LEFT(BF61,3) -> KIT | BC61: =IFERROR(VLOOKUP(BD61&BF61,AV:AW,2,FALSE),0) -> 79.45 | BD61: POLY-CRETE HF HS URETHANE CONCRETE COATING | BE61: CHESTNUT | BF61: KIT | BG61: CRETE | BH61: POLY-CRETE COLOR-FAST | BI61: 1.84 GAL
A62: DE | I62: S-CST-1 | J62: =_xlfn.CONCAT(K62:M62) -> CRETE COLORANTSADDLE TANPINT | K62: CRETE COLORANT | L62: SADDLE TAN | M62: PINT | X62: S-CCB-5 | Y62: SGC CRETE CB | Z62: 969.43 | AA62: 20 KITS MIN | AC62: N/A | AD62: RIO | AE62: 881.3 | AF62: =Table1[[#This Row],[C:C]]*1.1 -> 969.43 | AI62: =IFERROR(VLOOKUP(X62,#REF!,8,FALSE),0) -> 0 | AN62: =PROD_ID_TABLE[[#This Row],[PROD ID]] -> E HF HS URCOAYKIT | AO62: =_xlfn.CONCAT(BD62:BF62) -> POLY-CRETE HF HS URETHANE CONCRETE COATINGCONCRETE GRAYKIT | AP62: =BC62 -> 79.45 | AQ62: =BF62 -> KIT | AS62: =BE62 -> CONCRETE GRAY | AT62: RESUTILE 4641 HPS 100 HS ALIPHATIC URETHANE TOPCOAT | AU62: 0.9 | AV62: =AT62&AU62 -> RESUTILE 4641 HPS 100 HS ALIPHATIC URETHANE TOPCOAT0.9 | AW62: 234.81 | AY62: =_xlfn.CONCAT(AZ62:BB62) -> E HF HS URCOAYKIT | AZ62: =MID(BD62,10,10) -> E HF HS UR | BA62: =LEFT(BE62,2)&RIGHT(BE62,2) -> COAY | BB62: =LEFT(BF62,3) -> KIT | BC62: =IFERROR(VLOOKUP(BD62&BF62,AV:AW,2,FALSE),0) -> 79.45 | BD62: POLY-CRETE HF HS URETHANE CONCRETE COATING | BE62: CONCRETE GRAY | BF62: KIT | BG62: CRETE | BH62: POLY-CRETE WR COVE BASE, SLOPE/PATCHING | BI62: 3.3 Gal
A63: DC | B63: X | I63: S-GRY-1 | J63: =_xlfn.CONCAT(K63:M63) -> CRETE COLORANTGRAYPINT | K63: CRETE COLORANT | L63: GRAY | M63: PINT | X63: S-CTC-5 | Y63: SGC CRETE TC | Z63: 664.4 | AA63: 10 KITS MIN | AC63: N/A | AD63: RIO | AE63: 604 | AF63: =Table1[[#This Row],[C:C]]*1.1 -> 664.4 | AI63: =IFERROR(VLOOKUP(X63,#REF!,8,FALSE),0) -> 0 | AN63: =PROD_ID_TABLE[[#This Row],[PROD ID]] -> E HF HS URDAAYKIT | AO63: =_xlfn.CONCAT(BD63:BF63) -> POLY-CRETE HF HS URETHANE CONCRETE COATINGDARK GRAYKIT | AP63: =BC63 -> 79.45 | AQ63: =BF63 -> KIT | AS63: =BE63 -> DARK GRAY | AT63: RESUTILE 4641 HPS 100 HS ALIPHATIC URETHANE TOPCOAT | AU63: 1.8 | AV63: =AT63&AU63 -> RESUTILE 4641 HPS 100 HS ALIPHATIC URETHANE TOPCOAT1.8 | AW63: 416.07 | AY63: =_xlfn.CONCAT(AZ63:BB63) -> E HF HS URDAAYKIT | AZ63: =MID(BD63,10,10) -> E HF HS UR | BA63: =LEFT(BE63,2)&RIGHT(BE63,2) -> DAAY | BB63: =LEFT(BF63,3) -> KIT | BC63: =IFERROR(VLOOKUP(BD63&BF63,AV:AW,2,FALSE),0) -> 79.45 | BD63: POLY-CRETE HF HS URETHANE CONCRETE COATING | BE63: DARK GRAY | BF63: KIT | BG63: CRETE | BH63: POLY-CRETE HF ACCELERATOR LOW TEMPERATURE AID | BI63: 1 Qt
A64: FL | B64: X | D64: X | I64: R-CBG-25 | J64: =_xlfn.CONCAT(K64:M64) -> CRETE COLORANT - LARGEBATTLESHIP GRAY25 PINTS | K64: CRETE COLORANT - LARGE | L64: BATTLESHIP GRAY | M64: 25 PINTS | X64: S-QMT-1 | Y64: Malt Quartz | Z64: =Table1[[#This Row],[D:D]] -> 33 | AA64: 50lb bag | AC64: Malt | AD64: RIO | AE64: 30 | AF64: =Table1[[#This Row],[C:C]]*1.1 -> 33 | AI64: =IFERROR(VLOOKUP(X64,#REF!,8,FALSE),0) -> 0 | AN64: =PROD_ID_TABLE[[#This Row],[PROD ID]] -> E HF HS URGRENKIT | AO64: =_xlfn.CONCAT(BD64:BF64) -> POLY-CRETE HF HS URETHANE CONCRETE COATINGGREENKIT | AP64: =BC64 -> 79.45 | AQ64: =BF64 -> KIT | AS64: =BE64 -> GREEN | AT64: RESUTILE 4641 HPS 100 HS ALIPHATIC URETHANE TOPCOAT | AU64: 4.7 | AV64: =AT64&AU64 -> RESUTILE 4641 HPS 100 HS ALIPHATIC URETHANE TOPCOAT4.7 | AW64: 798.01 | AY64: =_xlfn.CONCAT(AZ64:BB64) -> E HF HS URGRENKIT | AZ64: =MID(BD64,10,10) -> E HF HS UR | BA64: =LEFT(BE64,2)&RIGHT(BE64,2) -> GREN | BB64: =LEFT(BF64,3) -> KIT | BC64: =IFERROR(VLOOKUP(BD64&BF64,AV:AW,2,FALSE),0) -> 79.45 | BD64: POLY-CRETE HF HS URETHANE CONCRETE COATING | BE64: GREEN | BF64: KIT | BG64: CRETE
A65: GA | B65: X | I65: R-CMG-25 | J65: =_xlfn.CONCAT(K65:M65) -> CRETE COLORANT - LARGEMEDIUM GRAY25 PINTS | K65: CRETE COLORANT - LARGE | L65: MEDIUM GRAY | M65: 25 PINTS | X65: S-QSA-1 | Y65: Ash Quartz | Z65: =Table1[[#This Row],[D:D]] -> 33 | AA65: 50lb bag | AC65: Ash | AD65: RIO | AE65: 30 | AF65: =Table1[[#This Row],[C:C]]*1.1 -> 33 | AI65: =IFERROR(VLOOKUP(X65,#REF!,8,FALSE),0) -> 0 | AN65: =PROD_ID_TABLE[[#This Row],[PROD ID]] -> E HF HS URGRAYKIT | AO65: =_xlfn.CONCAT(BD65:BF65) -> POLY-CRETE HF HS URETHANE CONCRETE COATINGGRAYKIT | AP65: =BC65 -> 79.45 | AQ65: =BF65 -> KIT | AS65: =BE65 -> GRAY | AT65: RESUTILE 4640 HTS 100 HS HIGH TRAFFIC URETHANE ENAMEL | AU65: 2.2 | AV65: =AT65&AU65 -> RESUTILE 4640 HTS 100 HS HIGH TRAFFIC URETHANE ENAMEL2.2 | AW65: 478.45 | AY65: =_xlfn.CONCAT(AZ65:BB65) -> E HF HS URGRAYKIT | AZ65: =MID(BD65,10,10) -> E HF HS UR | BA65: =LEFT(BE65,2)&RIGHT(BE65,2) -> GRAY | BB65: =LEFT(BF65,3) -> KIT | BC65: =IFERROR(VLOOKUP(BD65&BF65,AV:AW,2,FALSE),0) -> 79.45 | BD65: POLY-CRETE HF HS URETHANE CONCRETE COATING | BE65: GRAY | BF65: KIT | BG65: CRETE
A66: HI | B66: X | C66: X | I66: R-CSB-25 | J66: =_xlfn.CONCAT(K66:M66) -> CRETE COLORANT - LARGESANDY BEIGE25 PINTS | K66: CRETE COLORANT - LARGE | L66: SANDY BEIGE | M66: 25 PINTS | X66: S-QSM-1 | Y66: Gray (Smoke) Quartz | Z66: =Table1[[#This Row],[D:D]] -> 33 | AA66: 50lb bag | AC66: Gray | AD66: RIO | AE66: 30 | AF66: =Table1[[#This Row],[C:C]]*1.1 -> 33 | AI66: =IFERROR(VLOOKUP(X66,#REF!,8,FALSE),0) -> 0 | AN66: =PROD_ID_TABLE[[#This Row],[PROD ID]] -> E HF HS URREEDKIT | AO66: =_xlfn.CONCAT(BD66:BF66) -> POLY-CRETE HF HS URETHANE CONCRETE COATINGREDKIT | AP66: =BC66 -> 79.45 | AQ66: =BF66 -> KIT | AS66: =BE66 -> RED | AT66: RESUTILE 4640 HTS 100 HS HIGH TRAFFIC URETHANE ENAMEL | AU66: 5.75 | AV66: =AT66&AU66 -> RESUTILE 4640 HTS 100 HS HIGH TRAFFIC URETHANE ENAMEL5.75 | AW66: 948.07 | AY66: =_xlfn.CONCAT(AZ66:BB66) -> E HF HS URREEDKIT | AZ66: =MID(BD66,10,10) -> E HF HS UR | BA66: =LEFT(BE66,2)&RIGHT(BE66,2) -> REED | BB66: =LEFT(BF66,3) -> KIT | BC66: =IFERROR(VLOOKUP(BD66&BF66,AV:AW,2,FALSE),0) -> 79.45 | BD66: POLY-CRETE HF HS URETHANE CONCRETE COATING | BE66: RED | BF66: KIT | BG66: CRETE
A67: ID | B67: X | D67: X | I67: S-CST-25 | J67: =_xlfn.CONCAT(K67:M67) -> CRETE COLORANT - LARGESADDLE TAN25 PINTS | K67: CRETE COLORANT - LARGE | L67: SADDLE TAN | M67: 25 PINTS | X67: S-QST-1 | Y67: Gray (Smoke) Trowel Quartz | Z67: =Table1[[#This Row],[D:D]] -> 33 | AA67: 50lb bag | AC67: Solid Smoke | AD67: RIO | AE67: 30 | AF67: =Table1[[#This Row],[C:C]]*1.1 -> 33 | AI67: =IFERROR(VLOOKUP(X67,#REF!,8,FALSE),0) -> 0 | AN67: =PROD_ID_TABLE[[#This Row],[PROD ID]] -> E COLOR-FABLUEKIT | AO67: =_xlfn.CONCAT(BD67:BF67) -> POLY-CRETE COLOR-FASTBLUEKIT | AP67: =BC67 -> 154.78 | AQ67: =BF67 -> KIT | AS67: =BE67 -> BLUE | AT67: RESUTILE AQUA 4411 WB ALIPHATIC URETHANE - CLEAR | AU67: 1.25 GAL | AV67: =AT67&AU67 -> RESUTILE AQUA 4411 WB ALIPHATIC URETHANE - CLEAR1.25 GAL | AW67: 143.01 | AY67: =_xlfn.CONCAT(AZ67:BB67) -> E COLOR-FABLUEKIT | AZ67: =MID(BD67,10,10) -> E COLOR-FA | BA67: =LEFT(BE67,2)&RIGHT(BE67,2) -> BLUE | BB67: =LEFT(BF67,3) -> KIT | BC67: =IFERROR(VLOOKUP(BD67&BF67,AV:AW,2,FALSE),0) -> 154.78 | BD67: POLY-CRETE COLOR-FAST | BE67: BLUE | BF67: KIT | BG67: CRETE
A68: IL | B68: X | I68: S-GRY-25 | J68: =_xlfn.CONCAT(K68:M68) -> CRETE COLORANT - LARGEGRAY25 PINTS | K68: CRETE COLORANT - LARGE | L68: GRAY | M68: 25 PINTS | X68: S-RS88-ARG1 | Y68: RS88 Gray Area | Z68: =Table1[[#This Row],[D:D]] -> 44 | AA68: Tube | AC68: Gray Area | AD68: RIO | AE68: 40 | AF68: =Table1[[#This Row],[C:C]]*1.1 -> 44 | AI68: =IFERROR(VLOOKUP(X68,#REF!,8,FALSE),0) -> 0 | AN68: =PROD_ID_TABLE[[#This Row],[PROD ID]] -> E COLOR-FACHALKIT | AO68: =_xlfn.CONCAT(BD68:BF68) -> POLY-CRETE COLOR-FASTCHARCOALKIT | AP68: =BC68 -> 154.78 | AQ68: =BF68 -> KIT | AS68: =BE68 -> CHARCOAL | AT68: RESUTILE AQUA 4411 WB ALIPHATIC URETHANE - CLEAR | AU68: 5 GAL | AV68: =AT68&AU68 -> RESUTILE AQUA 4411 WB ALIPHATIC URETHANE - CLEAR5 GAL | AW68: 563.78 | AY68: =_xlfn.CONCAT(AZ68:BB68) -> E COLOR-FACHALKIT | AZ68: =MID(BD68,10,10) -> E COLOR-FA | BA68: =LEFT(BE68,2)&RIGHT(BE68,2) -> CHAL | BB68: =LEFT(BF68,3) -> KIT | BC68: =IFERROR(VLOOKUP(BD68&BF68,AV:AW,2,FALSE),0) -> 154.78 | BD68: POLY-CRETE COLOR-FAST | BE68: CHARCOAL | BF68: KIT | BG68: CRETE
A69: IN | B69: X | I69: S-UPA-3 | J69: =_xlfn.CONCAT(K69:M69) -> SGC COAT UPAN/A3 GAL | K69: SGC COAT UPA | L69: N/A | M69: 3 GAL | P69: A | Q69: 0.25 | R69: =5/Q69 -> 20 | S69: 210 | X69: S-RS88-CG1 | Y69: RS88 Chateau Gray | Z69: =Table1[[#This Row],[D:D]] -> 38.5 | AA69: Tube | AC69: Chateau Gray | AD69: RIO | AE69: 35 | AF69: =Table1[[#This Row],[C:C]]*1.1 -> 38.5 | AI69: =IFERROR(VLOOKUP(X69,#REF!,8,FALSE),0) -> 0 | AN69: =PROD_ID_TABLE[[#This Row],[PROD ID]] -> E COLOR-FACHUTKIT | AO69: =_xlfn.CONCAT(BD69:BF69) -> POLY-CRETE COLOR-FASTCHESTNUTKIT | AP69: =BC69 -> 154.78 | AQ69: =BF69 -> KIT | AS69: =BE69 -> CHESTNUT | AT69: RESUTILE AQUA 4410 WB ALIPHATIC URETHANE - COLOR | AU69: 1.25 GAL | AV69: =AT69&AU69 -> RESUTILE AQUA 4410 WB ALIPHATIC URETHANE - COLOR1.25 GAL | AW69: 132.41 | AY69: =_xlfn.CONCAT(AZ69:BB69) -> E COLOR-FACHUTKIT | AZ69: =MID(BD69,10,10) -> E COLOR-FA | BA69: =LEFT(BE69,2)&RIGHT(BE69,2) -> CHUT | BB69: =LEFT(BF69,3) -> KIT | BC69: =IFERROR(VLOOKUP(BD69&BF69,AV:AW,2,FALSE),0) -> 154.78 | BD69: POLY-CRETE COLOR-FAST | BE69: CHESTNUT | BF69: KIT | BG69: CRETE
A70: KS | F70: X | I70: R-ETM-C50 | J70: =_xlfn.CONCAT(K70:M70) -> RIO TROWEL CLAD SANDN/A50LB | K70: RIO TROWEL CLAD SAND | L70: N/A | M70: 50LB | P70: B | Q70: 0.25 | R70: =5/Q70 -> 20 | S70: 210 | X70: S-RS88-SG1 | Y70: RS88 Standard Gray | Z70: =Table1[[#This Row],[D:D]] -> 38.5 | AA70: Tube | AC70: Standard Gray | AD70: RIO | AE70: 35 | AF70: =Table1[[#This Row],[C:C]]*1.1 -> 38.5 | AI70: =IFERROR(VLOOKUP(X70,#REF!,8,FALSE),0) -> 0 | AN70: =PROD_ID_TABLE[[#This Row],[PROD ID]] -> E COLOR-FADAAYKIT | AO70: =_xlfn.CONCAT(BD70:BF70) -> POLY-CRETE COLOR-FASTDARK GRAYKIT | AP70: =BC70 -> 154.78 | AQ70: =BF70 -> KIT | AS70: =BE70 -> DARK GRAY | AT70: RESUTILE AQUA 4410 WB ALIPHATIC URETHANE - COLOR | AU70: 5 GAL | AV70: =AT70&AU70 -> RESUTILE AQUA 4410 WB ALIPHATIC URETHANE - COLOR5 GAL | AW70: 497.28 | AY70: =_xlfn.CONCAT(AZ70:BB70) -> E COLOR-FADAAYKIT | AZ70: =MID(BD70,10,10) -> E COLOR-FA | BA70: =LEFT(BE70,2)&RIGHT(BE70,2) -> DAAY | BB70: =LEFT(BF70,3) -> KIT | BC70: =IFERROR(VLOOKUP(BD70&BF70,AV:AW,2,FALSE),0) -> 154.78 | BD70: POLY-CRETE COLOR-FAST | BE70: DARK GRAY | BF70: KIT | BG70: CRETE
A71: KY | B71: X | C71: X | D71: X | I71: R-EMP-3 | J71: =_xlfn.CONCAT(K71:M71) -> RIO COAT EMPN/A3 GAL | K71: RIO COAT EMP | L71: N/A | M71: 3 GAL | P71: CB | Q71: 1 | R71: =R70 -> 20 | S71: =T71*R71 -> 333.8 | T71: 16.69 | X71: S-SCS-1 | Y71: SGC Speed | Z71: =Table1[[#This Row],[D:D]] -> 55 | AA71: 32 oz | AD71: RIO | AE71: 50 | AF71: =Table1[[#This Row],[C:C]]*1.1 -> 55 | AI71: =IFERROR(VLOOKUP(X71,#REF!,8,FALSE),0) -> 0 | AN71: =PROD_ID_TABLE[[#This Row],[PROD ID]] -> E COLOR-FAGRENKIT | AO71: =_xlfn.CONCAT(BD71:BF71) -> POLY-CRETE COLOR-FASTGREENKIT | AP71: =BC71 -> 154.78 | AQ71: =BF71 -> KIT | AS71: =BE71 -> GREEN | AT71: ACCELERA EXT SMALL 1R:1H | AU71: 0.25 GAL | AV71: =AT71&AU71 -> ACCELERA EXT SMALL 1R:1H0.25 GAL | AW71: 53.55 | AY71: =_xlfn.CONCAT(AZ71:BB71) -> E COLOR-FAGRENKIT | AZ71: =MID(BD71,10,10) -> E COLOR-FA | BA71: =LEFT(BE71,2)&RIGHT(BE71,2) -> GREN | BB71: =LEFT(BF71,3) -> KIT | BC71: =IFERROR(VLOOKUP(BD71&BF71,AV:AW,2,FALSE),0) -> 154.78 | BD71: POLY-CRETE COLOR-FAST | BE71: GREEN | BF71: KIT | BG71: CRETE
A72: LA | B72: X | I72: R-EMP-15 | J72: =_xlfn.CONCAT(K72:M72) -> RIO COAT EMPN/A15 GAL | K72: RIO COAT EMP | L72: N/A | M72: 15 GAL | P72: PIG | Q72: =3/12 -> 0.25 | R72: =ROUNDUP(Q72*R69,0) -> 5 | S72: =R72*T72 -> 127.5 | T72: 25.5 | X72: S-SPS-2.5 | Y72: SGC Polyaspartic 2.5 gal Kit (100% Solid) | Z72: =Table1[[#This Row],[D:D]] -> 330 | AA72: 2.5 gal kit | AD72: RIO | AE72: 300 | AF72: =Table1[[#This Row],[C:C]]*1.1 -> 330 | AI72: =IFERROR(VLOOKUP(X72,#REF!,8,FALSE),0) -> 0 | AN72: =PROD_ID_TABLE[[#This Row],[PROD ID]] -> E COLOR-FAGRAYKIT | AO72: =_xlfn.CONCAT(BD72:BF72) -> POLY-CRETE COLOR-FASTGRAYKIT | AP72: =BC72 -> 154.78 | AQ72: =BF72 -> KIT | AS72: =BE72 -> GRAY | AT72: ACCELERA EXT SMALL 1R:1H | AU72: 0.75 GAL | AV72: =AT72&AU72 -> ACCELERA EXT SMALL 1R:1H0.75 GAL | AW72: 127.12 | AY72: =_xlfn.CONCAT(AZ72:BB72) -> E COLOR-FAGRAYKIT | AZ72: =MID(BD72,10,10) -> E COLOR-FA | BA72: =LEFT(BE72,2)&RIGHT(BE72,2) -> GRAY | BB72: =LEFT(BF72,3) -> KIT | BC72: =IFERROR(VLOOKUP(BD72&BF72,AV:AW,2,FALSE),0) -> 154.78 | BD72: POLY-CRETE COLOR-FAST | BE72: GRAY | BF72: KIT | BG72: CRETE
A73: ME | B73: X | I73: R-CSB-25 | J73: =_xlfn.CONCAT(K73:M73) -> CRETE COLORANT - LARGESANDY BEIGE25 PINTS | K73: CRETE COLORANT - LARGE | L73: SANDY BEIGE | M73: 25 PINTS | P73: 28LB | S73: =SUM(S69:S72) -> 881.3 | X73: S-SPS-25 | Y73: SGC Polyaspartic 25 gal Kit (100% Solid) | Z73: =Table1[[#This Row],[D:D]] -> 3190 | AA73: 25 gal kit | AD73: RIO | AE73: 2900 | AF73: =Table1[[#This Row],[C:C]]*1.1 -> 3190 | AI73: =IFERROR(VLOOKUP(X73,#REF!,8,FALSE),0) -> 0 | AN73: =PROD_ID_TABLE[[#This Row],[PROD ID]] -> E COLOR-FAREEDKIT | AO73: =_xlfn.CONCAT(BD73:BF73) -> POLY-CRETE COLOR-FASTREDKIT | AP73: =BC73 -> 154.78 | AQ73: =BF73 -> KIT | AS73: =BE73 -> RED | AT73: ACCELERA EXT SMALL 1R:1H | AU73: 1.5 GAL | AV73: =AT73&AU73 -> ACCELERA EXT SMALL 1R:1H1.5 GAL | AW73: 253.64 | AY73: =_xlfn.CONCAT(AZ73:BB73) -> E COLOR-FAREEDKIT | AZ73: =MID(BD73,10,10) -> E COLOR-FA | BA73: =LEFT(BE73,2)&RIGHT(BE73,2) -> REED | BB73: =LEFT(BF73,3) -> KIT | BC73: =IFERROR(VLOOKUP(BD73&BF73,AV:AW,2,FALSE),0) -> 154.78 | BD73: POLY-CRETE COLOR-FAST | BE73: RED | BF73: KIT | BG73: CRETE
A74: MD | B74: X | D74: X | I74: S-CSL-SB | J74: =_xlfn.CONCAT(K74:M74) -> SL - PART CPIGMENTEDKIT | K74: SL - PART C | L74: PIGMENTED | M74: KIT | X74: 91336 | Y74: SIKAQUICK 1000 | Z74: 28.31 | AA74: 50LB | AD74: SIKA | AF74: =Table1[[#This Row],[C:C]]*1.1 -> 0 | AI74: =IFERROR(VLOOKUP(X74,#REF!,8,FALSE),0) -> 0 | AN74: =PROD_ID_TABLE[[#This Row],[PROD ID]] -> E COLOR-FABLUEKIT | AO74: =_xlfn.CONCAT(BD74:BF74) -> POLY-CRETE COLOR-FASTBLUEKIT | AP74: =BC74 -> 154.78 | AQ74: =BF74 -> KIT | AS74: =BE74 -> BLUE | AT74: ACCELERA ONE RESIN (SEE MIX CHART) | AU74: 5 GAL | AV74: =AT74&AU74 -> ACCELERA ONE RESIN (SEE MIX CHART)5 GAL | AW74: 684.43 | AY74: =_xlfn.CONCAT(AZ74:BB74) -> E COLOR-FABLUEKIT | AZ74: =MID(BD74,10,10) -> E COLOR-FA | BA74: =LEFT(BE74,2)&RIGHT(BE74,2) -> BLUE | BB74: =LEFT(BF74,3) -> KIT | BC74: =IFERROR(VLOOKUP(BD74&BF74,AV:AW,2,FALSE),0) -> 154.78 | BD74: POLY-CRETE COLOR-FAST | BE74: BLUE | BF74: KIT | BG74: CRETE
A75: MA | B75: X | C75: X | D75: X | I75: S-R88-ARG2 | J75: =_xlfn.CONCAT(K75:M75) -> RS88 (12 TUBES / CASE)GRAY AREACASE | K75: RS88 (12 TUBES / CASE) | L75: GRAY AREA | M75: CASE | X75: 187543 | Y75: SIKAFLOOR-265 FLEXABLE MEMBRANE W/ CRACK BRIDGING | Z75: 798.39 | AA75: 10 GAL | AD75: SIKA | AF75: =Table1[[#This Row],[C:C]]*1.1 -> 0 | AI75: =IFERROR(VLOOKUP(X75,#REF!,8,FALSE),0) -> 0 | AN75: =PROD_ID_TABLE[[#This Row],[PROD ID]] -> E COLOR-FACHALKIT | AO75: =_xlfn.CONCAT(BD75:BF75) -> POLY-CRETE COLOR-FASTCHARCOALKIT | AP75: =BC75 -> 154.78 | AQ75: =BF75 -> KIT | AS75: =BE75 -> CHARCOAL | AT75: ACCELERA ONE HARDENER (SEE MIX CHART) | AU75: 1 GAL | AV75: =AT75&AU75 -> ACCELERA ONE HARDENER (SEE MIX CHART)1 GAL | AW75: 362.52 | AY75: =_xlfn.CONCAT(AZ75:BB75) -> E COLOR-FACHALKIT | AZ75: =MID(BD75,10,10) -> E COLOR-FA | BA75: =LEFT(BE75,2)&RIGHT(BE75,2) -> CHAL | BB75: =LEFT(BF75,3) -> KIT | BC75: =IFERROR(VLOOKUP(BD75&BF75,AV:AW,2,FALSE),0) -> 154.78 | BD75: POLY-CRETE COLOR-FAST | BE75: CHARCOAL | BF75: KIT | BG75: CRETE
A76: MI | B76: X | D76: X | I76: S-R88-SG2 | J76: =_xlfn.CONCAT(K76:M76) -> RS88 (12 TUBES / CASE)STANDARD GRAYCASE | K76: RS88 (12 TUBES / CASE) | L76: STANDARD GRAY | M76: CASE | X76: 402892 | Y76: SIKAFLOOR-315 ABRASION RESISTANT ALIPHATIC | Z76: 777.14 | AA76: 4.68 GAL | AC76: CLEAR | AD76: SIKA | AF76: =Table1[[#This Row],[C:C]]*1.1 -> 0 | AI76: =IFERROR(VLOOKUP(X76,#REF!,8,FALSE),0) -> 0 | AN76: =PROD_ID_TABLE[[#This Row],[PROD ID]] -> E COLOR-FACHUTKIT | AO76: =_xlfn.CONCAT(BD76:BF76) -> POLY-CRETE COLOR-FASTCHESTNUTKIT | AP76: =BC76 -> 154.78 | AQ76: =BF76 -> KIT | AS76: =BE76 -> CHESTNUT | AT76: ACCELERA 5 66% SOLIDS 1:1 | AU76: 2 GAL | AV76: =AT76&AU76 -> ACCELERA 5 66% SOLIDS 1:12 GAL | AW76: 168.31 | AY76: =_xlfn.CONCAT(AZ76:BB76) -> E COLOR-FACHUTKIT | AZ76: =MID(BD76,10,10) -> E COLOR-FA | BA76: =LEFT(BE76,2)&RIGHT(BE76,2) -> CHUT | BB76: =LEFT(BF76,3) -> KIT | BC76: =IFERROR(VLOOKUP(BD76&BF76,AV:AW,2,FALSE),0) -> 154.78 | BD76: POLY-CRETE COLOR-FAST | BE76: CHESTNUT | BF76: KIT | BG76: CRETE
A77: MN | B77: X | C77: X | D77: X | I77: S-R88-CG2 | J77: =_xlfn.CONCAT(K77:M77) -> RS88 (12 TUBES / CASE)CHATEAU GRAYCASE | K77: RS88 (12 TUBES / CASE) | L77: CHATEAU GRAY | M77: CASE | P77: A | Q77: 0.5 | R77: =5/Q77 -> 10 | S77: 210 | X77: 402984 | Y77: SIKAFLOOR-315 ABRASION RESISTANT ALIPHATIC | Z77: 777.49 | AA77: 4.68 GAL | AC77: COLOR | AD77: SIKA | AF77: =Table1[[#This Row],[C:C]]*1.1 -> 0 | AI77: =IFERROR(VLOOKUP(X77,#REF!,8,FALSE),0) -> 0 | AN77: =PROD_ID_TABLE[[#This Row],[PROD ID]] -> E COLOR-FADAAYKIT | AO77: =_xlfn.CONCAT(BD77:BF77) -> POLY-CRETE COLOR-FASTDARK GRAYKIT | AP77: =BC77 -> 154.78 | AQ77: =BF77 -> KIT | AS77: =BE77 -> DARK GRAY | AT77: ACCELERA 5 66% SOLIDS 1:1 | AU77: 10 GAL | AV77: =AT77&AU77 -> ACCELERA 5 66% SOLIDS 1:110 GAL | AW77: 800.36 | AY77: =_xlfn.CONCAT(AZ77:BB77) -> E COLOR-FADAAYKIT | AZ77: =MID(BD77,10,10) -> E COLOR-FA | BA77: =LEFT(BE77,2)&RIGHT(BE77,2) -> DAAY | BB77: =LEFT(BF77,3) -> KIT | BC77: =IFERROR(VLOOKUP(BD77&BF77,AV:AW,2,FALSE),0) -> 154.78 | BD77: POLY-CRETE COLOR-FAST | BE77: DARK GRAY | BF77: KIT | BG77: CRETE
A78: MS | B78: X | D78: X | I78: S-R88-CG2 | J78: =_xlfn.CONCAT(K78:M78) -> RS88 (12 TUBES / CASE)BRICKPAVER REDCASE | K78: RS88 (12 TUBES / CASE) | L78: BRICKPAVER RED | M78: CASE | P78: B | Q78: 0.5 | R78: =5/Q78 -> 10 | S78: 210 | X78: 436246 | Y78: SIKAFLOOR-510 LPL HS UV RESISTANT POLYASPARTIC | Z78: 934.96 | AA78: 8.33 GAL | AD78: SIKA | AF78: =Table1[[#This Row],[C:C]]*1.1 -> 0 | AI78: =IFERROR(VLOOKUP(X78,#REF!,8,FALSE),0) -> 0 | AN78: =PROD_ID_TABLE[[#This Row],[PROD ID]] -> E COLOR-FAGRENKIT | AO78: =_xlfn.CONCAT(BD78:BF78) -> POLY-CRETE COLOR-FASTGREENKIT | AP78: =BC78 -> 154.78 | AQ78: =BF78 -> KIT | AS78: =BE78 -> GREEN | AT78: CEMLACK UM. URETHANE CEMENT PATCH 1:1:1 | AU78: 44 LBS | AV78: =AT78&AU78 -> CEMLACK UM. URETHANE CEMENT PATCH 1:1:144 LBS | AW78: 47.67 | AY78: =_xlfn.CONCAT(AZ78:BB78) -> E COLOR-FAGRENKIT | AZ78: =MID(BD78,10,10) -> E COLOR-FA | BA78: =LEFT(BE78,2)&RIGHT(BE78,2) -> GREN | BB78: =LEFT(BF78,3) -> KIT | BC78: =IFERROR(VLOOKUP(BD78&BF78,AV:AW,2,FALSE),0) -> 154.78 | BD78: POLY-CRETE COLOR-FAST | BE78: GREEN | BF78: KIT | BG78: CRETE
A79: MO | B79: X | D79: X | I79: S-R88-CG2 | J79: =_xlfn.CONCAT(K79:M79) -> RS88 (12 TUBES / CASE)OTHERCASE | K79: RS88 (12 TUBES / CASE) | L79: OTHER | M79: CASE | P79: SL | Q79: 1 | R79: =R78 -> 10 | S79: =T79*R79 -> 75.8 | T79: 7.58 | X79: 455082 | Y79: SIKAFLOOR-161 VERSATILE EPOXY PRIMER | Z79: 241.04 | AA79: 4.5 GAL | AD79: SIKA | AF79: =Table1[[#This Row],[C:C]]*1.1 -> 0 | AI79: =IFERROR(VLOOKUP(X79,#REF!,8,FALSE),0) -> 0 | AN79: =PROD_ID_TABLE[[#This Row],[PROD ID]] -> E COLOR-FAGRAYKIT | AO79: =_xlfn.CONCAT(BD79:BF79) -> POLY-CRETE COLOR-FASTGRAYKIT | AP79: =BC79 -> 154.78 | AQ79: =BF79 -> KIT | AS79: =BE79 -> GRAY | AT79: RESUFLOR PT 250 THICKENED EPOXY 2:1 | AU79: 15 GAL | AV79: =AT79&AU79 -> RESUFLOR PT 250 THICKENED EPOXY 2:115 GAL | AW79: 1053.42 | AY79: =_xlfn.CONCAT(AZ79:BB79) -> E COLOR-FAGRAYKIT | AZ79: =MID(BD79,10,10) -> E COLOR-FA | BA79: =LEFT(BE79,2)&RIGHT(BE79,2) -> GRAY | BB79: =LEFT(BF79,3) -> KIT | BC79: =IFERROR(VLOOKUP(BD79&BF79,AV:AW,2,FALSE),0) -> 154.78 | BD79: POLY-CRETE COLOR-FAST | BE79: GRAY | BF79: KIT | BG79: CRETE
A80: MT | I80: S-RS88-ARG1 | J80: =_xlfn.CONCAT(K80:M80) -> RS88 (12 TUBES / CASE)GRAY AREATUBE | K80: RS88 (12 TUBES / CASE) | L80: GRAY AREA | M80: TUBE | P80: PIG | Q80: =1/12 -> 0.083333333 | R80: =ROUNDUP(Q80*R77,0) -> 1 | S80: =R80*T80 -> 25.5 | T80: 25.5 | X80: 455425 | Y80: SIKAFLOOR-264 VERSATILE PIGMENTED EPOXY | Z80: 292.99 | AA80: 4.5 GAL | AC80: SILVER GRAY | AD80: SIKA | AF80: =Table1[[#This Row],[C:C]]*1.1 -> 0 | AI80: =IFERROR(VLOOKUP(X80,#REF!,8,FALSE),0) -> 0 | AN80: =PROD_ID_TABLE[[#This Row],[PROD ID]] -> E COLOR-FAREEDKIT | AO80: =_xlfn.CONCAT(BD80:BF80) -> POLY-CRETE COLOR-FASTREDKIT | AP80: =BC80 -> 154.78 | AQ80: =BF80 -> KIT | AS80: =BE80 -> RED | AT80: RESUFLOR NO SAG | AU80: 10 LBS | AV80: =AT80&AU80 -> RESUFLOR NO SAG10 LBS | AW80: 341.9 | AY80: =_xlfn.CONCAT(AZ80:BB80) -> E COLOR-FAREEDKIT | AZ80: =MID(BD80,10,10) -> E COLOR-FA | BA80: =LEFT(BE80,2)&RIGHT(BE80,2) -> REED | BB80: =LEFT(BF80,3) -> KIT | BC80: =IFERROR(VLOOKUP(BD80&BF80,AV:AW,2,FALSE),0) -> 154.78 | BD80: POLY-CRETE COLOR-FAST | BE80: RED | BF80: KIT | BG80: CRETE
A81: NE | B81: X | C81: X | I81: S-RS88-SG1 | J81: =_xlfn.CONCAT(K81:M81) -> RS88 (12 TUBES / CASE)STANDARD GRAYTUBE | K81: RS88 (12 TUBES / CASE) | L81: STANDARD GRAY | M81: TUBE | P81: 20LB | S81: =SUM(S77:S80) -> 521.3 | X81: 455426 | Y81: SIKAFLOOR-264 VERSATILE PIGMENTED EPOXY | Z81: 292.99 | AA81: 4.5 GAL | AC81: BASALT GRAY | AD81: SIKA | AF81: =Table1[[#This Row],[C:C]]*1.1 -> 0 | AI81: =IFERROR(VLOOKUP(X81,#REF!,8,FALSE),0) -> 0 | AN81: =PROD_ID_TABLE[[#This Row],[PROD ID]] -> E WR COVE BLUEKIT | AO81: =_xlfn.CONCAT(BD81:BF81) -> POLY-CRETE WR COVE BASE, SLOPE/PATCHINGBLUEKIT | AP81: =BC81 -> 57.67 | AQ81: =BF81 -> KIT | AS81: =BE81 -> BLUE | AT81: Q-ROCK 16 GRIT | AU81: 50LB BAG | AV81: =AT81&AU81 -> Q-ROCK 16 GRIT50LB BAG | AW81: 16 | AY81: =_xlfn.CONCAT(AZ81:BB81) -> E WR COVE BLUEKIT | AZ81: =MID(BD81,10,10) -> E WR COVE | BA81: =LEFT(BE81,2)&RIGHT(BE81,2) -> BLUE | BB81: =LEFT(BF81,3) -> KIT | BC81: =IFERROR(VLOOKUP(BD81&BF81,AV:AW,2,FALSE),0) -> 57.67 | BD81: POLY-CRETE WR COVE BASE, SLOPE/PATCHING | BE81: BLUE | BF81: KIT | BG81: CRETE
A82: NV | B82: X | D82: X | I82: S-RS88-CG1 | J82: =_xlfn.CONCAT(K82:M82) -> RS88 (12 TUBES / CASE)CHATEAU GRAYTUBE | K82: RS88 (12 TUBES / CASE) | L82: CHATEAU GRAY | M82: TUBE | X82: 455427 | Y82: SIKAFLOOR-264 VERSATILE PIGMENTED EPOXY | Z82: 292.99 | AA82: 4.5 GAL | AC82: LIGHT GRAY | AD82: SIKA | AF82: =Table1[[#This Row],[C:C]]*1.1 -> 0 | AI82: =IFERROR(VLOOKUP(X82,#REF!,8,FALSE),0) -> 0 | AN82: =PROD_ID_TABLE[[#This Row],[PROD ID]] -> E WR COVE CHALKIT | AO82: =_xlfn.CONCAT(BD82:BF82) -> POLY-CRETE WR COVE BASE, SLOPE/PATCHINGCHARCOALKIT | AP82: =BC82 -> 57.67 | AQ82: =BF82 -> KIT | AS82: =BE82 -> CHARCOAL | AT82: 1-8IN DECO FLAKE - 40LB BAG | AU82: 40LB BAG | AV82: =AT82&AU82 -> 1-8IN DECO FLAKE - 40LB BAG40LB BAG | AW82: 110 | AY82: =_xlfn.CONCAT(AZ82:BB82) -> E WR COVE CHALKIT | AZ82: =MID(BD82,10,10) -> E WR COVE | BA82: =LEFT(BE82,2)&RIGHT(BE82,2) -> CHAL | BB82: =LEFT(BF82,3) -> KIT | BC82: =IFERROR(VLOOKUP(BD82&BF82,AV:AW,2,FALSE),0) -> 57.67 | BD82: POLY-CRETE WR COVE BASE, SLOPE/PATCHING | BE82: CHARCOAL | BF82: KIT | BG82: CRETE
A83: NH | I83: S-RS88-SG1 | J83: =_xlfn.CONCAT(K83:M83) -> RS88 (12 TUBES / CASE)BRICKPAVER REDTUBE | K83: RS88 (12 TUBES / CASE) | L83: BRICKPAVER RED | M83: TUBE | P83: A | Q83: 0.5 | R83: =5/Q83 -> 10 | S83: 210 | X83: 455429 | Y83: SIKAFLOOR-264 VERSATILE PIGMENTED EPOXY | Z83: 292.99 | AA83: 4.5 GAL | AC83: WINDOW GRAY | AD83: SIKA | AF83: =Table1[[#This Row],[C:C]]*1.1 -> 0 | AI83: =IFERROR(VLOOKUP(X83,#REF!,8,FALSE),0) -> 0 | AN83: =PROD_ID_TABLE[[#This Row],[PROD ID]] -> E WR COVE CHUTKIT | AO83: =_xlfn.CONCAT(BD83:BF83) -> POLY-CRETE WR COVE BASE, SLOPE/PATCHINGCHESTNUTKIT | AP83: =BC83 -> 57.67 | AQ83: =BF83 -> KIT | AS83: =BE83 -> CHESTNUT | AT83: HPF COLOR QUARTZ | AU83: 25 MESH | AV83: =AT83&AU83 -> HPF COLOR QUARTZ25 MESH | AW83: 27.5 | AY83: =_xlfn.CONCAT(AZ83:BB83) -> E WR COVE CHUTKIT | AZ83: =MID(BD83,10,10) -> E WR COVE | BA83: =LEFT(BE83,2)&RIGHT(BE83,2) -> CHUT | BB83: =LEFT(BF83,3) -> KIT | BC83: =IFERROR(VLOOKUP(BD83&BF83,AV:AW,2,FALSE),0) -> 57.67 | BD83: POLY-CRETE WR COVE BASE, SLOPE/PATCHING | BE83: CHESTNUT | BF83: KIT | BG83: CRETE
A84: NJ | B84: X | C84: X | D84: X | I84: S-RS88-CG1 | J84: =_xlfn.CONCAT(K84:M84) -> RS88 (12 TUBES / CASE)OTHERTUBE | K84: RS88 (12 TUBES / CASE) | L84: OTHER | M84: TUBE | P84: B | Q84: 0.5 | R84: =5/Q84 -> 10 | S84: 210 | X84: 455450 | Y84: SIKAFLOOR-264 VERSATILE PIGMENTED EPOXY | Z84: 292.99 | AA84: 4.5 GAL | AC84: TRAFFIC GRAY | AD84: SIKA | AF84: =Table1[[#This Row],[C:C]]*1.1 -> 0 | AI84: =IFERROR(VLOOKUP(X84,#REF!,8,FALSE),0) -> 0 | AN84: =PROD_ID_TABLE[[#This Row],[PROD ID]] -> E WR COVE COAYKIT | AO84: =_xlfn.CONCAT(BD84:BF84) -> POLY-CRETE WR COVE BASE, SLOPE/PATCHINGCONCRETE GRAYKIT | AP84: =BC84 -> 57.67 | AQ84: =BF84 -> KIT | AS84: =BE84 -> CONCRETE GRAY | AT84: HPF COLOR QUARTZ | AU84: 40 MESH | AV84: =AT84&AU84 -> HPF COLOR QUARTZ40 MESH | AW84: 27.5 | AY84: =_xlfn.CONCAT(AZ84:BB84) -> E WR COVE COAYKIT | AZ84: =MID(BD84,10,10) -> E WR COVE | BA84: =LEFT(BE84,2)&RIGHT(BE84,2) -> COAY | BB84: =LEFT(BF84,3) -> KIT | BC84: =IFERROR(VLOOKUP(BD84&BF84,AV:AW,2,FALSE),0) -> 57.67 | BD84: POLY-CRETE WR COVE BASE, SLOPE/PATCHING | BE84: CONCRETE GRAY | BF84: KIT | BG84: CRETE
A85: NM | I85: R-MMP-5 | J85: =_xlfn.CONCAT(K85:M85) -> SGC MMA PRIMERN/A5 GAL | K85: SGC MMA PRIMER | L85: N/A | M85: 5 GAL | P85: SF | Q85: 1 | R85: =R84 -> 10 | S85: =T85*R85 -> 102 | T85: 10.2 | X85: 455451 | Y85: SIKAFLOOR-264 VERSATILE PIGMENTED EPOXY | Z85: 292.99 | AA85: 4.5 GAL | AC85: BEIGE | AD85: SIKA | AF85: =Table1[[#This Row],[C:C]]*1.1 -> 0 | AI85: =IFERROR(VLOOKUP(X85,#REF!,8,FALSE),0) -> 0 | AN85: =PROD_ID_TABLE[[#This Row],[PROD ID]] -> E WR COVE DAAYKIT | AO85: =_xlfn.CONCAT(BD85:BF85) -> POLY-CRETE WR COVE BASE, SLOPE/PATCHINGDARK GRAYKIT | AP85: =BC85 -> 57.67 | AQ85: =BF85 -> KIT | AS85: =BE85 -> DARK GRAY | AT85: 1-4IN DECO FLAKE - 40LB BAG | AU85: 40LB BAG | AV85: =AT85&AU85 -> 1-4IN DECO FLAKE - 40LB BAG40LB BAG | AW85: 110 | AY85: =_xlfn.CONCAT(AZ85:BB85) -> E WR COVE DAAYKIT | AZ85: =MID(BD85,10,10) -> E WR COVE | BA85: =LEFT(BE85,2)&RIGHT(BE85,2) -> DAAY | BB85: =LEFT(BF85,3) -> KIT | BC85: =IFERROR(VLOOKUP(BD85&BF85,AV:AW,2,FALSE),0) -> 57.67 | BD85: POLY-CRETE WR COVE BASE, SLOPE/PATCHING | BE85: DARK GRAY | BF85: KIT | BG85: CRETE
A86: NY | B86: X | D86: X | I86: R-MMP-50 | J86: =_xlfn.CONCAT(K86:M86) -> SGC MMA PRIMERN/A50 GAL | K86: SGC MMA PRIMER | L86: N/A | M86: 50 GAL | P86: PIG | Q86: 0 | R86: =ROUNDUP(Q86*R83,0) -> 0 | S86: =R86*T86 -> 0 | T86: 25.5 | X86: 455464 | Y86: SIKAFLOOR-264 VERSATILE PIGMENTED EPOXY | Z86: 292.99 | AA86: 4.5 GAL | AC86: GRAY BEIGE | AD86: SIKA | AF86: =Table1[[#This Row],[C:C]]*1.1 -> 0 | AI86: =IFERROR(VLOOKUP(X86,#REF!,8,FALSE),0) -> 0 | AN86: =PROD_ID_TABLE[[#This Row],[PROD ID]] -> E WR COVE GRENKIT | AO86: =_xlfn.CONCAT(BD86:BF86) -> POLY-CRETE WR COVE BASE, SLOPE/PATCHINGGREENKIT | AP86: =BC86 -> 57.67 | AQ86: =BF86 -> KIT | AS86: =BE86 -> GREEN | AT86: 24 MESH ALUMINUM OXIDE | AU86: 50LB BAG | AV86: =AT86&AU86 -> 24 MESH ALUMINUM OXIDE50LB BAG | AW86: 235.8 | AY86: =_xlfn.CONCAT(AZ86:BB86) -> E WR COVE GRENKIT | AZ86: =MID(BD86,10,10) -> E WR COVE | BA86: =LEFT(BE86,2)&RIGHT(BE86,2) -> GREN | BB86: =LEFT(BF86,3) -> KIT | BC86: =IFERROR(VLOOKUP(BD86&BF86,AV:AW,2,FALSE),0) -> 57.67 | BD86: POLY-CRETE WR COVE BASE, SLOPE/PATCHING | BE86: GREEN | BF86: KIT | BG86: CRETE
A87: NC | B87: X | I87: R-MMA-5 | J87: =_xlfn.CONCAT(K87:M87) -> RIO MMA BONDING ADDITIVEN/A5 GAL | K87: RIO MMA BONDING ADDITIVE | L87: N/A | M87: 5 GAL | P87: 35LB | S87: =SUM(S83:S86) -> 522 | X87: 455466 | Y87: SIKAFLOOR-264 VERSATILE PIGMENTED EPOXY | Z87: 292.99 | AA87: 4.5 GAL | AC87: TRAFFIC BLUE | AD87: SIKA | AF87: =Table1[[#This Row],[C:C]]*1.1 -> 0 | AI87: =IFERROR(VLOOKUP(X87,#REF!,8,FALSE),0) -> 0 | AN87: =PROD_ID_TABLE[[#This Row],[PROD ID]] -> E WR COVE GRAYKIT | AO87: =_xlfn.CONCAT(BD87:BF87) -> POLY-CRETE WR COVE BASE, SLOPE/PATCHINGGRAYKIT | AP87: =BC87 -> 57.67 | AQ87: =BF87 -> KIT | AS87: =BE87 -> GRAY | AT87: 36 MESH ALUMINUM OXIDE | AU87: 50LB BAG | AV87: =AT87&AU87 -> 36 MESH ALUMINUM OXIDE50LB BAG | AW87: 235.8 | AY87: =_xlfn.CONCAT(AZ87:BB87) -> E WR COVE GRAYKIT | AZ87: =MID(BD87,10,10) -> E WR COVE | BA87: =LEFT(BE87,2)&RIGHT(BE87,2) -> GRAY | BB87: =LEFT(BF87,3) -> KIT | BC87: =IFERROR(VLOOKUP(BD87&BF87,AV:AW,2,FALSE),0) -> 57.67 | BD87: POLY-CRETE WR COVE BASE, SLOPE/PATCHING | BE87: GRAY | BF87: KIT | BG87: CRETE
A88: ND | B88: X | I88: JS4U-SG | J88: =_xlfn.CONCAT(K88:M88) -> 600 UV (SSP JS-600 ALIPHATIC POLYUREA)STANDARD GRAY1 GAL BOX | K88: 600 UV (SSP JS-600 ALIPHATIC POLYUREA) | L88: STANDARD GRAY | M88: 1 GAL BOX | X88: 455468 | Y88: SIKAFLOOR-264 VERSATILE PIGMENTED EPOXY | Z88: 292.99 | AA88: 4.5 GAL | AC88: PALE GREEN | AD88: SIKA | AF88: =Table1[[#This Row],[C:C]]*1.1 -> 0 | AI88: =IFERROR(VLOOKUP(X88,#REF!,8,FALSE),0) -> 0 | AN88: =PROD_ID_TABLE[[#This Row],[PROD ID]] -> E WR COVE REEDKIT | AO88: =_xlfn.CONCAT(BD88:BF88) -> POLY-CRETE WR COVE BASE, SLOPE/PATCHINGREDKIT | AP88: =BC88 -> 57.67 | AQ88: =BF88 -> KIT | AS88: =BE88 -> RED | AT88: RS88 (12 TUBES / CASE) | AU88: TUBE | AV88: =AT88&AU88 -> RS88 (12 TUBES / CASE)TUBE | AW88: 38.5 | AY88: =_xlfn.CONCAT(AZ88:BB88) -> E WR COVE REEDKIT | AZ88: =MID(BD88,10,10) -> E WR COVE | BA88: =LEFT(BE88,2)&RIGHT(BE88,2) -> REED | BB88: =LEFT(BF88,3) -> KIT | BC88: =IFERROR(VLOOKUP(BD88&BF88,AV:AW,2,FALSE),0) -> 57.67 | BD88: POLY-CRETE WR COVE BASE, SLOPE/PATCHING | BE88: RED | BF88: KIT | BG88: CRETE
A89: OH | B89: X | C89: X | D89: X | I89: JS4U-GA | J89: =_xlfn.CONCAT(K89:M89) -> 600 UV (SSP JS-600 ALIPHATIC POLYUREA)GRAY AREA1 GAL BOX | K89: 600 UV (SSP JS-600 ALIPHATIC POLYUREA) | L89: GRAY AREA | M89: 1 GAL BOX | P89: A | Q89: 0.5 | R89: =5/Q89 -> 10 | S89: 210 | X89: 455500 | Y89: SIKAFLOOR-264 VERSATILE PIGMENTED EPOXY | Z89: 292.99 | AA89: 4.5 GAL | AC89: TRAFFIC RED | AD89: SIKA | AF89: =Table1[[#This Row],[C:C]]*1.1 -> 0 | AI89: =IFERROR(VLOOKUP(X89,#REF!,8,FALSE),0) -> 0 | AN89: =PROD_ID_TABLE[[#This Row],[PROD ID]] -> E HF ACCELN//A1 Q | AO89: =_xlfn.CONCAT(BD89:BF89) -> POLY-CRETE HF ACCELERATOR LOW TEMPERATURE AIDN/A1 Qt | AP89: =BC89 -> 43.8 | AQ89: =BF89 -> 1 Qt | AS89: =BE89 -> N/A | AT89: RS88 (12 TUBES / CASE) | AU89: CASE | AV89: =AT89&AU89 -> RS88 (12 TUBES / CASE)CASE | AW89: 462 | AY89: =_xlfn.CONCAT(AZ89:BB89) -> E HF ACCELN//A1 Q | AZ89: =MID(BD89,10,10) -> E HF ACCEL | BA89: =LEFT(BE89,2)&RIGHT(BE89,2) -> N//A | BB89: =LEFT(BF89,3) -> 1 Q | BC89: =IFERROR(VLOOKUP(BD89&BF89,AV:AW,2,FALSE),0) -> 43.8 | BD89: POLY-CRETE HF ACCELERATOR LOW TEMPERATURE AID | BE89: N/A | BF89: 1 Qt | BG89: CRETE | BH89: MMA
A90: OK | B90: X | I90: JS4U-CG | J90: =_xlfn.CONCAT(K90:M90) -> 600 UV (SSP JS-600 ALIPHATIC POLYUREA)CHATEAU GRAY1 GAL BOX | K90: 600 UV (SSP JS-600 ALIPHATIC POLYUREA) | L90: CHATEAU GRAY | M90: 1 GAL BOX | P90: B | Q90: 0.5 | R90: =5/Q90 -> 10 | S90: 210 | X90: 455501 | Y90: SIKAFLOOR-264 VERSATILE PIGMENTED EPOXY | Z90: 292.99 | AA90: 4.5 GAL | AC90: SIGNAL YELLOW | AD90: SIKA | AF90: =Table1[[#This Row],[C:C]]*1.1 -> 0 | AI90: =IFERROR(VLOOKUP(X90,#REF!,8,FALSE),0) -> 0 | AN90: =PROD_ID_TABLE[[#This Row],[PROD ID]] -> BOND ENHAN//AKIT | AO90: =_xlfn.CONCAT(BD90:BF90) -> CRYLAFLOR BOND ENHANCER TO P-101N/AKIT | AP90: =BC90 -> 30 | AQ90: =BF90 -> KIT | AS90: =BE90 -> N/A | AT90: NP-1 TUBES (30 TUBE/CASE) | AU90: TUBE | AV90: =AT90&AU90 -> NP-1 TUBES (30 TUBE/CASE)TUBE | AW90: 8.29 | AY90: =_xlfn.CONCAT(AZ90:BB90) -> BOND ENHAN//AKIT | AZ90: =MID(BD90,10,10) -> BOND ENHA | BA90: =LEFT(BE90,2)&RIGHT(BE90,2) -> N//A | BB90: =LEFT(BF90,3) -> KIT | BC90: =IFERROR(VLOOKUP(BD90&BF90,AV:AW,2,FALSE),0) -> 30 | BD90: CRYLAFLOR BOND ENHANCER TO P-101 | BE90: N/A | BF90: KIT | BG90: MMA | BH90: BLACK
A91: OR | I91: JS4U-CG | J91: =_xlfn.CONCAT(K91:M91) -> 600 UV (SSP JS-600 ALIPHATIC POLYUREA)OTHER1 GAL BOX | K91: 600 UV (SSP JS-600 ALIPHATIC POLYUREA) | L91: OTHER | M91: 1 GAL BOX | P91: TC | Q91: 1 | R91: =R90 -> 10 | S91: =T91*R91 -> 107.5 | T91: 10.75 | X91: 455503 | Y91: SIKAFLOOR-264 VERSATILE PIGMENTED EPOXY | Z91: 292.99 | AA91: 4.5 GAL | AC91: SIGNAL WHITE | AD91: SIKA | AF91: =Table1[[#This Row],[C:C]]*1.1 -> 0 | AI91: =IFERROR(VLOOKUP(X91,#REF!,8,FALSE),0) -> 0 | AN91: =PROD_ID_TABLE[[#This Row],[PROD ID]] -> P-101 PRICLAR5 G | AO91: =_xlfn.CONCAT(BD91:BF91) -> CRYLAFLOR P-101 PRIMERCLEAR5 GAL KIT | AP91: =BC91 -> 323 | AQ91: =BF91 -> 5 GAL KIT | AS91: =BE91 -> CLEAR | AT91: NP-1 TUBES (30 TUBE/CASE) | AU91: CASE | AV91: =AT91&AU91 -> NP-1 TUBES (30 TUBE/CASE)CASE | AW91: 210 | AY91: =_xlfn.CONCAT(AZ91:BB91) -> P-101 PRICLAR5 G | AZ91: =MID(BD91,10,10) -> P-101 PRI | BA91: =LEFT(BE91,2)&RIGHT(BE91,2) -> CLAR | BB91: =LEFT(BF91,3) -> 5 G | BC91: =IFERROR(VLOOKUP(BD91&BF91,AV:AW,2,FALSE),0) -> 323 | BD91: CRYLAFLOR P-101 PRIMER | BE91: CLEAR | BF91: 5 GAL KIT | BG91: MMA | BH91: GRAY
A92: PA | B92: X | C92: X | P92: PIG | Q92: =3/12 -> 0.25 | R92: =ROUNDUP(Q92*R89,0) -> 3 | S92: =R92*T92 -> 76.5 | T92: 25.5 | X92: 455506 | Y92: SIKAFLOOR-264 VERSATILE PIGMENTED EPOXY | Z92: 292.99 | AA92: 4.5 GAL | AC92: TAN 251 | AD92: SIKA | AF92: =Table1[[#This Row],[C:C]]*1.1 -> 0 | AI92: =IFERROR(VLOOKUP(X92,#REF!,8,FALSE),0) -> 0 | AN92: =PROD_ID_TABLE[[#This Row],[PROD ID]] -> P-101 PRIBEGE5 G | AO92: =_xlfn.CONCAT(BD92:BF92) -> CRYLAFLOR P-101 PRIMERBEIGE5 GAL KIT | AP92: =BC92 -> 323 | AQ92: =BF92 -> 5 GAL KIT | AS92: =BE92 -> BEIGE | AT92: RS65 (12 TUBES / CASE) | AU92: TUBE | AV92: =AT92&AU92 -> RS65 (12 TUBES / CASE)TUBE | AW92: 38.5 | AY92: =_xlfn.CONCAT(AZ92:BB92) -> P-101 PRIBEGE5 G | AZ92: =MID(BD92,10,10) -> P-101 PRI | BA92: =LEFT(BE92,2)&RIGHT(BE92,2) -> BEGE | BB92: =LEFT(BF92,3) -> 5 G | BC92: =IFERROR(VLOOKUP(BD92&BF92,AV:AW,2,FALSE),0) -> 323 | BD92: CRYLAFLOR P-101 PRIMER | BE92: BEIGE | BF92: 5 GAL KIT | BG92: MMA | BH92: GREEN | BI92: {=IF(C52="","",_xlfn.SWITCH(C52,P!$BL$17,P!$BE$91:$BE$98,P!$BL$18,P!$BE$99:$BE$111,P!$BL$19,P!$BE$112:$BE$125,P!$BL$20,P!$BE$126:$BE$139,P!$BL$21,P!$BE$140:$BE$145,P!$BL$22,P!$BE$146,P!$BL$23,P!$BE$147:$BE$152,P!$BE$153))}
A93: RI | P93: 6.5LB | S93: =SUM(S89:S92) -> 604 | X93: 455508 | Y93: SIKAFLOOR-264 VERSATILE PIGMENTED EPOXY | Z93: 292.99 | AA93: 4.5 GAL | AC93: RAFFIA BEIGE | AD93: SIKA | AF93: =Table1[[#This Row],[C:C]]*1.1 -> 0 | AI93: =IFERROR(VLOOKUP(X93,#REF!,8,FALSE),0) -> 0 | AN93: =PROD_ID_TABLE[[#This Row],[PROD ID]] -> P-101 PRIBROW5 G | AO93: =_xlfn.CONCAT(BD93:BF93) -> CRYLAFLOR P-101 PRIMERBRIGHT YELLOW5 GAL KIT | AP93: =BC93 -> 323 | AQ93: =BF93 -> 5 GAL KIT | AS93: =BE93 -> BRIGHT YELLOW | AT93: RS65 (12 TUBES / CASE) | AU93: CASE | AV93: =AT93&AU93 -> RS65 (12 TUBES / CASE)CASE | AW93: 462 | AY93: =_xlfn.CONCAT(AZ93:BB93) -> P-101 PRIBROW5 G | AZ93: =MID(BD93,10,10) -> P-101 PRI | BA93: =LEFT(BE93,2)&RIGHT(BE93,2) -> BROW | BB93: =LEFT(BF93,3) -> 5 G | BC93: =IFERROR(VLOOKUP(BD93&BF93,AV:AW,2,FALSE),0) -> 323 | BD93: CRYLAFLOR P-101 PRIMER | BE93: BRIGHT YELLOW | BF93: 5 GAL KIT | BG93: MMA | BH93: TILE RED
A94: SC | B94: X | C94: X | X94: 456659 | Y94: SIKAFLOOR-264 VERSATILE PIGMENTED EPOXY | Z94: 292.99 | AA94: 4.5 GAL | AC94: OXFORD GRAY | AD94: SIKA | AF94: =Table1[[#This Row],[C:C]]*1.1 -> 0 | AI94: =IFERROR(VLOOKUP(X94,#REF!,8,FALSE),0) -> 0 | AN94: =PROD_ID_TABLE[[#This Row],[PROD ID]] -> P-101 PRICOAY5 G | AO94: =_xlfn.CONCAT(BD94:BF94) -> CRYLAFLOR P-101 PRIMERCONCRETE GRAY5 GAL KIT | AP94: =BC94 -> 323 | AQ94: =BF94 -> 5 GAL KIT | AS94: =BE94 -> CONCRETE GRAY | AT94: RESUPRIME 3831 MVB MOISTURE EPOXY PRIMER | AU94: 110 GAL | AV94: =AT94&AU94 -> RESUPRIME 3831 MVB MOISTURE EPOXY PRIMER110 GAL | AW94: 5826.15 | AY94: =_xlfn.CONCAT(AZ94:BB94) -> P-101 PRICOAY5 G | AZ94: =MID(BD94,10,10) -> P-101 PRI | BA94: =LEFT(BE94,2)&RIGHT(BE94,2) -> COAY | BB94: =LEFT(BF94,3) -> 5 G | BC94: =IFERROR(VLOOKUP(BD94&BF94,AV:AW,2,FALSE),0) -> 323 | BD94: CRYLAFLOR P-101 PRIMER | BE94: CONCRETE GRAY | BF94: 5 GAL KIT | BG94: MMA | BH94: BEIGE
A95: SD | B95: X | C95: X | D95: X | X95: 456680 | Y95: SIKAFLOOR-264 VERSATILE PIGMENTED EPOXY | Z95: 292.99 | AA95: 4.5 GAL | AC95: BEIGE ROSE | AD95: SIKA | AF95: =Table1[[#This Row],[C:C]]*1.1 -> 0 | AI95: =IFERROR(VLOOKUP(X95,#REF!,8,FALSE),0) -> 0 | AN95: =PROD_ID_TABLE[[#This Row],[PROD ID]] -> P-101 PRICHAY5 G | AO95: =_xlfn.CONCAT(BD95:BF95) -> CRYLAFLOR P-101 PRIMERCHARCOAL GRAY5 GAL KIT | AP95: =BC95 -> 323 | AQ95: =BF95 -> 5 GAL KIT | AS95: =BE95 -> CHARCOAL GRAY | AT95: RESUFLOR 3760 MPE MULTI-PURPOSE EPOXY | AU95: 165 GAL | AV95: =AT95&AU95 -> RESUFLOR 3760 MPE MULTI-PURPOSE EPOXY165 GAL | AW95: 16242.6 | AY95: =_xlfn.CONCAT(AZ95:BB95) -> P-101 PRICHAY5 G | AZ95: =MID(BD95,10,10) -> P-101 PRI | BA95: =LEFT(BE95,2)&RIGHT(BE95,2) -> CHAY | BB95: =LEFT(BF95,3) -> 5 G | BC95: =IFERROR(VLOOKUP(BD95&BF95,AV:AW,2,FALSE),0) -> 323 | BD95: CRYLAFLOR P-101 PRIMER | BE95: CHARCOAL GRAY | BF95: 5 GAL KIT | BG95: MMA | BH95: WHITE
A96: TN | B96: X | C96: X | X96: 459042 | Y96: SIKA UCRETE HS22 NA HIGH BUILD SL SLURRY | Z96: 82.22 | AA96: KIT | AC96: BEIGE | AD96: SIKA | AF96: =Table1[[#This Row],[C:C]]*1.1 -> 0 | AI96: =IFERROR(VLOOKUP(X96,#REF!,8,FALSE),0) -> 0 | AN96: =PROD_ID_TABLE[[#This Row],[PROD ID]] -> P-101 PRILIAY5 G | AO96: =_xlfn.CONCAT(BD96:BF96) -> CRYLAFLOR P-101 PRIMERLIGHT GRAY5 GAL KIT | AP96: =BC96 -> 323 | AQ96: =BF96 -> 5 GAL KIT | AS96: =BE96 -> LIGHT GRAY | AT96: RESUFLOR 3746 HIGH PERFORMANCE EPOXY | AU96: 159 GAL | AV96: =AT96&AU96 -> RESUFLOR 3746 HIGH PERFORMANCE EPOXY159 GAL | AW96: 6920.76 | AY96: =_xlfn.CONCAT(AZ96:BB96) -> P-101 PRILIAY5 G | AZ96: =MID(BD96,10,10) -> P-101 PRI | BA96: =LEFT(BE96,2)&RIGHT(BE96,2) -> LIAY | BB96: =LEFT(BF96,3) -> 5 G | BC96: =IFERROR(VLOOKUP(BD96&BF96,AV:AW,2,FALSE),0) -> 323 | BD96: CRYLAFLOR P-101 PRIMER | BE96: LIGHT GRAY | BF96: 5 GAL KIT | BG96: MMA | BH96: CONCRETE GRAY
A97: TX | C97: X | D97: X | F97: X | X97: 459045 | Y97: SIKA UCRETE HS22 NA HIGH BUILD SL SLURRY | Z97: 82.22 | AA97: KIT | AC97: OXIDE RED | AD97: SIKA | AF97: =Table1[[#This Row],[C:C]]*1.1 -> 0 | AI97: =IFERROR(VLOOKUP(X97,#REF!,8,FALSE),0) -> 0 | AN97: =PROD_ID_TABLE[[#This Row],[PROD ID]] -> P-101 PRIMEAY5 G | AO97: =_xlfn.CONCAT(BD97:BF97) -> CRYLAFLOR P-101 PRIMERMED. GRAY5 GAL KIT | AP97: =BC97 -> 323 | AQ97: =BF97 -> 5 GAL KIT | AS97: =BE97 -> MED. GRAY | AT97: RESUTILE 4640 HTS 100 HS HIGH TRAFFIC URETHANE ENAMEL | AU97: 1.2 GAL | AV97: =AT97&AU97 -> RESUTILE 4640 HTS 100 HS HIGH TRAFFIC URETHANE ENAMEL1.2 GAL | AW97: 478.45 | AY97: =_xlfn.CONCAT(AZ97:BB97) -> P-101 PRIMEAY5 G | AZ97: =MID(BD97,10,10) -> P-101 PRI | BA97: =LEFT(BE97,2)&RIGHT(BE97,2) -> MEAY | BB97: =LEFT(BF97,3) -> 5 G | BC97: =IFERROR(VLOOKUP(BD97&BF97,AV:AW,2,FALSE),0) -> 323 | BD97: CRYLAFLOR P-101 PRIMER | BE97: MED. GRAY | BF97: 5 GAL KIT | BG97: MMA | BH97: MED. GRAY | BI97: 101
A98: UT | B98: X | D98: X | X98: 459046 | Y98: SIKA UCRETE HS22 NA HIGH BUILD SL SLURRY | Z98: 82.22 | AA98: KIT | AC98: AGATE GREY | AD98: SIKA | AF98: =Table1[[#This Row],[C:C]]*1.1 -> 0 | AI98: =IFERROR(VLOOKUP(X98,#REF!,8,FALSE),0) -> 0 | AN98: =PROD_ID_TABLE[[#This Row],[PROD ID]] -> P-101 PRISLAY5 G | AO98: =_xlfn.CONCAT(BD98:BF98) -> CRYLAFLOR P-101 PRIMERSLATE GRAY5 GAL KIT | AP98: =BC98 -> 323 | AQ98: =BF98 -> 5 GAL KIT | AS98: =BE98 -> SLATE GRAY | AT98: CRYLAFLOR P-101 PRIMER | AU98: 50 Gal KIT | AV98: =AT98&AU98 -> CRYLAFLOR P-101 PRIMER50 Gal KIT | AW98: 2702.39 | AY98: =_xlfn.CONCAT(AZ98:BB98) -> P-101 PRISLAY5 G | AZ98: =MID(BD98,10,10) -> P-101 PRI | BA98: =LEFT(BE98,2)&RIGHT(BE98,2) -> SLAY | BB98: =LEFT(BF98,3) -> 5 G | BC98: =IFERROR(VLOOKUP(BD98&BF98,AV:AW,2,FALSE),0) -> 323 | BD98: CRYLAFLOR P-101 PRIMER | BE98: SLATE GRAY | BF98: 5 GAL KIT | BG98: MMA | BH98: SLATE GRAY
A99: VT | B99: X | C99: X | X99: 459048 | Y99: SIKA UCRETE HS22 NA HIGH BUILD SL SLURRY | Z99: 82.22 | AA99: KIT | AC99: TRAFFIC GREY | AD99: SIKA | AF99: =Table1[[#This Row],[C:C]]*1.1 -> 0 | AI99: =IFERROR(VLOOKUP(X99,#REF!,8,FALSE),0) -> 0 | AN99: =PROD_ID_TABLE[[#This Row],[PROD ID]] -> G-201 BINCLAR5 G | AO99: =_xlfn.CONCAT(BD99:BF99) -> CRYLAFLOR G-201 BINDERCLEAR5 GAL KIT | AP99: =BC99 -> 341.92 | AQ99: =BF99 -> 5 GAL KIT | AS99: =BE99 -> CLEAR | AT99: CRYLAFLOR G-201 BINDER | AU99: 50 Gal KIT | AV99: =AT99&AU99 -> CRYLAFLOR G-201 BINDER50 Gal KIT | AW99: 3294.42 | AY99: =_xlfn.CONCAT(AZ99:BB99) -> G-201 BINCLAR5 G | AZ99: =MID(BD99,10,10) -> G-201 BIN | BA99: =LEFT(BE99,2)&RIGHT(BE99,2) -> CLAR | BB99: =LEFT(BF99,3) -> 5 G | BC99: =IFERROR(VLOOKUP(BD99&BF99,AV:AW,2,FALSE),0) -> 341.92 | BD99: CRYLAFLOR G-201 BINDER | BE99: CLEAR | BF99: 5 GAL KIT | BG99: MMA | BH99: CLEAR
A100: VA | B100: X | D100: X | X100: 465609 | Y100: SIKADUR 509 - COARSE BROADCAST AGGREGATE | Z100: 21.14 | AA100: 50LB | AD100: SIKA | AF100: =Table1[[#This Row],[C:C]]*1.1 -> 0 | AI100: =IFERROR(VLOOKUP(X100,#REF!,8,FALSE),0) -> 0 | AN100: =PROD_ID_TABLE[[#This Row],[PROD ID]] -> G-201 BINBEGE5 G | AO100: =_xlfn.CONCAT(BD100:BF100) -> CRYLAFLOR G-201 BINDERBEIGE5 GAL KIT | AP100: =BC100 -> 341.92 | AQ100: =BF100 -> 5 GAL KIT | AS100: =BE100 -> BEIGE | AT100: CRYLAFLOR T-301 TOPCOAT | AU100: 50 Gal KIT | AV100: =AT100&AU100 -> CRYLAFLOR T-301 TOPCOAT50 Gal KIT | AW100: 3206.15 | AY100: =_xlfn.CONCAT(AZ100:BB100) -> G-201 BINBEGE5 G | AZ100: =MID(BD100,10,10) -> G-201 BIN | BA100: =LEFT(BE100,2)&RIGHT(BE100,2) -> BEGE | BB100: =LEFT(BF100,3) -> 5 G | BC100: =IFERROR(VLOOKUP(BD100&BF100,AV:AW,2,FALSE),0) -> 341.92 | BD100: CRYLAFLOR G-201 BINDER | BE100: BEIGE | BF100: 5 GAL KIT | BG100: MMA | BH100: LIGHT GRAY
...

Sheet INFO
B2: Project Name: | F2: Country: | H2: Job #:
B4: Project Manager: | F4: Super/Foreman:
B6: Scope/Schedule
B7: PHASE / SCOPE / COP | C7: Installed System | D7: SQ FT | E7: LF Cove | F7: LF Joints | G7: Material Delivery Date | H7: Start Time | I7: Install Start Date | J7: Install End Date
B16: Jobsite Information
B18: Ship To Address: | F18: Install Address:
C22: CITY | D22: STATE | E22: ZIP | H22: CITY | I22: STATE | J22: ZIP
B24: Site Contact: | G24: Union: | I24: x
B25: Phone? | G25: Non-Union:
G26: Prevailing Wage:
B28: Pre-Job Checklist
B30: Contract Executed: | E30: Heat: | H30: Complete:
B31: Installation Scheduled: | E31: Lights: | H31: Final Walk:
B32: Materials Ordered: | E32: Power: | H32: Return Mat:
B33: Rental Booked: | E33: Trash: | H33: New Building:
B35: General Project and Flooring System Info
B47: Financials
B49: Tab | C49: Subtotal | E49: Total | G49: Markup % | H49: Gross Profit % | I49: Bid Amount
B50: SW | C50: =SW!N91 -> 0 | E50: =SW!N96 -> 0 | G50: =SW!R92 -> 0 | H50: =SW!R93 -> 0 | I50: =SW!Q97 -> 0
B51: SIKA | C51: =SIKA!N68 -> 0 | E51: =SIKA!N73 -> 0 | G51: =SIKA!R69 -> 0 | H51: =SIKA!R70 -> 0 | I51: =SIKA!Q74 -> 0
B52: RIO | C52: =SGC!N77 -> 0 | E52: =SGC!N82 -> 0 | G52: =SGC!R78 -> 0 | H52: =SGC!R79 -> 0 | I52: =SGC!Q83 -> 0
B53: BLANK | C53: =BLANK!N46 -> 0 | E53: =BLANK!N51 -> 0 | G53: =BLANK!R47 -> 0 | H53: =BLANK!R48 -> 0 | I53: =BLANK!Q52 -> 0
B54: Grand Total | I54: =SUM(I50:I53) -> 0
G56: Total Sq. Ft. | H56: =SUM($D$8:$D$14) -> 0 | I56: Cost Per Sq. Ft. | J56: =IFERROR($I$54/$H$56, "")

Sheet FIELD
B2: **TO EXPORT TABS -"File" / "Export" / "Create PDF/XPS Document" / enter file name / choose save location / "Publish"
B4: =IF(INFO!B2=0,"",INFO!B2) -> Project Name: | C4: =IF(INFO!C2=0,"",INFO!C2) | G4: =IF(INFO!H2=0,"",INFO!H2) -> Job #: | I4: =IF(INFO!I2=0,"",INFO!I2)
B6: =IF(INFO!B4=0,"",INFO!B4) -> Project Manager: | C6: =IF(INFO!C4=0,"",INFO!C4) | G6: =IF(INFO!F4=0,"",INFO!F4) -> Super/Foreman: | I6: =IF(INFO!H4=0,"",INFO!H4)
B8: Scope/Schedule
B9: =IF(INFO!B7=0,"",INFO!B7) -> PHASE / SCOPE / COP | C9: =IF(INFO!C7=0,"",INFO!C7) -> Installed System | D9: =IF(INFO!D7=0,"",INFO!D7) -> SQ FT | E9: =IF(INFO!E7=0,"",INFO!E7) -> LF Cove | F9: =IF(INFO!F7=0,"",INFO!F7) -> LF Joints | G9: =IF(INFO!G7=0,"",INFO!G7) -> Material Delivery Date | H9: =IF(INFO!H7=0,"",INFO!H7) -> Start Time | I9: =IF(INFO!I7=0,"",INFO!I7) -> Install Start Date | J9: =IF(INFO!J7=0,"",INFO!J7) -> Install End Date
B10: =IF(INFO!B8=0,"",INFO!B8) | C10: =IF(INFO!C8=0,"",INFO!C8) | D10: =IF(INFO!D8=0,"",INFO!D8) | E10: =IF(INFO!E8=0,"",INFO!E8) | F10: =IF(INFO!F8=0,"",INFO!F8) | G10: =IF(INFO!G8=0,"",INFO!G8) | H10: =IF(INFO!H8=0,"",INFO!H8) | I10: =IF(INFO!I8=0,"",INFO!I8) | J10: =IF(INFO!J8=0,"",INFO!J8)
B11: =IF(INFO!B9=0,"",INFO!B9) | C11: =IF(INFO!C9=0,"",INFO!C9) | D11: =IF(INFO!D9=0,"",INFO!D9) | E11: =IF(INFO!E9=0,"",INFO!E9) | F11: =IF(INFO!F9=0,"",INFO!F9) | G11: =IF(INFO!G9=0,"",INFO!G9) | H11: =IF(INFO!H9=0,"",INFO!H9) | I11: =IF(INFO!I9=0,"",INFO!I9) | J11: =IF(INFO!J9=0,"",INFO!J9)
B12: =IF(INFO!B10=0,"",INFO!B10) | C12: =IF(INFO!C10=0,"",INFO!C10) | D12: =IF(INFO!D10=0,"",INFO!D10) | E12: =IF(INFO!E10=0,"",INFO!E10) | F12: =IF(INFO!F10=0,"",INFO!F10) | G12: =IF(INFO!G10=0,"",INFO!G10) | H12: =IF(INFO!H10=0,"",INFO!H10) | I12: =IF(INFO!I10=0,"",INFO!I10) | J12: =IF(INFO!J10=0,"",INFO!J10)
B13: =IF(INFO!B11=0,"",INFO!B11) | C13: =IF(INFO!C11=0,"",INFO!C11) | D13: =IF(INFO!D11=0,"",INFO!D11) | E13: =IF(INFO!E11=0,"",INFO!E11) | F13: =IF(INFO!F11=0,"",INFO!F11) | G13: =IF(INFO!G11=0,"",INFO!G11) | H13: =IF(INFO!H11=0,"",INFO!H11) | I13: =IF(INFO!I11=0,"",INFO!I11) | J13: =IF(INFO!J11=0,"",INFO!J11)
B14: =IF(INFO!B12=0,"",INFO!B12) | C14: =IF(INFO!C12=0,"",INFO!C12) | D14: =IF(INFO!D12=0,"",INFO!D12) | E14: =IF(INFO!E12=0,"",INFO!E12) | F14: =IF(INFO!F12=0,"",INFO!F12) | G14: =IF(INFO!G12=0,"",INFO!G12) | H14: =IF(INFO!H12=0,"",INFO!H12) | I14: =IF(INFO!I12=0,"",INFO!I12) | J14: =IF(INFO!J12=0,"",INFO!J12)
B15: =IF(INFO!B13=0,"",INFO!B13) | C15: =IF(INFO!C13=0,"",INFO!C13) | D15: =IF(INFO!D13=0,"",INFO!D13) | E15: =IF(INFO!E13=0,"",INFO!E13) | F15: =IF(INFO!F13=0,"",INFO!F13) | G15: =IF(INFO!G13=0,"",INFO!G13) | H15: =IF(INFO!H13=0,"",INFO!H13) | I15: =IF(INFO!I13=0,"",INFO!I13) | J15: =IF(INFO!J13=0,"",INFO!J13)
B16: =IF(INFO!B14=0,"",INFO!B14) | C16: =IF(INFO!C14=0,"",INFO!C14) | D16: =IF(INFO!D14=0,"",INFO!D14) | E16: =IF(INFO!E14=0,"",INFO!E14) | F16: =IF(INFO!F14=0,"",INFO!F14) | G16: =IF(INFO!G14=0,"",INFO!G14) | H16: =IF(INFO!H14=0,"",INFO!H14) | I16: =IF(INFO!I14=0,"",INFO!I14) | J16: =IF(INFO!J14=0,"",INFO!J14)
B18: Jobsite Information
B20: =IF(INFO!B18=0,"",INFO!B18) -> Ship To Address: | C20: =IF(INFO!C18=0,"",INFO!C18) | F20: Install Address: | H20: =IF(INFO!H18=0,"",INFO!H18)
C21: =IF(INFO!C19=0,"",INFO!C19) | H21: =IF(INFO!H19=0,"",INFO!H19)
C22: =IF(INFO!C20=0,"",INFO!C20) | H22: =IF(INFO!H20=0,"",INFO!H20)
C23: =IF(INFO!C21=0,"",INFO!C21) | D23: =IF(INFO!D21=0,"",INFO!D21) | E23: =IF(INFO!E21=0,"",INFO!E21) | H23: =IF(INFO!H21=0,"",INFO!H21) | I23: =IF(INFO!I21=0,"",INFO!I21) | J23: =IF(INFO!J21=0,"",INFO!J21)
C24: CITY | D24: STATE | E24: ZIP | H24: CITY | I24: STATE | J24: ZIP
B26: =IF(INFO!B24=0,"",INFO!B24) -> Site Contact: | C26: =IF(INFO!C24=0,"",INFO!C24) | G26: =IF(INFO!G24=0,"",INFO!G24) -> Union: | I26: =IF(INFO!I24=0,"",INFO!I24) -> x
C27: =IF(INFO!C25=0,"",INFO!C25) | G27: =IF(INFO!G25=0,"",INFO!G25) -> Non-Union: | I27: =IF(INFO!I25=0,"",INFO!I25)
C28: =IF(INFO!C26=0,"",INFO!C26) | G28: =IF(INFO!G26=0,"",INFO!G26) -> Prevailing Wage: | I28: =IF(INFO!I26=0,"",INFO!I26)
B30: Pre-Job Checklist
B32: =IF(INFO!B30=0,"",INFO!B30) -> Contract Executed: | C32: =IF(INFO!C30=0,"",INFO!C30) | E32: =IF(INFO!E30=0,"",INFO!E30) -> Heat: | F32: =IF(INFO!F30=0,"",INFO!F30) | H32: =IF(INFO!H30=0,"",INFO!H30) -> Complete: | J32: =IF(INFO!J30=0,"",INFO!J30)
B33: =IF(INFO!B31=0,"",INFO!B31) -> Installation Scheduled: | C33: =IF(INFO!C31=0,"",INFO!C31) | E33: =IF(INFO!E31=0,"",INFO!E31) -> Lights: | F33: =IF(INFO!F31=0,"",INFO!F31) | H33: =IF(INFO!H31=0,"",INFO!H31) -> Final Walk: | J33: =IF(INFO!J31=0,"",INFO!J31)
B34: =IF(INFO!B32=0,"",INFO!B32) -> Materials Ordered: | C34: =IF(INFO!C32=0,"",INFO!C32) | E34: =IF(INFO!E32=0,"",INFO!E32) -> Power: | F34: =IF(INFO!F32=0,"",INFO!F32) | H34: =IF(INFO!H32=0,"",INFO!H32) -> Return Mat: | J34: =IF(INFO!J32=0,"",INFO!J32)
B35: =IF(INFO!B33=0,"",INFO!B33) -> Rental Booked: | C35: =IF(INFO!C33=0,"",INFO!C33) | E35: =IF(INFO!E33=0,"",INFO!E33) -> Trash: | F35: =IF(INFO!F33=0,"",INFO!F33) | H35: =IF(INFO!H33=0,"",INFO!H33) -> New Building: | J35: =IF(INFO!J33=0,"",INFO!J33)
B37: General Project and Flooring System Info
B39: =IF(INFO!B37="","",INFO!B37)
B49: Labor Budget
B51: Scope | C51: Tab | F51: Crew | G51: Days | H51: Rate/Day | I51: Total Man-Days
B52: {=_xlfn.LET( _xlpm.gAll, _xlfn.VSTACK(SW!G69:G77, SGC!G55:G63, SIKA!G45:G54, BLANK!G31:G40), _xlpm.fAll, _xlfn.VSTACK(SW!F69:F77, SGC!F55:F63, SIKA!F45:F54, BLANK!F31:F40), _xlpm.cAll, _xlfn.VSTACK(SW!C69:C77, SGC!C55:C63, SIKA!C45:C54, BLANK!C31:C40), _xlpm.mask, (_xlpm.gAll<>"")+(_xlpm.fAll<>""), _xlpm.n, SUM(--_xlpm.mask), IF(_xlpm.n=0, "", _xlfn.LET( _xlpm.cKeep, _xlfn._xlws.FILTER(_xlpm.cAll, _xlpm.mask), _xlpm.k, MIN(ROWS(B50:B59), ROWS(_xlpm.cKeep)), _xlfn.TAKE(IF(_xlpm.cKeep<>"", _xlpm.cKeep, "INPUT NEEDED"), _xlpm.k) ) ) )} | C52: {=_xlfn.LET( _xlpm.gAll, _xlfn.VSTACK(SW!G69:G77, SGC!G55:G63, SIKA!G45:G54, BLANK!G31:G40), _xlpm.fAll, _xlfn.VSTACK(SW!F69:F77, SGC!F55:F63, SIKA!F45:F54, BLANK!F31:F40), _xlpm.srcAll, _xlfn.VSTACK( _xlfn.MAKEARRAY(ROWS(SW!G69:G77),1,_xlfn.LAMBDA(_xlpm.r,_xlpm.c,"SW")), _xlfn.MAKEARRAY(ROWS(SGC!G55:G63),1,_xlfn.LAMBDA(_xlpm.r,_xlpm.c,"RIO")), _xlfn.MAKEARRAY(ROWS(SIKA!G45:G54),1,_xlfn.LAMBDA(_xlpm.r,_xlpm.c,"SIKA")), _xlfn.MAKEARRAY(ROWS(BLANK!G31:G40),1,_xlfn.LAMBDA(_xlpm.r,_xlpm.c,"BLANK")) ), _xlpm.mask, (_xlpm.gAll<>"")+(_xlpm.fAll<>""), _xlpm.sKeep, _xlfn._xlws.FILTER(_xlpm.srcAll, _xlpm.mask), IF(SUM(_xlpm.mask)=0, "", _xlfn.TAKE(_xlpm.sKeep, MIN(ROWS(_xlfn.ANCHORARRAY(B52)), ROWS(_xlpm.sKeep))) ) )} | F52: {=_xlfn.LET( _xlpm.gAll, _xlfn.VSTACK(SW!G69:G77, SGC!G55:G63, SIKA!G45:G54, BLANK!G31:G40), _xlpm.fAll, _xlfn.VSTACK(SW!F69:F77, SGC!F55:F63, SIKA!F45:F54, BLANK!F31:F40), _xlpm.mask, (_xlpm.gAll<>"")+(_xlpm.fAll<>""), _xlpm.n, SUM(--_xlpm.mask), IF(_xlpm.n=0, "", _xlfn.LET( _xlpm.fKeep, _xlfn._xlws.FILTER(_xlpm.fAll, _xlpm.mask), _xlpm.k, MIN(ROWS(F50:F59), ROWS(_xlpm.fKeep)), _xlfn.TAKE(IF(_xlpm.fKeep<>"", _xlpm.fKeep, "INPUT REQ."), _xlpm.k) ) ) )} | G52: {=_xlfn.LET( _xlpm.gAll, _xlfn.VSTACK(SW!G69:G77, SGC!G55:G63, SIKA!G45:G54, BLANK!G31:G40), _xlpm.fAll, _xlfn.VSTACK(SW!F69:F77, SGC!F55:F63, SIKA!F45:F54, BLANK!F31:F40), _xlpm.mask, (_xlpm.gAll<>"")+(_xlpm.fAll<>""), _xlpm.n, SUM(--_xlpm.mask), IF(_xlpm.n=0, "", _xlfn.LET( _xlpm.gKeep, _xlfn._xlws.FILTER(_xlpm.gAll, _xlpm.mask), _xlpm.k, MIN(ROWS(H50:H59), ROWS(_xlpm.gKeep)), _xlfn.TAKE(IF(_xlpm.gKeep<>"", _xlpm.gKeep, "INPUT REQ."), _xlpm.k) ) ) )} | H52: {=_xlfn.LET( _xlpm.gAll, _xlfn.VSTACK(SW!G69:G77, SGC!G55:G63, SIKA!G45:G54, BLANK!G31:G40), _xlpm.fAll, _xlfn.VSTACK(SW!F69:F77, SGC!F55:F63, SIKA!F45:F54, BLANK!F31:F40), _xlpm.hAll, _xlfn.VSTACK(SW!H69:H77, SGC!H55:H63, SIKA!H45:H54, BLANK!H31:H40), _xlpm.mask, (_xlpm.gAll<>"")+(_xlpm.fAll<>""), _xlpm.n, SUM(_xlpm.mask), IF(_xlpm.n=0, "", _xlfn.LET( _xlpm.hKeep, _xlfn._xlws.FILTER(_xlpm.hAll, _xlpm.mask), _xlfn.TAKE(_xlpm.hKeep, MIN(ROWS(I50:I56), ROWS(_xlpm.hKeep))) ) ) )} | I52: =_xlfn.LET(_xlpm.a, N(G52:G61), _xlpm.b, N(F52:F61), _xlpm.p, _xlpm.a*_xlpm.b, IF(_xlpm.p=0, "", _xlpm.p))
I53: =_xlfn.LET(_xlpm.a, N(G53:G62), _xlpm.b, N(F53:F62), _xlpm.p, _xlpm.a*_xlpm.b, IF(_xlpm.p=0, "", _xlpm.p))
I54: =_xlfn.LET(_xlpm.a, N(G54:G63), _xlpm.b, N(F54:F63), _xlpm.p, _xlpm.a*_xlpm.b, IF(_xlpm.p=0, "", _xlpm.p))
I55: =_xlfn.LET(_xlpm.a, N(G55:G64), _xlpm.b, N(F55:F64), _xlpm.p, _xlpm.a*_xlpm.b, IF(_xlpm.p=0, "", _xlpm.p))
I56: =_xlfn.LET(_xlpm.a, N(G56:G65), _xlpm.b, N(F56:F65), _xlpm.p, _xlpm.a*_xlpm.b, IF(_xlpm.p=0, "", _xlpm.p))
I57: =_xlfn.LET(_xlpm.a, N(G57:G66), _xlpm.b, N(F57:F66), _xlpm.p, _xlpm.a*_xlpm.b, IF(_xlpm.p=0, "", _xlpm.p))
I58: =_xlfn.LET(_xlpm.a, N(G58:G67), _xlpm.b, N(F58:F67), _xlpm.p, _xlpm.a*_xlpm.b, IF(_xlpm.p=0, "", _xlpm.p))
I59: =_xlfn.LET(_xlpm.a, N(G59:G68), _xlpm.b, N(F59:F68), _xlpm.p, _xlpm.a*_xlpm.b, IF(_xlpm.p=0, "", _xlpm.p))
I60: =_xlfn.LET(_xlpm.a, N(G60:G69), _xlpm.b, N(F60:F69), _xlpm.p, _xlpm.a*_xlpm.b, IF(_xlpm.p=0, "", _xlpm.p))
I61: =_xlfn.LET(_xlpm.a, N(G61:G70), _xlpm.b, N(F61:F70), _xlpm.p, _xlpm.a*_xlpm.b, IF(_xlpm.p=0, "", _xlpm.p))
B63: Travel/Equipment Budget
B65: Expense Type | C65: Tab | F65: Crew | G65: Days | H65: Rate | I65: Total
B66: {=_xlfn.LET( _xlpm.gAll, _xlfn.VSTACK(SW!G79:G86, SGC!G65:G72, SIKA!G56:G63, BLANK!G42:G49), _xlpm.fAll, _xlfn.VSTACK(SW!F79:F86, SGC!F65:F72, SIKA!F56:F63, BLANK!F42:F49), _xlpm.cAll, _xlfn.VSTACK(SW!C79:C86, SGC!C65:C72, SIKA!C56:C63, BLANK!C42:C49), _xlpm.mask, (_xlpm.gAll<>"")+(_xlpm.fAll<>""), _xlpm.n, SUM(--_xlpm.mask), IF(_xlpm.n=0, "", _xlfn.LET( _xlpm.cKeep, _xlfn._xlws.FILTER(_xlpm.cAll, _xlpm.mask), _xlpm.k, MIN(ROWS(B50:B60), ROWS(_xlpm.cKeep)), _xlfn.TAKE(IF(_xlpm.cKeep<>"", _xlpm.cKeep, "INPUT NEEDED"), _xlpm.k) ) ) )} | C66: {=_xlfn.LET( _xlpm.gAll, _xlfn.VSTACK(SW!G79:G86, SGC!G65:G72, SIKA!G56:G63, BLANK!G42:G49), _xlpm.fAll, _xlfn.VSTACK(SW!F79:F86, SGC!F65:F72, SIKA!F56:F63, BLANK!F42:F49), _xlpm.srcAll, _xlfn.VSTACK( _xlfn.MAKEARRAY(ROWS(SW!G79:G86),1,_xlfn.LAMBDA(_xlpm.r,_xlpm.c,"SW")), _xlfn.MAKEARRAY(ROWS(SGC!G65:G72),1,_xlfn.LAMBDA(_xlpm.r,_xlpm.c,"RIO")), _xlfn.MAKEARRAY(ROWS(SIKA!G56:G63),1,_xlfn.LAMBDA(_xlpm.r,_xlpm.c,"SIKA")), _xlfn.MAKEARRAY(ROWS(BLANK!G42:G49),1,_xlfn.LAMBDA(_xlpm.r,_xlpm.c,"BLANK")) ), _xlpm.mask, (_xlpm.gAll<>"")+(_xlpm.fAll<>""), _xlpm.sKeep, _xlfn._xlws.FILTER(_xlpm.srcAll, _xlpm.mask), IF(SUM(_xlpm.mask)=0,"", _xlfn.TAKE(_xlpm.sKeep, MIN(ROWS(_xlfn.ANCHORARRAY(B66)), ROWS(_xlpm.sKeep))) ) )} | F66: {=_xlfn.LET( _xlpm.gAll,_xlfn.VSTACK(SW!G79:G86,SGC!G65:G72,SIKA!G56:G63,BLANK!G42:G49), _xlpm.fAll,_xlfn.VSTACK(SW!F79:F86,SGC!F65:F72,SIKA!F56:F63,BLANK!F42:F49), _xlpm.mask,(_xlpm.gAll<>"")+(_xlpm.fAll<>""),IF(SUM(_xlpm.mask)=0,"", _xlfn.LET( _xlpm.fKeep,_xlfn._xlws.FILTER(_xlpm.fAll,_xlpm.mask), _xlfn.TAKE(IF(_xlpm.fKeep<>"",_xlpm.fKeep,"INPUT REQ."),MIN(ROWS(F72:F81),ROWS(_xlpm.fKeep))) ) ) )} | G66: {=_xlfn.LET( _xlpm.gAll, _xlfn.VSTACK(SW!G79:G86, SGC!G65:G72, SIKA!G56:G63, BLANK!G42:G49), _xlpm.fAll, _xlfn.VSTACK(SW!F79:F86, SGC!F65:F72, SIKA!F56:F63, BLANK!F42:F49), _xlpm.mask, (_xlpm.gAll<>"")+(_xlpm.fAll<>""), IF(SUM(_xlpm.mask)=0,"", _xlfn.LET( _xlpm.gKeep, _xlfn._xlws.FILTER(_xlpm.gAll, _xlpm.mask), _xlfn.TAKE(IF(_xlpm.gKeep<>"", _xlpm.gKeep, "INPUT REQ."), MIN(ROWS(G72:G81), ROWS(_xlpm.gKeep))) ) ) )} | H66: {=_xlfn.LET( _xlpm.gAll, _xlfn.VSTACK(SW!G79:G86, SGC!G65:G72, SIKA!G56:G63, BLANK!G42:G49), _xlpm.fAll, _xlfn.VSTACK(SW!F79:F86, SGC!F65:F72, SIKA!F56:F63, BLANK!F42:F49), _xlpm.hAll, _xlfn.VSTACK(SW!H79:H86, SGC!H65:H72, SIKA!H56:H63, BLANK!H42:H49), _xlpm.mask, (_xlpm.gAll<>"")+(_xlpm.fAll<>""), IF(SUM(_xlpm.mask)=0, "", _xlfn.LET( _xlpm.hKeep, _xlfn._xlws.FILTER(_xlpm.hAll, _xlpm.mask), _xlpm.k, MIN(ROWS(I50:I59), ROWS(_xlpm.hKeep)), _xlfn.TAKE(_xlpm.hKeep, _xlpm.k) ) ) )} | I66: {=_xlfn.LET( _xlpm.gAll, _xlfn.VSTACK(SW!G79:G86, SGC!G65:G72, SIKA!G56:G63, BLANK!G42:G49), _xlpm.fAll, _xlfn.VSTACK(SW!F79:F86, SGC!F65:F72, SIKA!F56:F63, BLANK!F42:F49), _xlpm.iAll, _xlfn.VSTACK(SW!I79:I86, SGC!I65:I72, SIKA!I56:I63, BLANK!I42:I49), _xlpm.mask, (_xlpm.gAll<>"")+(_xlpm.fAll<>""), IF(SUM(_xlpm.mask)=0,"", _xlfn.LET( _xlpm.iKeep, _xlfn._xlws.FILTER(_xlpm.iAll, _xlpm.mask), _xlfn.TAKE(_xlpm.iKeep, MIN(ROWS(J50:J59), ROWS(_xlpm.iKeep))) ) ) )}
D76: =IF(INFO!D69=0,"",INFO!D69) | E76: =IF(INFO!E69=0,"",INFO!E69)
E77: CONSUMABLES-SUPPLIES-BOX STORE | H77: =IF(COUNTA(SW!D99, SGC!D85, SIKA!D76, BLANK!N35)>1, "Multiple MFR(!)", "") | J77: =SUM(SW!D99, SGC!D85, SIKA!D76, BLANK!N35) -> 0
E78: PO CONSUMABLES | H78: =IF(COUNTA(SW!D100, SGC!D86, SIKA!D77, BLANK!N36)>1, "Multiple MFR(!)", "") | J78: =SUM(SW!D100, SGC!D86, SIKA!D77, BLANK!N36) -> 0

Sheet CODES
C2: Project Name | E2: =IF(INFO!C2=0,"",INFO!C2)
C3: Job Number | E3: =IF(INFO!I2=0,"",INFO!I2)
C4: Contract Value | E4: =IF(INFO!I54=0,"",INFO!I54)
B6: Cost Code | C6: Description | D6: Value | E6: Notes
B7: 1-100 | C7: Polymer Materials | D7: =P!B9 -> 0
B8: 2-100 | C8: In house Labor | D8: =P!C9 -> 0 | E8: $450 (Max) includes wages and burden
B9: 2-200 | C9: Payroll Taxes | E9: 2-200 through 2-700 will be included in man day rate above
B10: 2-300 | C10: Workers' Compensation
B11: 2-400 | C11: Union Costs
B12: 2-500 | C12: Fringe Benefits
B13: 2-600 | C13: Liability Insurance
B14: 2-700 | C14: Shop Allocation
B15: 4-100 | C15: Subcontractor Work Order | D15: =P!D9 -> 0 | E15: Subcontractor work order value
B16: 5-000 | C16: Other Job Costs | D16: =P!M9 -> 0 | E16: Miscellaneous Items
B17: 5-100 | C17: Freight | D17: =P!N9+P!O9 -> 0
B18: 5-150 | C18: Expedited Freight | E18: Use if freight is expedited
B19: 5-300 | C19: Equipment Rental | D19: =P!P9 -> 0 | E19: Use if there is large equipment rented from rental yard
B20: 5-400 | C20: Tools and Small Equipment | D20: =P!G48 -> 0 | E20: Use if unique hand tools are needed for a particular job
B21: 5-500 | C21: Consumables Supplies-Box Store | D21: =P!G49 -> 0 | E21: Home Depot, Lowes, hardware store purchases
B22: 5-550 | C22: PO Consumables Supplies | D22: =P!G50 -> 0 | E22: Charged against shop allocation
B23: 5-600 | C23: In-House Equipment Cost | D23: =P!G51 -> 0 | E23: $650 per day. Large equipment.
B24: 5-900 | C24: Misc. Expenses - External | D24: =P!R9 -> 0 | E24: Also known as Warranty Markup
B25: 5-901 | C25: Misc. Expenses - Internal | D25: =P!S9 -> 0 | E25: Also known as Contingency
B26: 7-100 | C26: Airline Expenses | D26: =P!E9 -> 0 | E26: $420 per one way flight per man
B27: 7-200 | C27: Hotel Expenses | D27: =P!F9 -> 0 | E27: $85 per day. Odd sizes still use $170 per room per night
B28: 7-300 | C28: Auto Rental | D28: =P!G9 -> 0 | E28: Use $65/day
B29: 7-400 | C29: Mileage/Fuel Expense | D29: =P!H9 -> 0 | E29: Use $0.50/ mile
B30: 7-600 | C30: Parking / Tolls | D30: =P!I9 -> 0
B31: 7-750 | C31: Per Diem for Travel Days Only | D31: =P!J9 -> 0 | E31: $38.25 / day on travel days
B32: 7-760 | C32: Per Diem for Work Days Only | D32: =P!K9 -> 0 | E32: $51.00/ day on work days
B33: 7-770 | C33: Travel Pay | D33: =P!L9 -> 0 | E33: $325/ day except DOT Driver which is $450/ day
B34: 7-910 | C34: PM Airline Expenses | D34: =P!G42 -> 0
B35: 7-920 | C35: PM Hotel Expenses | D35: =P!G43 -> 0
B36: 7-930 | C36: PM Auto Rental | D36: =P!G44 -> 0
B37: 7-940 | C37: PM Mileage/Fuel Expense | D37: =P!G45 -> 0
B38: 7-950 | C38: PM Meals | D38: =P!G46 -> 0
B39: 7-960 | C39: PM Parking / Tolls | D39: =P!G47 -> 0
B40: 8-100 | C40: Sales Tax | D40: =P!T9 -> 0 | E40: Use only on jobs within states that charge sales tax
C41: California Litigation Fund | D41: =P!Q9 -> 0 | E41: Used for California jobs without subcontractors

Sheet PO
B2: **TO EXPORT TABS -"File" / "Export" / "Create PDF/XPS Document" / enter file name / choose save location / "Publish" | L2: VERSION | M2: Version Date: | N2: 46086 | P2: Material Tax Rate: | Q2: 0.1
B3: ALL INFORMATION FIELDS BELOW ARE FILLED FROM THE INFO TAB | L3: 3.8 | M3: Secret Version Date | N3: 45875
B4: =IF(INFO!B2=0,"",INFO!B2) -> Project Name: | C4: =IF(INFO!C2=0,"",INFO!C2) | G4: =IF(INFO!H2=0,"",INFO!H2) -> Job #: | I4: =IF(INFO!I2=0,"",INFO!I2) | M4: Today's Date: | N4: =TODAY() -> 46100 | P4: Rental Tax Rate: | Q4: 0.1
B6: =IF(INFO!B4=0,"",INFO!B4) -> Project Manager: | C6: =IF(INFO!C4=0,"",INFO!C4) | G6: =IF(INFO!F4=0,"",INFO!F4) -> Super/Foreman: | I6: =IF(INFO!H4=0,"",INFO!H4) | M6: Currency: | N6: USD | P6: Freight Tax Rate: | Q6: 0.1
B8: Jobsite Information | M8: ***Right click on the table to generate/refresh PO List***
B10: =IF(INFO!B18=0,"",INFO!B18) -> Ship To Address: | C10: =IF(INFO!C18=0,"",INFO!C18) | F10: Install Address: | H10: =IF(INFO!H18=0,"",INFO!H18)
C11: =IF(INFO!C19=0,"",INFO!C19) | H11: =IF(INFO!H19=0,"",INFO!H19)
C12: =IF(INFO!C20=0,"",INFO!C20) | H12: =IF(INFO!H20=0,"",INFO!H20)
C13: =IF(INFO!C21=0,"",INFO!C21) | D13: =IF(INFO!D21=0,"",INFO!D21) | E13: =IF(INFO!E21=0,"",INFO!E21) | H13: =IF(INFO!H21=0,"",INFO!H21) | I13: =IF(INFO!I21=0,"",INFO!I21) | J13: =IF(INFO!J21=0,"",INFO!J21)
C14: CITY | D14: STATE | E14: ZIP | H14: CITY | I14: STATE | J14: ZIP
B16: =IF(INFO!B24=0,"",INFO!B24) -> Site Contact: | C16: =IF(INFO!C24=0,"",INFO!C24) | G16: =IF(INFO!G24=0,"",INFO!G24) -> Union: | I16: =IF(INFO!I24=0,"",INFO!I24) -> x
C17: =IF(INFO!C25=0,"",INFO!C25) | G17: =IF(INFO!G15=0,"",INFO!G15) | I17: =IF(INFO!I15=0,"",INFO!I25)
C18: =IF(INFO!C26=0,"",INFO!C26) | G18: =IF(INFO!G16=0,"",INFO!G16) | I18: =IF(INFO!I16=0,"",INFO!I26)
B20: RIGHT CLICK TABLE BELOW TO GENERATE/REFRESH PO LIST
B21: Description | C21: Color | D21: Qty | E21: Unit Size | F21: Cost | G21: Quoted Cost | H21: Total Amount | I21: Qty Adjust | J21: Adjusted Total
B23: Total | H23: =SUBTOTAL(109,PO_Summary3[Total Amount]) -> 0

Sheet Old PO
A1: Description | B1: Color | C1: Qty | D1: Unit Size | E1: Cost | F1: Quoted Cost | G1: Total Amount | H1: Qty Adjust | I1: Adjusted Total | S1: =IF(V1=0,"NEED ADDRESS",IF(OR(IFERROR(VLOOKUP(V1,P!$A$55:$B$113,2,FALSE),"")<>"",AND(IFERROR(FIND("C",INFO!I2),"")<>"",(IFERROR(VLOOKUP(V1,P!$A$55:$F$113,5,FALSE),""))<>""),AND(INFO!J33<>"",(IFERROR(VLOOKUP(V1,P!$A$55:$F$113,6,FALSE),""))<>"")),"Taxable","Not Taxable")) -> #REF! | V1: =IF(INFO!D21="",INFO!#REF!,INFO!D21) -> #REF!
A3: Total | G3: =SUBTOTAL(109,PO_Summary[Total Amount]) -> 0 | S3: =IF(V1=0,"",IF(IFERROR(VLOOKUP(V1,P!$A$55:$D$113,4,FALSE),"")<>"","Taxable","Not Taxable")) -> #REF!
S5: =IF(V1=0,"",IF(IFERROR(VLOOKUP(V1,P!$A$55:$C$113,3,FALSE),"")<>"","Taxable","Not Taxable")) -> #REF!

Sheet SW
C1: ="Tax Rate on PO Tab: "&TEXT(PO!$Q$2,"##0.00#%")&" Material / "&TEXT(PO!$Q$4,"##0.00#%")&" Rental / "&TEXT(PO!$Q$6,"##0.00#%")&" Freight" -> Tax Rate on PO Tab: 10.00% Material / 10.00% Rental / 10.00% Freight
C2: **TO SELECT PRODUCTS - USE DROP DOWN MENU ON THE PRODUCT LINES AND SELECT MATERIAL, COLOR AND UOM
C3: **FOR ORDERS THAT HAVE QUOTES - ENTER IN QUOTED RATE INTO BLUE BOXES BELOW
B4: PRIMERS & SEALERS | C4: PRIMERS & SEALERS | K4: ~~~~ | L4: EPOXY | M4: EPOXY
B5: PROD # | C5: PRODUCT | D5: COLOR | E5: UOM | F5: QTY | G5: UNIT RATE | H5: QUOTED RATE | I5: EXTENSION | J5: WEIGHT | K5: ~~~~ | L5: PROD # | M5: PRODUCT | N5: COLOR | O5: UOM | P5: QTY | Q5: UNIT RATE | R5: QUOTED RATE | S5: EXTENSION | T5: WEIGHT
B6: =IFERROR(IF(C6="","",_xlfn.XLOOKUP(_xlfn.CONCAT(C6:E6),P!$Y:$Y,P!$X:$X,"UNAVAILABLE")),"UNAVAILABLE") -> 3477 EPOXN//A3 G | C6: RESUPRIME 3477 EPOXY WATER PRIMER/SEALER | D6: N/A | E6: 3 GAL | G6: =IFERROR(VLOOKUP(SWPRIME[[#This Row],[PROD '#]],Table1[[Product '#]:[Cost]],3,FALSE),0) -> 217.16 | I6: =IFERROR(IF(H6<>"",F6*H6,F6*G6),"") -> 0 | K6: ~~~~ | L6: =IFERROR(IF(M6="","",_xlfn.XLOOKUP(_xlfn.CONCAT(M6:O6),P!$Y:$Y,P!$X:$X,"UNAVAILABLE")),"UNAVAILABLE") -> 3725 STATIMEAY3 G | M6: RESUFLOR 3725 STATIC CONTROL EPOXY | N6: MEDIUM GRAY | O6: 3 GAL | Q6: =IFERROR(VLOOKUP(SWEPOXY[[#This Row],[PROD '#]],Table1[[Product '#]:[Cost]],3,FALSE),0) -> 790.2 | S6: =IFERROR(IF(R6<>"",P6*R6,P6*Q6),"") -> 0
B7: =IFERROR(IF(C7="","",_xlfn.XLOOKUP(_xlfn.CONCAT(C7:E7),P!$Y:$Y,P!$X:$X,"UNAVAILABLE")),"UNAVAILABLE") -> 3504 HIGHGRAY2 G | C7: RESUPRIME 3504 HIGH SOLID CLEAR PRIMER/SEALER | D7: GRAY | E7: 2 GAL | G7: =IFERROR(VLOOKUP(SWPRIME[[#This Row],[PROD '#]],Table1[[Product '#]:[Cost]],3,FALSE),0) -> 168.31 | I7: =IFERROR(IF(H7<>"",F7*H7,F7*G7),"") -> 0 | K7: ~~~~ | L7: =IFERROR(IF(M7="","",_xlfn.XLOOKUP(_xlfn.CONCAT(M7:O7),P!$Y:$Y,P!$X:$X,"UNAVAILABLE")),"UNAVAILABLE") -> AQUA 3461 N//A15 | M7: RESUFLOR AQUA 3461 HIGH SOLIDS WB EPOXY GROUT/TOPCOAT | N7: N/A | O7: 15 GAL | Q7: =IFERROR(VLOOKUP(SWEPOXY[[#This Row],[PROD '#]],Table1[[Product '#]:[Cost]],3,FALSE),0) -> 1617 | S7: =IFERROR(IF(R7<>"",P7*R7,P7*Q7),"") -> 0
B8: =IFERROR(IF(C8="","",_xlfn.XLOOKUP(_xlfn.CONCAT(C8:E8),P!$Y:$Y,P!$X:$X,"UNAVAILABLE")),"UNAVAILABLE") -> 3579 HIGHWHTE3 G | C8: RESUPRIME 3579 HIGH SOLID EPOXY PRIMER/BINDER | D8: WHITE | E8: 3 GAL | G8: =IFERROR(VLOOKUP(SWPRIME[[#This Row],[PROD '#]],Table1[[Product '#]:[Cost]],3,FALSE),0) -> 187.14 | I8: =IFERROR(IF(H8<>"",F8*H8,F8*G8),"") -> 0 | K8: ~~~~ | L8: =IFERROR(IF(M8="","",_xlfn.XLOOKUP(_xlfn.CONCAT(M8:O8),P!$Y:$Y,P!$X:$X,"UNAVAILABLE")),"UNAVAILABLE") -> 3746 HIGH CLAR3 G | M8: RESUFLOR 3746 HIGH PERFORMANCE EPOXY | N8: CLEAR | O8: 3 GAL | Q8: =IFERROR(VLOOKUP(SWEPOXY[[#This Row],[PROD '#]],Table1[[Product '#]:[Cost]],3,FALSE),0) -> 205.98 | S8: =IFERROR(IF(R8<>"",P8*R8,P8*Q8),"") -> 0
B9: =IFERROR(IF(C9="","",_xlfn.XLOOKUP(_xlfn.CONCAT(C9:E9),P!$Y:$Y,P!$X:$X,"UNAVAILABLE")),"UNAVAILABLE") -> 3831 MVB N//A2 G | C9: RESUPRIME 3831 MVB MOISTURE EPOXY PRIMER | D9: N/A | E9: 2 GAL | G9: =IFERROR(VLOOKUP(SWPRIME[[#This Row],[PROD '#]],Table1[[Product '#]:[Cost]],3,FALSE),0) -> 135.36 | I9: =IFERROR(IF(H9<>"",F9*H9,F9*G9),"") -> 0 | K9: ~~~~ | L9: =IFERROR(IF(M9="","",_xlfn.XLOOKUP(_xlfn.CONCAT(M9:O9),P!$Y:$Y,P!$X:$X,"UNAVAILABLE")),"UNAVAILABLE") -> 3760 MPE MN//A15 | M9: RESUFLOR 3760 MPE MULTI-PURPOSE EPOXY | N9: N/A | O9: 15 GAL | Q9: =IFERROR(VLOOKUP(SWEPOXY[[#This Row],[PROD '#]],Table1[[Product '#]:[Cost]],3,FALSE),0) -> 847.44 | S9: =IFERROR(IF(R9<>"",P9*R9,P9*Q9),"") -> 0
B10: =IFERROR(IF(C10="","",_xlfn.XLOOKUP(_xlfn.CONCAT(C10:E10),P!$Y:$Y,P!$X:$X,"UNAVAILABLE")),"UNAVAILABLE") -> 5531 OIL N//A1 Q | C10: RESUPRIME 5531 OIL STOP PRIMER | D10: N/A | E10: 1 QT | G10: =IFERROR(VLOOKUP(SWPRIME[[#This Row],[PROD '#]],Table1[[Product '#]:[Cost]],3,FALSE),0) -> 48.26 | I10: =IFERROR(IF(H10<>"",F10*H10,F10*G10),"") -> 0 | K10: ~~~~ | L10: =IFERROR(IF(M10="","",_xlfn.XLOOKUP(_xlfn.CONCAT(M10:O10),P!$Y:$Y,P!$X:$X,"UNAVAILABLE")),"UNAVAILABLE") -> AQUA 3460 WHTE1.2 | M10: RESUFLOR AQUA 3460 WB EPOXY PRIMER, BINDER, TOPCOAT | N10: WHITE | O10: 1.25 GAL | Q10: =IFERROR(VLOOKUP(SWEPOXY[[#This Row],[PROD '#]],Table1[[Product '#]:[Cost]],3,FALSE),0) -> 131.82 | S10: =IFERROR(IF(R10<>"",P10*R10,P10*Q10),"") -> 0
B11: =IFERROR(IF(C11="","",_xlfn.XLOOKUP(_xlfn.CONCAT(C11:E11),P!$Y:$Y,P!$X:$X,"UNAVAILABLE")),"UNAVAILABLE") -> MVP EPOXYN//A3 G | C11: RESUPRIME MVP EPOXY PRIMER | D11: N/A | E11: 3 GAL | G11: =IFERROR(VLOOKUP(SWPRIME[[#This Row],[PROD '#]],Table1[[Product '#]:[Cost]],3,FALSE),0) -> 421.2 | I11: =IFERROR(IF(H11<>"",F11*H11,F11*G11),"") -> 0 | K11: ~~~~ | L11: =IFERROR(IF(M11="","",_xlfn.XLOOKUP(_xlfn.CONCAT(M11:O11),P!$Y:$Y,P!$X:$X,"UNAVAILABLE")),"UNAVAILABLE") -> AQUA 3461 N//A3 G | M11: RESUFLOR AQUA 3461 HIGH SOLIDS WB EPOXY GROUT/TOPCOAT | N11: N/A | O11: 3 GAL | Q11: =IFERROR(VLOOKUP(SWEPOXY[[#This Row],[PROD '#]],Table1[[Product '#]:[Cost]],3,FALSE),0) -> 318 | S11: =IFERROR(IF(R11<>"",P11*R11,P11*Q11),"") -> 0
B12: =IFERROR(IF(C12="","",_xlfn.XLOOKUP(_xlfn.CONCAT(C12:E12),P!$Y:$Y,P!$X:$X,"UNAVAILABLE")),"UNAVAILABLE") | G12: =IFERROR(VLOOKUP(SWPRIME[[#This Row],[PROD '#]],Table1[[Product '#]:[Cost]],3,FALSE),0) -> 0 | I12: =IFERROR(IF(H12<>"",F12*H12,F12*G12),"") -> 0 | K12: ~~~~ | L12: =IFERROR(IF(M12="","",_xlfn.XLOOKUP(_xlfn.CONCAT(M12:O12),P!$Y:$Y,P!$X:$X,"UNAVAILABLE")),"UNAVAILABLE") -> 4638 HS POCUOM3 G | M12: RESUTILE 4638 HS POLYURETHANE FLOOR ENAMEL | N12: CUSTOM | O12: 3 GAL | Q12: =IFERROR(VLOOKUP(SWEPOXY[[#This Row],[PROD '#]],Table1[[Product '#]:[Cost]],3,FALSE),0) -> 305.43 | S12: =IFERROR(IF(R12<>"",P12*R12,P12*Q12),"") -> 0
B13: =IFERROR(IF(C13="","",_xlfn.XLOOKUP(_xlfn.CONCAT(C13:E13),P!$Y:$Y,P!$X:$X,"UNAVAILABLE")),"UNAVAILABLE") | G13: =IFERROR(VLOOKUP(SWPRIME[[#This Row],[PROD '#]],Table1[[Product '#]:[Cost]],3,FALSE),0) -> 0 | I13: =IFERROR(IF(H13<>"",F13*H13,F13*G13),"") -> 0 | K13: ~~~~ | L13: =IFERROR(IF(M13="","",_xlfn.XLOOKUP(_xlfn.CONCAT(M13:O13),P!$Y:$Y,P!$X:$X,"UNAVAILABLE")),"UNAVAILABLE") -> PT 250 THICLAR15 | M13: RESUFLOR PT 250 THICKENED EPOXY 2:1 | N13: CLEAR | O13: 15 GAL | Q13: =IFERROR(VLOOKUP(SWEPOXY[[#This Row],[PROD '#]],Table1[[Product '#]:[Cost]],3,FALSE),0) -> 1053.42 | S13: =IFERROR(IF(R13<>"",P13*R13,P13*Q13),"") -> 0
B14: =IFERROR(IF(C14="","",_xlfn.XLOOKUP(_xlfn.CONCAT(C14:E14),P!$Y:$Y,P!$X:$X,"UNAVAILABLE")),"UNAVAILABLE") | G14: =IFERROR(VLOOKUP(SWPRIME[[#This Row],[PROD '#]],Table1[[Product '#]:[Cost]],3,FALSE),0) -> 0 | I14: =IFERROR(IF(H14<>"",F14*H14,F14*G14),"") -> 0 | K14: ~~~~ | L14: =IFERROR(IF(M14="","",_xlfn.XLOOKUP(_xlfn.CONCAT(M14:O14),P!$Y:$Y,P!$X:$X,"UNAVAILABLE")),"UNAVAILABLE") -> 3760 RCE RN//A15 | M14: RESUFLOR 3760 RCE RAPID CURE EPOXY | N14: N/A | O14: 15 GAL | Q14: =IFERROR(VLOOKUP(SWEPOXY[[#This Row],[PROD '#]],Table1[[Product '#]:[Cost]],3,FALSE),0) -> 962.2 | S14: =IFERROR(IF(R14<>"",P14*R14,P14*Q14),"") -> 0
B15: =IFERROR(IF(C15="","",_xlfn.XLOOKUP(_xlfn.CONCAT(C15:E15),P!$Y:$Y,P!$X:$X,"UNAVAILABLE")),"UNAVAILABLE") | G15: =IFERROR(VLOOKUP(SWPRIME[[#This Row],[PROD '#]],Table1[[Product '#]:[Cost]],3,FALSE),0) -> 0 | I15: =IFERROR(IF(H15<>"",F15*H15,F15*G15),"") -> 0 | K15: ~~~~ | L15: =IFERROR(IF(M15="","",_xlfn.XLOOKUP(_xlfn.CONCAT(M15:O15),P!$Y:$Y,P!$X:$X,"UNAVAILABLE")),"UNAVAILABLE") -> POFLEX 1:1GRAY2 | M15: GP 3555 EPOFLEX 1:1 | N15: GRAY | O15: 2 GAL | Q15: =IFERROR(VLOOKUP(SWEPOXY[[#This Row],[PROD '#]],Table1[[Product '#]:[Cost]],3,FALSE),0) -> 216.57 | S15: =IFERROR(IF(R15<>"",P15*R15,P15*Q15),"") -> 0
B16: =IFERROR(IF(C16="","",_xlfn.XLOOKUP(_xlfn.CONCAT(C16:E16),P!$Y:$Y,P!$X:$X,"UNAVAILABLE")),"UNAVAILABLE") | G16: =IFERROR(VLOOKUP(SWPRIME[[#This Row],[PROD '#]],Table1[[Product '#]:[Cost]],3,FALSE),0) -> 0 | I16: =IFERROR(IF(H16<>"",F16*H16,F16*G16),"") -> 0 | K16: ~~~~ | L16: =IFERROR(IF(M16="","",_xlfn.XLOOKUP(_xlfn.CONCAT(M16:O16),P!$Y:$Y,P!$X:$X,"UNAVAILABLE")),"UNAVAILABLE") -> 3741 CHEMISTAY3 G | M16: RESUFLOR 3741 CHEMICAL RESISTANT NOVOLAC | N16: STEEL GRAY | O16: 3 GAL | Q16: =IFERROR(VLOOKUP(SWEPOXY[[#This Row],[PROD '#]],Table1[[Product '#]:[Cost]],3,FALSE),0) -> 388.66 | S16: =IFERROR(IF(R16<>"",P16*R16,P16*Q16),"") -> 0
B17: =IFERROR(IF(C17="","",_xlfn.XLOOKUP(_xlfn.CONCAT(C17:E17),P!$Y:$Y,P!$X:$X,"UNAVAILABLE")),"UNAVAILABLE") | G17: =IFERROR(VLOOKUP(SWPRIME[[#This Row],[PROD '#]],Table1[[Product '#]:[Cost]],3,FALSE),0) -> 0 | I17: =IFERROR(IF(H17<>"",F17*H17,F17*G17),"") -> 0 | K17: ~~~~ | L17: =IFERROR(IF(M17="","",_xlfn.XLOOKUP(_xlfn.CONCAT(M17:O17),P!$Y:$Y,P!$X:$X,"UNAVAILABLE")),"UNAVAILABLE") | Q17: =IFERROR(VLOOKUP(SWEPOXY[[#This Row],[PROD '#]],Table1[[Product '#]:[Cost]],3,FALSE),0) -> 0 | S17: =IFERROR(IF(R17<>"",P17*R17,P17*Q17),"") -> 0
B18: =IFERROR(IF(C18="","",_xlfn.XLOOKUP(_xlfn.CONCAT(C18:E18),P!$Y:$Y,P!$X:$X,"UNAVAILABLE")),"UNAVAILABLE") | G18: =IFERROR(VLOOKUP(SWPRIME[[#This Row],[PROD '#]],Table1[[Product '#]:[Cost]],3,FALSE),0) -> 0 | I18: =IFERROR(IF(H18<>"",F18*H18,F18*G18),"") -> 0 | K18: ~~~~ | L18: =IFERROR(IF(M18="","",_xlfn.XLOOKUP(_xlfn.CONCAT(M18:O18),P!$Y:$Y,P!$X:$X,"UNAVAILABLE")),"UNAVAILABLE") | Q18: =IFERROR(VLOOKUP(SWEPOXY[[#This Row],[PROD '#]],Table1[[Product '#]:[Cost]],3,FALSE),0) -> 0 | S18: =IFERROR(IF(R18<>"",P18*R18,P18*Q18),"") -> 0
B19: =IFERROR(IF(C19="","",_xlfn.XLOOKUP(_xlfn.CONCAT(C19:E19),P!$Y:$Y,P!$X:$X,"UNAVAILABLE")),"UNAVAILABLE") | G19: =IFERROR(VLOOKUP(SWPRIME[[#This Row],[PROD '#]],Table1[[Product '#]:[Cost]],3,FALSE),0) -> 0 | I19: =IFERROR(IF(H19<>"",F19*H19,F19*G19),"") -> 0 | K19: ~~~~ | L19: =IFERROR(IF(M19="","",_xlfn.XLOOKUP(_xlfn.CONCAT(M19:O19),P!$Y:$Y,P!$X:$X,"UNAVAILABLE")),"UNAVAILABLE") | Q19: =IFERROR(VLOOKUP(SWEPOXY[[#This Row],[PROD '#]],Table1[[Product '#]:[Cost]],3,FALSE),0) -> 0 | S19: =IFERROR(IF(R19<>"",P19*R19,P19*Q19),"") -> 0
B20: Total | C20: Total | I20: =SUBTOTAL(109,SWPRIME[EXTENSION]) -> 0 | J20: =SUBTOTAL(103,SWPRIME[WEIGHT]) -> 0 | K20: ~~~~ | L20: Total | M20: Total | S20: =SUBTOTAL(109,SWEPOXY[EXTENSION]) -> 0 | T20: =SUBTOTAL(103,SWEPOXY[WEIGHT]) -> 0
K21: ~~~~
B22: CRACK FILLER & PATCHING | C22: CRACK FILLER & PATCHING & COLORANT | K22: ~~~~ | L22: POLYASPARTIC | M22: POLYASPARTIC
B23: PROD # | C23: PRODUCT | D23: COLOR | E23: UOM | F23: QTY | G23: UNIT RATE | H23: QUOTED RATE | I23: EXTENSION | J23: WEIGHT | K23: ~~~~ | L23: PROD # | M23: PRODUCT | N23: COLOR | O23: UOM | P23: QTY | Q23: UNIT RATE | R23: QUOTED RATE | S23: EXTENSION | T23: WEIGHT
B24: =IFERROR(IF(C24="","",_xlfn.XLOOKUP(_xlfn.CONCAT(C24:E24),P!$Y:$Y,P!$X:$X,"UNAVAILABLE")),"UNAVAILABLE") -> 3500 EPOXYN//A1/2 | C24: RESUFLOR 3500 EPOXY QUICK PATCH (FAST) | D24: N/A | E24: 1/2 GAL | G24: =IFERROR(VLOOKUP(SWPATCH[[#This Row],[PROD '#]],Table1[[Product '#]:[Cost]],3,FALSE),0) -> 97.69 | I24: =IFERROR(IF(H24<>"",F24*H24,F24*G24),"") -> 0 | K24: ~~~~ | L24: =IFERROR(IF(M24="","",_xlfn.XLOOKUP(_xlfn.CONCAT(M24:O24),P!$Y:$Y,P!$X:$X,"UNAVAILABLE")),"UNAVAILABLE") -> 4850 GROUTSTAY3 G | M24: ACCELERA 4850 GROUT/TOPCOAT POLYASPARTIC | N24: STEEL GRAY | O24: 3 GAL | Q24: =IFERROR(VLOOKUP(SWPOLY[[#This Row],[PROD '#]],Table1[[Product '#]:[Cost]],3,FALSE),0) -> 466.86 | S24: =IFERROR(IF(R24<>"",P24*R24,P24*Q24),"") -> 0
B25: =IFERROR(IF(C25="","",_xlfn.XLOOKUP(_xlfn.CONCAT(C25:E25),P!$Y:$Y,P!$X:$X,"UNAVAILABLE")),"UNAVAILABLE") -> 3513 SCRATGRAY2 G | C25: RESUFLOR 3513 SCRATCH COAT MASTIC (THICK/SLOW) | D25: GRAY | E25: 2 GAL | G25: =IFERROR(VLOOKUP(SWPATCH[[#This Row],[PROD '#]],Table1[[Product '#]:[Cost]],3,FALSE),0) -> 104.75 | I25: =IFERROR(IF(H25<>"",F25*H25,F25*G25),"") -> 0 | K25: ~~~~ | L25: =IFERROR(IF(M25="","",_xlfn.XLOOKUP(_xlfn.CONCAT(M25:O25),P!$Y:$Y,P!$X:$X,"UNAVAILABLE")),"UNAVAILABLE") -> FLA CLEAR CLAR2 G | M25: RESUDECK FLA CLEAR ALIPHATIC POLYASPARTIC TOPCOAT | N25: CLEAR | O25: 2 GAL | Q25: =IFERROR(VLOOKUP(SWPOLY[[#This Row],[PROD '#]],Table1[[Product '#]:[Cost]],3,FALSE),0) -> 215.98 | S25: =IFERROR(IF(R25<>"",P25*R25,P25*Q25),"") -> 0
B26: =IFERROR(IF(C26="","",_xlfn.XLOOKUP(_xlfn.CONCAT(C26:E26),P!$Y:$Y,P!$X:$X,"UNAVAILABLE")),"UNAVAILABLE") -> M. URETHAN//A44 | C26: CEMLACK UM. URETHANE CEMENT PATCH 1:1:1 | D26: N/A | E26: 44 LBS | G26: =IFERROR(VLOOKUP(SWPATCH[[#This Row],[PROD '#]],Table1[[Product '#]:[Cost]],3,FALSE),0) -> 47.67 | I26: =IFERROR(IF(H26<>"",F26*H26,F26*G26),"") -> 0 | K26: ~~~~ | L26: =IFERROR(IF(M26="","",_xlfn.XLOOKUP(_xlfn.CONCAT(M26:O26),P!$Y:$Y,P!$X:$X,"UNAVAILABLE")),"UNAVAILABLE") -> EXT SMALL SIAY1.5 | M26: ACCELERA EXT SMALL 1R:1H | N26: SILVER GRAY | O26: 1.5 GAL | Q26: =IFERROR(VLOOKUP(SWPOLY[[#This Row],[PROD '#]],Table1[[Product '#]:[Cost]],3,FALSE),0) -> 253.64 | S26: =IFERROR(IF(R26<>"",P26*R26,P26*Q26),"") -> 0
B27: =IFERROR(IF(C27="","",_xlfn.XLOOKUP(_xlfn.CONCAT(C27:E27),P!$Y:$Y,P!$X:$X,"UNAVAILABLE")),"UNAVAILABLE") -> RSAL COLORBlck1 Pt | C27: HPF UNIVERSAL COLORANT | D27: Black | E27: 1 Pt | G27: =IFERROR(VLOOKUP(SWPATCH[[#This Row],[PROD '#]],Table1[[Product '#]:[Cost]],3,FALSE),0) -> 34.13 | I27: =IFERROR(IF(H27<>"",F27*H27,F27*G27),"") -> 0 | K27: ~~~~ | L27: =IFERROR(IF(M27="","",_xlfn.XLOOKUP(_xlfn.CONCAT(M27:O27),P!$Y:$Y,P!$X:$X,"UNAVAILABLE")),"UNAVAILABLE") -> ONE RESIN CLAR5 G | M27: ACCELERA ONE RESIN (SEE MIX CHART) | N27: CLEAR | O27: 5 GAL | Q27: =IFERROR(VLOOKUP(SWPOLY[[#This Row],[PROD '#]],Table1[[Product '#]:[Cost]],3,FALSE),0) -> 684.43 | S27: =IFERROR(IF(R27<>"",P27*R27,P27*Q27),"") -> 0
B28: =IFERROR(IF(C28="","",_xlfn.XLOOKUP(_xlfn.CONCAT(C28:E28),P!$Y:$Y,P!$X:$X,"UNAVAILABLE")),"UNAVAILABLE") -> RSAL COLORYeow1 Pt | C28: HPF UNIVERSAL COLORANT | D28: Yellow | E28: 1 Pt | G28: =IFERROR(VLOOKUP(SWPATCH[[#This Row],[PROD '#]],Table1[[Product '#]:[Cost]],3,FALSE),0) -> 58.85 | I28: =IFERROR(IF(H28<>"",F28*H28,F28*G28),"") -> 0 | K28: ~~~~ | L28: =IFERROR(IF(M28="","",_xlfn.XLOOKUP(_xlfn.CONCAT(M28:O28),P!$Y:$Y,P!$X:$X,"UNAVAILABLE")),"UNAVAILABLE") -> ONE HARDENCLAR1 G | M28: ACCELERA ONE HARDENER (SEE MIX CHART) | N28: CLEAR | O28: 1 GAL | Q28: =IFERROR(VLOOKUP(SWPOLY[[#This Row],[PROD '#]],Table1[[Product '#]:[Cost]],3,FALSE),0) -> 362.52 | S28: =IFERROR(IF(R28<>"",P28*R28,P28*Q28),"") -> 0
B29: =IFERROR(IF(C29="","",_xlfn.XLOOKUP(_xlfn.CONCAT(C29:E29),P!$Y:$Y,P!$X:$X,"UNAVAILABLE")),"UNAVAILABLE") -> RSAL COLORWhte25 | C29: HPF UNIVERSAL COLORANT | D29: White | E29: 25 Pt | G29: =IFERROR(VLOOKUP(SWPATCH[[#This Row],[PROD '#]],Table1[[Product '#]:[Cost]],3,FALSE),0) -> 431.37 | I29: =IFERROR(IF(H29<>"",F29*H29,F29*G29),"") -> 0 | K29: ~~~~ | L29: =IFERROR(IF(M29="","",_xlfn.XLOOKUP(_xlfn.CONCAT(M29:O29),P!$Y:$Y,P!$X:$X,"UNAVAILABLE")),"UNAVAILABLE") -> 5 66% SOLICLAR10 | M29: ACCELERA 5 66% SOLIDS 1:1 | N29: CLEAR | O29: 10 GAL | Q29: =IFERROR(VLOOKUP(SWPOLY[[#This Row],[PROD '#]],Table1[[Product '#]:[Cost]],3,FALSE),0) -> 800.36 | S29: =IFERROR(IF(R29<>"",P29*R29,P29*Q29),"") -> 0
B30: =IFERROR(IF(C30="","",_xlfn.XLOOKUP(_xlfn.CONCAT(C30:E30),P!$Y:$Y,P!$X:$X,"UNAVAILABLE")),"UNAVAILABLE") | G30: =IFERROR(VLOOKUP(SWPATCH[[#This Row],[PROD '#]],Table1[[Product '#]:[Cost]],3,FALSE),0) -> 0 | I30: =IFERROR(IF(H30<>"",F30*H30,F30*G30),"") -> 0 | K30: ~~~~ | L30: =IFERROR(IF(M30="","",_xlfn.XLOOKUP(_xlfn.CONCAT(M30:O30),P!$Y:$Y,P!$X:$X,"UNAVAILABLE")),"UNAVAILABLE") | Q30: =IFERROR(VLOOKUP(SWPOLY[[#This Row],[PROD '#]],Table1[[Product '#]:[Cost]],3,FALSE),0) -> 0 | S30: =IFERROR(IF(R30<>"",P30*R30,P30*Q30),"") -> 0
B31: =IFERROR(IF(C31="","",_xlfn.XLOOKUP(_xlfn.CONCAT(C31:E31),P!$Y:$Y,P!$X:$X,"UNAVAILABLE")),"UNAVAILABLE") | G31: =IFERROR(VLOOKUP(SWPATCH[[#This Row],[PROD '#]],Table1[[Product '#]:[Cost]],3,FALSE),0) -> 0 | I31: =IFERROR(IF(H31<>"",F31*H31,F31*G31),"") -> 0 | K31: ~~~~ | L31: =IFERROR(IF(M31="","",_xlfn.XLOOKUP(_xlfn.CONCAT(M31:O31),P!$Y:$Y,P!$X:$X,"UNAVAILABLE")),"UNAVAILABLE") | Q31: =IFERROR(VLOOKUP(SWPOLY[[#This Row],[PROD '#]],Table1[[Product '#]:[Cost]],3,FALSE),0) -> 0 | S31: =IFERROR(IF(R31<>"",P31*R31,P31*Q31),"") -> 0
B32: Total | C32: Total | I32: =SUBTOTAL(109,SWPATCH[EXTENSION]) -> 0 | J32: =SUBTOTAL(103,SWPATCH[WEIGHT]) -> 0 | K32: ~~~~ | L32: Total | M32: Total | S32: =SUBTOTAL(109,SWPOLY[EXTENSION]) -> 0 | T32: =SUBTOTAL(103,SWPOLY[WEIGHT]) -> 0
K33: ~~~~
B34: POLY-CRETE | C34: POLY-CRETE | K34: ~~~~ | L34: POLYURETHANE | M34: POLYURETHANE
B35: PROD # | C35: PRODUCT | D35: COLOR | E35: UOM | F35: QTY | G35: UNIT RATE | H35: QUOTED RATE | I35: EXTENSION | J35: WEIGHT | K35: ~~~~ | L35: PROD # | M35: PRODUCT | N35: COLOR | O35: UOM | P35: QTY | Q35: UNIT RATE | R35: QUOTED RATE | S35: EXTENSION | T35: WEIGHT
B36: =IFERROR(IF(C36="","",_xlfn.XLOOKUP(_xlfn.CONCAT(C36:E36),P!$Y:$Y,P!$X:$X,"UNAVAILABLE")),"UNAVAILABLE") -> E COLOR-FABLUEKIT | C36: POLY-CRETE COLOR-FAST | D36: BLUE | E36: KIT | G36: =IFERROR(VLOOKUP(SWCRETE[[#This Row],[PROD '#]],Table1[[Product '#]:[Cost]],3,FALSE),0) -> 154.78 | I36: =IFERROR(IF(H36<>"",F36*H36,F36*G36),"") -> 0 | K36: ~~~~ | L36: =IFERROR(IF(M36="","",_xlfn.XLOOKUP(_xlfn.CONCAT(M36:O36),P!$Y:$Y,P!$X:$X,"UNAVAILABLE")),"UNAVAILABLE") -> 4638 HS POCLAR3 G | M36: RESUTILE 4638 HS POLYURETHANE FLOOR ENAMEL | N36: CLEAR | O36: 3 GAL | Q36: =IFERROR(VLOOKUP(SWURETHANE[[#This Row],[PROD '#]],Table1[[Product '#]:[Cost]],3,FALSE),0) -> 305.43 | S36: =IFERROR(IF(R36<>"",P36*R36,P36*Q36),"") -> 0
B37: =IFERROR(IF(C37="","",_xlfn.XLOOKUP(_xlfn.CONCAT(C37:E37),P!$Y:$Y,P!$X:$X,"UNAVAILABLE")),"UNAVAILABLE") -> E HF ACCELN//A1 Q | C37: POLY-CRETE HF ACCELERATOR LOW TEMPERATURE AID | D37: N/A | E37: 1 Qt | G37: =IFERROR(VLOOKUP(SWCRETE[[#This Row],[PROD '#]],Table1[[Product '#]:[Cost]],3,FALSE),0) -> 43.8 | I37: =IFERROR(IF(H37<>"",F37*H37,F37*G37),"") -> 0 | K37: ~~~~ | L37: =IFERROR(IF(M37="","",_xlfn.XLOOKUP(_xlfn.CONCAT(M37:O37),P!$Y:$Y,P!$X:$X,"UNAVAILABLE")),"UNAVAILABLE") -> 4640 HTS 1CLAR1. | M37: RESUTILE 4640 HTS 100 HS HIGH TRAFFIC URETHANE ENAMEL | N37: CLEAR | O37: 1.2 GAL | Q37: =IFERROR(VLOOKUP(SWURETHANE[[#This Row],[PROD '#]],Table1[[Product '#]:[Cost]],3,FALSE),0) -> 267.77 | S37: =IFERROR(IF(R37<>"",P37*R37,P37*Q37),"") -> 0
B38: =IFERROR(IF(C38="","",_xlfn.XLOOKUP(_xlfn.CONCAT(C38:E38),P!$Y:$Y,P!$X:$X,"UNAVAILABLE")),"UNAVAILABLE") -> E HF HS URCHALKIT | C38: POLY-CRETE HF HS URETHANE CONCRETE COATING | D38: CHARCOAL | E38: KIT | G38: =IFERROR(VLOOKUP(SWCRETE[[#This Row],[PROD '#]],Table1[[Product '#]:[Cost]],3,FALSE),0) -> 79.45 | I38: =IFERROR(IF(H38<>"",F38*H38,F38*G38),"") -> 0 | K38: ~~~~ | L38: =IFERROR(IF(M38="","",_xlfn.XLOOKUP(_xlfn.CONCAT(M38:O38),P!$Y:$Y,P!$X:$X,"UNAVAILABLE")),"UNAVAILABLE") -> 4641 HPS 1CLAR.9 | M38: RESUTILE 4641 HPS 100 HS ALIPHATIC URETHANE TOPCOAT | N38: CLEAR | O38: .9 GAL | Q38: =IFERROR(VLOOKUP(SWURETHANE[[#This Row],[PROD '#]],Table1[[Product '#]:[Cost]],3,FALSE),0) -> 234.81 | S38: =IFERROR(IF(R38<>"",P38*R38,P38*Q38),"") -> 0
B39: =IFERROR(IF(C39="","",_xlfn.XLOOKUP(_xlfn.CONCAT(C39:E39),P!$Y:$Y,P!$X:$X,"UNAVAILABLE")),"UNAVAILABLE") -> E HF HS URDAAYKIT | C39: POLY-CRETE HF HS URETHANE CONCRETE COATING | D39: DARK GRAY | E39: KIT | G39: =IFERROR(VLOOKUP(SWCRETE[[#This Row],[PROD '#]],Table1[[Product '#]:[Cost]],3,FALSE),0) -> 79.45 | I39: =IFERROR(IF(H39<>"",F39*H39,F39*G39),"") -> 0 | K39: ~~~~ | L39: =IFERROR(IF(M39="","",_xlfn.XLOOKUP(_xlfn.CONCAT(M39:O39),P!$Y:$Y,P!$X:$X,"UNAVAILABLE")),"UNAVAILABLE") -> AQUA 4410 CHAL1.2 | M39: RESUTILE AQUA 4410 WB ALIPHATIC URETHANE - COLOR | N39: CHARCOAL | O39: 1.25 GAL | Q39: =IFERROR(VLOOKUP(SWURETHANE[[#This Row],[PROD '#]],Table1[[Product '#]:[Cost]],3,FALSE),0) -> 132.41 | S39: =IFERROR(IF(R39<>"",P39*R39,P39*Q39),"") -> 0
B40: =IFERROR(IF(C40="","",_xlfn.XLOOKUP(_xlfn.CONCAT(C40:E40),P!$Y:$Y,P!$X:$X,"UNAVAILABLE")),"UNAVAILABLE") -> E MD HS URDAAYKIT | C40: POLY-CRETE MD HS URETHANE CONCRETE COATING | D40: DARK GRAY | E40: KIT | G40: =IFERROR(VLOOKUP(SWCRETE[[#This Row],[PROD '#]],Table1[[Product '#]:[Cost]],3,FALSE),0) -> 116.52 | I40: =IFERROR(IF(H40<>"",F40*H40,F40*G40),"") -> 0 | K40: ~~~~ | L40: =IFERROR(IF(M40="","",_xlfn.XLOOKUP(_xlfn.CONCAT(M40:O40),P!$Y:$Y,P!$X:$X,"UNAVAILABLE")),"UNAVAILABLE") -> AQUA 4411 CLAR1.2 | M40: RESUTILE AQUA 4411 WB ALIPHATIC URETHANE - CLEAR | N40: CLEAR | O40: 1.25 GAL | Q40: =IFERROR(VLOOKUP(SWURETHANE[[#This Row],[PROD '#]],Table1[[Product '#]:[Cost]],3,FALSE),0) -> 143.01 | S40: =IFERROR(IF(R40<>"",P40*R40,P40*Q40),"") -> 0
B41: =IFERROR(IF(C41="","",_xlfn.XLOOKUP(_xlfn.CONCAT(C41:E41),P!$Y:$Y,P!$X:$X,"UNAVAILABLE")),"UNAVAILABLE") -> E SL HS SEGRAYKIT | C41: POLY-CRETE SL HS SELF LEVELING URETHANE | D41: GRAY | E41: KIT | G41: =IFERROR(VLOOKUP(SWCRETE[[#This Row],[PROD '#]],Table1[[Product '#]:[Cost]],3,FALSE),0) -> 102.4 | I41: =IFERROR(IF(H41<>"",F41*H41,F41*G41),"") -> 0 | K41: ~~~~ | L41: =IFERROR(IF(M41="","",_xlfn.XLOOKUP(_xlfn.CONCAT(M41:O41),P!$Y:$Y,P!$X:$X,"UNAVAILABLE")),"UNAVAILABLE") | Q41: =IFERROR(VLOOKUP(SWURETHANE[[#This Row],[PROD '#]],Table1[[Product '#]:[Cost]],3,FALSE),0) -> 0 | S41: =IFERROR(IF(R41<>"",P41*R41,P41*Q41),"") -> 0
B42: =IFERROR(IF(C42="","",_xlfn.XLOOKUP(_xlfn.CONCAT(C42:E42),P!$Y:$Y,P!$X:$X,"UNAVAILABLE")),"UNAVAILABLE") -> E TF PLUS N//AKIT | C42: POLY-CRETE TF PLUS COVE VERTICAL APPLICATIONS | D42: N/A | E42: KIT | G42: =IFERROR(VLOOKUP(SWCRETE[[#This Row],[PROD '#]],Table1[[Product '#]:[Cost]],3,FALSE),0) -> 31.8 | I42: =IFERROR(IF(H42<>"",F42*H42,F42*G42),"") -> 0 | K42: ~~~~ | L42: =IFERROR(IF(M42="","",_xlfn.XLOOKUP(_xlfn.CONCAT(M42:O42),P!$Y:$Y,P!$X:$X,"UNAVAILABLE")),"UNAVAILABLE") | Q42: =IFERROR(VLOOKUP(SWURETHANE[[#This Row],[PROD '#]],Table1[[Product '#]:[Cost]],3,FALSE),0) -> 0 | S42: =IFERROR(IF(R42<>"",P42*R42,P42*Q42),"") -> 0
B43: =IFERROR(IF(C43="","",_xlfn.XLOOKUP(_xlfn.CONCAT(C43:E43),P!$Y:$Y,P!$X:$X,"UNAVAILABLE")),"UNAVAILABLE") -> E TF PLUS CHAL1.7 | C43: POLY-CRETE TF PLUS PRIMER/TOPCOAT | D43: CHARCOAL | E43: KIT | G43: =IFERROR(VLOOKUP(SWCRETE[[#This Row],[PROD '#]],Table1[[Product '#]:[Cost]],3,FALSE),0) -> 53.55 | I43: =IFERROR(IF(H43<>"",F43*H43,F43*G43),"") -> 0 | K43: ~~~~ | L43: =IFERROR(IF(M43="","",_xlfn.XLOOKUP(_xlfn.CONCAT(M43:O43),P!$Y:$Y,P!$X:$X,"UNAVAILABLE")),"UNAVAILABLE") | Q43: =IFERROR(VLOOKUP(SWURETHANE[[#This Row],[PROD '#]],Table1[[Product '#]:[Cost]],3,FALSE),0) -> 0 | S43: =IFERROR(IF(R43<>"",P43*R43,P43*Q43),"") -> 0
B44: =IFERROR(IF(C44="","",_xlfn.XLOOKUP(_xlfn.CONCAT(C44:E44),P!$Y:$Y,P!$X:$X,"UNAVAILABLE")),"UNAVAILABLE") -> E WR COVE REEDKIT | C44: POLY-CRETE WR COVE BASE, SLOPE/PATCHING | D44: RED | E44: KIT | G44: =IFERROR(VLOOKUP(SWCRETE[[#This Row],[PROD '#]],Table1[[Product '#]:[Cost]],3,FALSE),0) -> 57.67 | I44: =IFERROR(IF(H44<>"",F44*H44,F44*G44),"") -> 0 | K44: ~~~~ | L44: =IFERROR(IF(M44="","",_xlfn.XLOOKUP(_xlfn.CONCAT(M44:O44),P!$Y:$Y,P!$X:$X,"UNAVAILABLE")),"UNAVAILABLE") | Q44: =IFERROR(VLOOKUP(SWURETHANE[[#This Row],[PROD '#]],Table1[[Product '#]:[Cost]],3,FALSE),0) -> 0 | S44: =IFERROR(IF(R44<>"",P44*R44,P44*Q44),"") -> 0
B45: =IFERROR(IF(C45="","",_xlfn.XLOOKUP(_xlfn.CONCAT(C45:E45),P!$Y:$Y,P!$X:$X,"UNAVAILABLE")),"UNAVAILABLE") | G45: =IFERROR(VLOOKUP(SWCRETE[[#This Row],[PROD '#]],Table1[[Product '#]:[Cost]],3,FALSE),0) -> 0 | I45: =IFERROR(IF(H45<>"",F45*H45,F45*G45),"") -> 0 | K45: ~~~~ | L45: =IFERROR(IF(M45="","",_xlfn.XLOOKUP(_xlfn.CONCAT(M45:O45),P!$Y:$Y,P!$X:$X,"UNAVAILABLE")),"UNAVAILABLE") | Q45: =IFERROR(VLOOKUP(SWURETHANE[[#This Row],[PROD '#]],Table1[[Product '#]:[Cost]],3,FALSE),0) -> 0 | S45: =IFERROR(IF(R45<>"",P45*R45,P45*Q45),"") -> 0
B46: =IFERROR(IF(C46="","",_xlfn.XLOOKUP(_xlfn.CONCAT(C46:E46),P!$Y:$Y,P!$X:$X,"UNAVAILABLE")),"UNAVAILABLE") | G46: =IFERROR(VLOOKUP(SWCRETE[[#This Row],[PROD '#]],Table1[[Product '#]:[Cost]],3,FALSE),0) -> 0 | I46: =IFERROR(IF(H46<>"",F46*H46,F46*G46),"") -> 0 | K46: ~~~~ | L46: =IFERROR(IF(M46="","",_xlfn.XLOOKUP(_xlfn.CONCAT(M46:O46),P!$Y:$Y,P!$X:$X,"UNAVAILABLE")),"UNAVAILABLE") | Q46: =IFERROR(VLOOKUP(SWURETHANE[[#This Row],[PROD '#]],Table1[[Product '#]:[Cost]],3,FALSE),0) -> 0 | S46: =IFERROR(IF(R46<>"",P46*R46,P46*Q46),"") -> 0
B47: =IFERROR(IF(C47="","",_xlfn.XLOOKUP(_xlfn.CONCAT(C47:E47),P!$Y:$Y,P!$X:$X,"UNAVAILABLE")),"UNAVAILABLE") | G47: =IFERROR(VLOOKUP(SWCRETE[[#This Row],[PROD '#]],Table1[[Product '#]:[Cost]],3,FALSE),0) -> 0 | I47: =IFERROR(IF(H47<>"",F47*H47,F47*G47),"") -> 0 | K47: ~~~~ | L47: =IFERROR(IF(M47="","",_xlfn.XLOOKUP(_xlfn.CONCAT(M47:O47),P!$Y:$Y,P!$X:$X,"UNAVAILABLE")),"UNAVAILABLE") | Q47: =IFERROR(VLOOKUP(SWURETHANE[[#This Row],[PROD '#]],Table1[[Product '#]:[Cost]],3,FALSE),0) -> 0 | S47: =IFERROR(IF(R47<>"",P47*R47,P47*Q47),"") -> 0
B48: =IFERROR(IF(C48="","",_xlfn.XLOOKUP(_xlfn.CONCAT(C48:E48),P!$Y:$Y,P!$X:$X,"UNAVAILABLE")),"UNAVAILABLE") | G48: =IFERROR(VLOOKUP(SWCRETE[[#This Row],[PROD '#]],Table1[[Product '#]:[Cost]],3,FALSE),0) -> 0 | I48: =IFERROR(IF(H48<>"",F48*H48,F48*G48),"") -> 0 | K48: ~~~~ | L48: =IFERROR(IF(M48="","",_xlfn.XLOOKUP(_xlfn.CONCAT(M48:O48),P!$Y:$Y,P!$X:$X,"UNAVAILABLE")),"UNAVAILABLE") | Q48: =IFERROR(VLOOKUP(SWURETHANE[[#This Row],[PROD '#]],Table1[[Product '#]:[Cost]],3,FALSE),0) -> 0 | S48: =IFERROR(IF(R48<>"",P48*R48,P48*Q48),"") -> 0
B49: Total | C49: Total | I49: =SUBTOTAL(109,SWCRETE[EXTENSION]) -> 0 | J49: =SUBTOTAL(103,SWCRETE[WEIGHT]) -> 0 | K49: ~~~~ | L49: Total | M49: Total | S49: =SUBTOTAL(109,SWURETHANE[EXTENSION]) -> 0 | T49: =SUBTOTAL(103,SWURETHANE[WEIGHT]) -> 0
K50: ~~~~
B51: MMA | C51: MMA | K51: ~~~~ | L51: AGGREGATES | M51: AGGREGATES
B52: PROD # | C52: PRODUCT | D52: COLOR | E52: UOM | F52: QTY | G52: UNIT RATE | H52: QUOTED RATE | I52: EXTENSION | J52: WEIGHT | K52: ~~~~ | L52: PROD # | M52: PRODUCT | N52: COLOR | O52: UOM | P52: QTY | Q52: UNIT RATE | R52: QUOTED RATE | S52: EXTENSION | T52: WEIGHT
B53: =IFERROR(IF(C53="","",_xlfn.XLOOKUP(_xlfn.CONCAT(C53:E53),P!$Y:$Y,P!$X:$X,"UNAVAILABLE")),"UNAVAILABLE") -> P-101 PRICLAR5 G | C53: CRYLAFLOR P-101 PRIMER | D53: CLEAR | E53: 5 GAL KIT | G53: =IFERROR(VLOOKUP(SWMMA[[#This Row],[PROD '#]],Table1[[Product '#]:[Cost]],3,FALSE),0) -> 323 | I53: =IFERROR(IF(H53<>"",F53*H53,F53*G53),"") -> 0 | K53: ~~~~ | L53: =IFERROR(IF(M53="","",_xlfn.XLOOKUP(_xlfn.CONCAT(M53:O53),P!$Y:$Y,P!$X:$X,"UNAVAILABLE")),"UNAVAILABLE") -> AR AGGREGAN//A50L | M53: 5115 MORTAR AGGREGATE BLEND | N53: N/A | O53: 50LB BAG | Q53: =IFERROR(VLOOKUP(SWAGG[[#This Row],[PROD '#]],Table1[[Product '#]:[Cost]],3,FALSE),0) -> 10.4 | S53: =IFERROR(IF(R53<>"",P53*R53,P53*Q53),"") -> 0
B54: =IFERROR(IF(C54="","",_xlfn.XLOOKUP(_xlfn.CONCAT(C54:E54),P!$Y:$Y,P!$X:$X,"UNAVAILABLE")),"UNAVAILABLE") -> G-201 BINBEGE5 G | C54: CRYLAFLOR G-201 BINDER | D54: BEIGE | E54: 5 GAL KIT | G54: =IFERROR(VLOOKUP(SWMMA[[#This Row],[PROD '#]],Table1[[Product '#]:[Cost]],3,FALSE),0) -> 341.92 | I54: =IFERROR(IF(H54<>"",F54*H54,F54*G54),"") -> 0 | K54: ~~~~ | L54: =IFERROR(IF(M54="","",_xlfn.XLOOKUP(_xlfn.CONCAT(M54:O54),P!$Y:$Y,P!$X:$X,"UNAVAILABLE")),"UNAVAILABLE") -> GRAVEL 3/1N//A50L | M54: 7310 PEA GRAVEL 3/16 X 3/8 | N54: N/A | O54: 50LB BAG | Q54: =IFERROR(VLOOKUP(SWAGG[[#This Row],[PROD '#]],Table1[[Product '#]:[Cost]],3,FALSE),0) -> 20.8 | S54: =IFERROR(IF(R54<>"",P54*R54,P54*Q54),"") -> 0
B55: =IFERROR(IF(C55="","",_xlfn.XLOOKUP(_xlfn.CONCAT(C55:E55),P!$Y:$Y,P!$X:$X,"UNAVAILABLE")),"UNAVAILABLE") -> T-301 TOPCHAY5 G | C55: CRYLAFLOR T-301 TOPCOAT | D55: CHARCOAL GRAY | E55: 5 GAL KIT | G55: =IFERROR(VLOOKUP(SWMMA[[#This Row],[PROD '#]],Table1[[Product '#]:[Cost]],3,FALSE),0) -> 329.56 | I55: =IFERROR(IF(H55<>"",F55*H55,F55*G55),"") -> 0 | K55: ~~~~ | L55: =IFERROR(IF(M55="","",_xlfn.XLOOKUP(_xlfn.CONCAT(M55:O55),P!$Y:$Y,P!$X:$X,"UNAVAILABLE")),"UNAVAILABLE") -> N//A50L | M55: F-60 | N55: N/A | O55: 50LB BAG | Q55: =IFERROR(VLOOKUP(SWAGG[[#This Row],[PROD '#]],Table1[[Product '#]:[Cost]],3,FALSE),0) -> 0 | S55: =IFERROR(IF(R55<>"",P55*R55,P55*Q55),"") -> 0
B56: =IFERROR(IF(C56="","",_xlfn.XLOOKUP(_xlfn.CONCAT(C56:E56),P!$Y:$Y,P!$X:$X,"UNAVAILABLE")),"UNAVAILABLE") -> T-303 FLEGREN5 G | C56: CRYLAFLOR T-303 FLEXIBLE TOPCOAT | D56: GREEN | E56: 5 GAL KIT | G56: =IFERROR(VLOOKUP(SWMMA[[#This Row],[PROD '#]],Table1[[Product '#]:[Cost]],3,FALSE),0) -> 424.9 | I56: =IFERROR(IF(H56<>"",F56*H56,F56*G56),"") -> 0 | K56: ~~~~ | L56: =IFERROR(IF(M56="","",_xlfn.XLOOKUP(_xlfn.CONCAT(M56:O56),P!$Y:$Y,P!$X:$X,"UNAVAILABLE")),"UNAVAILABLE") -> CO FLAKE KIIN40 | M56: 1-16IN DECO FLAKE - 40LB BAG | N56: KIWI SKIN | O56: 40LB BAG | Q56: =IFERROR(VLOOKUP(SWAGG[[#This Row],[PROD '#]],Table1[[Product '#]:[Cost]],3,FALSE),0) -> 143 | S56: =IFERROR(IF(R56<>"",P56*R56,P56*Q56),"") -> 0
B57: =IFERROR(IF(C57="","",_xlfn.XLOOKUP(_xlfn.CONCAT(C57:E57),P!$Y:$Y,P!$X:$X,"UNAVAILABLE")),"UNAVAILABLE") -> COVECLAR1 G | C57: CRYLAFLOR COVE | D57: CLEAR | E57: 1 GAL KIT | G57: =IFERROR(VLOOKUP(SWMMA[[#This Row],[PROD '#]],Table1[[Product '#]:[Cost]],3,FALSE),0) -> 117.7 | I57: =IFERROR(IF(H57<>"",F57*H57,F57*G57),"") -> 0 | K57: ~~~~ | L57: =IFERROR(IF(M57="","",_xlfn.XLOOKUP(_xlfn.CONCAT(M57:O57),P!$Y:$Y,P!$X:$X,"UNAVAILABLE")),"UNAVAILABLE") -> O FLAKE -GROT40 | M57: 1-8IN DECO FLAKE - 40LB BAG | N57: GRAY PARROT | O57: 40LB BAG | Q57: =IFERROR(VLOOKUP(SWAGG[[#This Row],[PROD '#]],Table1[[Product '#]:[Cost]],3,FALSE),0) -> 110 | S57: =IFERROR(IF(R57<>"",P57*R57,P57*Q57),"") -> 0
B58: =IFERROR(IF(C58="","",_xlfn.XLOOKUP(_xlfn.CONCAT(C58:E58),P!$Y:$Y,P!$X:$X,"UNAVAILABLE")),"UNAVAILABLE") -> CURE (BPON//A5 L | C58: CRYLAFLOR CURE (BPO) | D58: N/A | E58: 5 LB KIT | G58: =IFERROR(VLOOKUP(SWMMA[[#This Row],[PROD '#]],Table1[[Product '#]:[Cost]],3,FALSE),0) -> 122.41 | I58: =IFERROR(IF(H58<>"",F58*H58,F58*G58),"") -> 0 | K58: ~~~~ | L58: =IFERROR(IF(M58="","",_xlfn.XLOOKUP(_xlfn.CONCAT(M58:O58),P!$Y:$Y,P!$X:$X,"UNAVAILABLE")),"UNAVAILABLE") -> O FLAKE - AGVE40L | M58: 1-4IN DECO FLAKE - 40LB BAG | N58: AGAVE | O58: 40LB BAG | Q58: =IFERROR(VLOOKUP(SWAGG[[#This Row],[PROD '#]],Table1[[Product '#]:[Cost]],3,FALSE),0) -> 110 | S58: =IFERROR(IF(R58<>"",P58*R58,P58*Q58),"") -> 0
B59: =IFERROR(IF(C59="","",_xlfn.XLOOKUP(_xlfn.CONCAT(C59:E59),P!$Y:$Y,P!$X:$X,"UNAVAILABLE")),"UNAVAILABLE") -> COLOR - BWHTEKIT | C59: CRYLAFLOR COLOR - BACKGROUND ONLY | D59: WHITE | E59: =IF(C59="","","KIT") -> KIT | G59: =IFERROR(VLOOKUP(SWMMA[[#This Row],[PROD '#]],Table1[[Product '#]:[Cost]],3,FALSE),0) -> 112.8 | I59: =IFERROR(IF(H59<>"",F59*H59,F59*G59),"") -> 0 | K59: ~~~~ | L59: =IFERROR(IF(M59="","",_xlfn.XLOOKUP(_xlfn.CONCAT(M59:O59),P!$Y:$Y,P!$X:$X,"UNAVAILABLE")),"UNAVAILABLE") -> NO SAGN//A10 | M59: RESUFLOR NO SAG | N59: N/A | O59: 10 LBS | Q59: =IFERROR(VLOOKUP(SWAGG[[#This Row],[PROD '#]],Table1[[Product '#]:[Cost]],3,FALSE),0) -> 341.9 | S59: =IFERROR(IF(R59<>"",P59*R59,P59*Q59),"") -> 0
B60: =IFERROR(IF(C60="","",_xlfn.XLOOKUP(_xlfn.CONCAT(C60:E60),P!$Y:$Y,P!$X:$X,"UNAVAILABLE")),"UNAVAILABLE") -> BOND ENHAN//AKIT | C60: CRYLAFLOR BOND ENHANCER TO P-101 | D60: N/A | E60: =IF(C60="","","KIT") -> KIT | G60: =IFERROR(VLOOKUP(SWMMA[[#This Row],[PROD '#]],Table1[[Product '#]:[Cost]],3,FALSE),0) -> 30 | I60: =IFERROR(IF(H60<>"",F60*H60,F60*G60),"") -> 0 | K60: ~~~~ | L60: =IFERROR(IF(M60="","",_xlfn.XLOOKUP(_xlfn.CONCAT(M60:O60),P!$Y:$Y,P!$X:$X,"UNAVAILABLE")),"UNAVAILABLE") -> GRITN//A50L | M60: Q-ROCK 16 GRIT | N60: N/A | O60: 50LB BAG | Q60: =IFERROR(VLOOKUP(SWAGG[[#This Row],[PROD '#]],Table1[[Product '#]:[Cost]],3,FALSE),0) -> 16 | S60: =IFERROR(IF(R60<>"",P60*R60,P60*Q60),"") -> 0
B61: =IFERROR(IF(C61="","",_xlfn.XLOOKUP(_xlfn.CONCAT(C61:E61),P!$Y:$Y,P!$X:$X,"UNAVAILABLE")),"UNAVAILABLE") -> SL FILLERN//AKIT | C61: CRYLAFLOR SL FILLER BLEND TO G-201 | D61: N/A | E61: =IF(C61="","","KIT") -> KIT | G61: =IFERROR(VLOOKUP(SWMMA[[#This Row],[PROD '#]],Table1[[Product '#]:[Cost]],3,FALSE),0) -> 23.4 | I61: =IFERROR(IF(H61<>"",F61*H61,F61*G61),"") -> 0 | K61: ~~~~ | L61: =IFERROR(IF(M61="","",_xlfn.XLOOKUP(_xlfn.CONCAT(M61:O61),P!$Y:$Y,P!$X:$X,"UNAVAILABLE")),"UNAVAILABLE") -> SILICA SAN204050L | M61: 5310 DRY SILICA SAND - 20/40 | N61: 20/40 | O61: 50LB BAG | Q61: =IFERROR(VLOOKUP(SWAGG[[#This Row],[PROD '#]],Table1[[Product '#]:[Cost]],3,FALSE),0) -> 12.79 | S61: =IFERROR(IF(R61<>"",P61*R61,P61*Q61),"") -> 0
B62: =IFERROR(IF(C62="","",_xlfn.XLOOKUP(_xlfn.CONCAT(C62:E62),P!$Y:$Y,P!$X:$X,"UNAVAILABLE")),"UNAVAILABLE") -> BOND MT MN//AKIT | C62: CRYLAFLOR BOND MT METAL/TILE ENHANCER | D62: N/A | E62: =IF(C62="","","KIT") -> KIT | G62: =IFERROR(VLOOKUP(SWMMA[[#This Row],[PROD '#]],Table1[[Product '#]:[Cost]],3,FALSE),0) -> 85.8 | I62: =IFERROR(IF(H62<>"",F62*H62,F62*G62),"") -> 0 | K62: ~~~~ | L62: =IFERROR(IF(M62="","",_xlfn.XLOOKUP(_xlfn.CONCAT(M62:O62),P!$Y:$Y,P!$X:$X,"UNAVAILABLE")),"UNAVAILABLE") -> SILICA SAN406050L | M62: 5310 DRY SILICA SAND - 40/60 | N62: 40/60 | O62: 50LB BAG | Q62: =IFERROR(VLOOKUP(SWAGG[[#This Row],[PROD '#]],Table1[[Product '#]:[Cost]],3,FALSE),0) -> 18.85 | S62: =IFERROR(IF(R62<>"",P62*R62,P62*Q62),"") -> 0
B63: =IFERROR(IF(C63="","",_xlfn.XLOOKUP(_xlfn.CONCAT(C63:E63),P!$Y:$Y,P!$X:$X,"UNAVAILABLE")),"UNAVAILABLE") -> LTC ADDITN//AKIT | C63: CRYLAFLOR LTC ADDITIVE LOW TEMPERATURE | D63: N/A | E63: =IF(C63="","","KIT") -> KIT | G63: =IFERROR(VLOOKUP(SWMMA[[#This Row],[PROD '#]],Table1[[Product '#]:[Cost]],3,FALSE),0) -> 46.8 | I63: =IFERROR(IF(H63<>"",F63*H63,F63*G63),"") -> 0 | K63: ~~~~ | L63: =IFERROR(IF(M63="","",_xlfn.XLOOKUP(_xlfn.CONCAT(M63:O63),P!$Y:$Y,P!$X:$X,"UNAVAILABLE")),"UNAVAILABLE") -> SILICA SAN802050L | M63: 5310 DRY SILICA SAND - 80/120 | N63: 80/120 | O63: 50LB BAG | Q63: =IFERROR(VLOOKUP(SWAGG[[#This Row],[PROD '#]],Table1[[Product '#]:[Cost]],3,FALSE),0) -> 26 | S63: =IFERROR(IF(R63<>"",P63*R63,P63*Q63),"") -> 0
B64: =IFERROR(IF(C64="","",_xlfn.XLOOKUP(_xlfn.CONCAT(C64:E64),P!$Y:$Y,P!$X:$X,"UNAVAILABLE")),"UNAVAILABLE") -> CLEAN SOLN//AKIT | C64: CRYLAFLOR CLEAN SOLVENT TO CLEAN TOOLS | D64: N/A | E64: =IF(C64="","","KIT") -> KIT | G64: =IFERROR(VLOOKUP(SWMMA[[#This Row],[PROD '#]],Table1[[Product '#]:[Cost]],3,FALSE),0) -> 37.8 | I64: =IFERROR(IF(H64<>"",F64*H64,F64*G64),"") -> 0 | K64: ~~~~ | L64: =IFERROR(IF(M64="","",_xlfn.XLOOKUP(_xlfn.CONCAT(M64:O64),P!$Y:$Y,P!$X:$X,"UNAVAILABLE")),"UNAVAILABLE") -> QUARTZAMNO25 | M64: HPF COLOR QUARTZ | N64: AMERICANO | O64: 25 MESH | Q64: =IFERROR(VLOOKUP(SWAGG[[#This Row],[PROD '#]],Table1[[Product '#]:[Cost]],3,FALSE),0) -> 27.5 | S64: =IFERROR(IF(R64<>"",P64*R64,P64*Q64),"") -> 0
B65: Total | C65: Total | I65: =SUBTOTAL(109,SWMMA[EXTENSION]) -> 0 | J65: =SUBTOTAL(103,SWMMA[WEIGHT]) -> 0 | K65: ~~~~ | L65: Total | M65: Total | S65: =SUBTOTAL(109,SWAGG[EXTENSION]) -> 0 | T65: =SUBTOTAL(103,SWAGG[WEIGHT]) -> 0
K66: ~~~~
C67: LABOR - IN HOUSE INSTALLS | K67: ~~~~ | L67: ADDITIONAL PRODUCTS | M67: ADDITIONAL PRODUCTS
C68: ACTIVITY | F68: MEN | G68: DAYS / RATE | H68: COST / DAY | I68: EXTENSION | K68: ~~~~ | L68: PROD # | M68: PRODUCT | N68: COLOR | O68: UOM | P68: QTY | Q68: UNIT RATE | S68: EXTENSION | T68: WEIGHT
B69: 2-100 LABOR | C69: Prep | H69: 600 | I69: =F69*G69*H69 -> 0 | K69: ~~~~ | L69: =IF(M69="","",_xlfn.CONCAT(M69:O69)) -> Rentals (Equipment, Sunbelt etc)<-- Rentals Here | M69: Rentals (Equipment, Sunbelt etc) | N69: <-- Rentals Here | S69: =IF(P69="", Q69, P69*Q69) -> 0
B70: 2-100 LABOR | C70: Cove | H70: 600 | I70: =F70*G70*H70 -> 0 | K70: ~~~~ | L70: =IF(M70="","",_xlfn.CONCAT(M70:O70)) -> Rentals (Equipment, Sunbelt etc)<-- Rentals Here | M70: Rentals (Equipment, Sunbelt etc) | N70: <-- Rentals Here | S70: =IF(P70="", Q70, P70*Q70) -> 0
B71: 2-100 LABOR | C71: Trowel | H71: 600 | I71: =F71*G71*H71 -> 0 | K71: ~~~~ | L71: =IF(M71="","",_xlfn.CONCAT(M71:O71)) -> Rentals (Equipment, Sunbelt etc)<-- Rentals Here | M71: Rentals (Equipment, Sunbelt etc) | N71: <-- Rentals Here | S71: =IF(P71="", Q71, P71*Q71) -> 0
B72: 2-100 LABOR | C72: Seal | H72: 600 | I72: =F72*G72*H72 -> 0 | K72: ~~~~ | L72: =IF(M72="","",_xlfn.CONCAT(M72:O72)) -> Contingency | M72: Contingency | Q72: 0 | S72: =Q72 -> 0
B73: 2-100 LABOR | C73: Joints | H73: 600 | I73: =F73*G73*H73 -> 0 | K73: ~~~~ | L73: =IF(M73="","",_xlfn.CONCAT(M73:O73)) -> Box Truck Rental | M73: Box Truck Rental | Q73: 0 | S73: =Q73 -> 0
B74: 2-100 LABOR | C74: Labor 1 | H74: 600 | I74: =F74*G74*H74 -> 0 | K74: ~~~~ | L74: =IFERROR(IF(M74="","",_xlfn.XLOOKUP(_xlfn.CONCAT(M74:O74),P!$Y:$Y,P!$X:$X,"UNAVAILABLE")),"UNAVAILABLE") -> S (30 TUBEN//ATU | M74: NP-1 TUBES (30 TUBE/CASE) | N74: N/A | O74: TUBE | Q74: =IFERROR(VLOOKUP(L74,P!$X:$Z,3,FALSE),0) -> 8.29 | S74: =Q74*P74 -> 0
B75: 2-100 LABOR | C75: Labor 2 | H75: 600 | I75: =F75*G75*H75 -> 0 | K75: ~~~~ | L75: =IF(M75="","",_xlfn.XLOOKUP(_xlfn.CONCAT(M75:O75),P!$J:$J,P!$I:$I,"UNAVAILABLE")) -> JS4U-SG | M75: 600 UV (SSP JS-600 ALIPHATIC POLYUREA) | N75: STANDARD GRAY | O75: 1 GAL BOX | Q75: =IFERROR(VLOOKUP(L75,P!$X:$Z,3,FALSE),0) -> 125.4 | S75: =Q75*P75 -> 0
B76: 2-100 LABOR | C76: Labor 3 | H76: 600 | I76: =F76*G76*H76 -> 0 | K76: ~~~~ | L76: =IFERROR(IF(M76="","",_xlfn.XLOOKUP(_xlfn.CONCAT(M76:O76),P!$Y:$Y,P!$X:$X,"UNAVAILABLE")),"UNAVAILABLE") -> TUBES / CASTAYTU | M76: RS88 (12 TUBES / CASE) | N76: STANDARD GRAY | O76: TUBE | Q76: =IFERROR(VLOOKUP(L76,P!$X:$Z,3,FALSE),0) -> 38.5 | S76: =Q76*P76 -> 0
B77: 2-100 LABOR | C77: Labor 4 | H77: 600 | I77: =F77*G77*H77 -> 0 | K77: ~~~~ | L77: =IFERROR(IF(M77="","",_xlfn.XLOOKUP(_xlfn.CONCAT(M77:O77),P!$Y:$Y,P!$X:$X,"UNAVAILABLE")),"UNAVAILABLE") -> TUBES / CAGRAYTU | M77: RS65 (12 TUBES / CASE) | N77: GRAY | O77: TUBE | Q77: =IFERROR(VLOOKUP(L77,P!$X:$Z,3,FALSE),0) -> 38.5 | S77: =Q77*P77 -> 0
B78: 4-100 SUBCONTRACTOR | C78: Subcontractor Work Order | H78: 0 | I78: =H78 -> 0 | K78: ~~~~ | L78: =IF(M78="","",_xlfn.CONCAT(M78:O78)) | S78: =Q78*P78 -> 0
B79: 7-100 AIRLINE EXPENSES | C79: Airline Expenses | H79: 420 | I79: =F79*G79*H79 -> 0 | K79: ~~~~ | L79: =IF(M79="","",_xlfn.CONCAT(M79:O79)) | S79: =Q79*P79 -> 0
B80: 7-200 HOTEL EXPENSES | C80: Hotel Expenses | H80: 180 | I80: =F80*G80*H80 -> 0 | K80: ~~~~ | L80: =IF(M80="","",_xlfn.CONCAT(M80:O80)) | S80: =Q80*P80 -> 0
B81: 7-300 AUTO RENTAL | C81: Auto Rental | H81: 65 | I81: =F81*G81*H81 -> 0 | K81: ~~~~ | L81: =IF(M81="","",_xlfn.CONCAT(M81:O81)) | S81: =Q81*P81 -> 0
B82: 7-400 MILEAGE/FUEL EXPENSE | C82: Mileage/Fuel Expense | H82: 0.75 | I82: =F82*H82 -> 0 | K82: ~~~~ | L82: =IF(M82="","",_xlfn.CONCAT(M82:O82)) | S82: =Q82*P82 -> 0
B83: 7-600 PARKING / TOLLS | C83: Parking / Tolls | I83: =H83 -> 0 | K83: ~~~~ | L83: =IF(M83="","",_xlfn.CONCAT(M83:O83)) | S83: =Q83*P83 -> 0
B84: 7-750 PER DIEM (TRAVEL DAYS) | C84: Per Diem for Travel Days Only | H84: 38.25 | I84: =F84*G84*H84 -> 0 | K84: ~~~~ | L84: =IF(M84="","",_xlfn.CONCAT(M84:O84)) | S84: =Q84*P84 -> 0
B85: 7-760 PER DIEM (WORK DAYS) | C85: Per Diem for Work Days Only | H85: 51 | I85: =F85*G85*H85 -> 0 | K85: ~~~~ | L85: =IF(M85="","",_xlfn.CONCAT(M85:O85)) | S85: =Q85*P85 -> 0
B86: 7-770 TRAVEL PAY | C86: Travel Pay | H86: 325 | I86: =F86*G86*H86 -> 0 | K86: ~~~~ | L86: =IF(M86="","",_xlfn.CONCAT(M86:O86)) | S86: =Q86*P86 -> 0
C87: Total | I87: =SUBTOTAL(109,SWLABOR[EXTENSION]) -> 0 | K87: ~~~~ | M87: Total | S87: =SUBTOTAL(109, SWADDS[EXTENSION]) -> 0 | T87: =SUBTOTAL(103,SWADDS[WEIGHT]) -> 0
K88: ~~~~
C89: COST ALLOCATION | K89: ~~~~ | M89: SUMMARY
C90: MATERIAL / LABOR | K90: ~~~~ | M90: TAX AND TOTAL | P90: MARK UP
C91: 1-100 MATERIALS | D91: =SUM(SWPRIME[[#Totals],[EXTENSION]],SWPATCH[[#Totals],[EXTENSION]],SWPOLY[[#Totals],[EXTENSION]],SWCRETE[[#Totals],[EXTENSION]],SWMMA[[#Totals],[EXTENSION]],SWAGG[[#Totals],[EXTENSION]],SWURETHANE[[#Totals],[EXTENSION]],SWEPOXY[[#Totals],[EXTENSION]],S72:S86) -> 0 | F91: 7-750 PER DIEM (TRAVEL DAYS) | H91: =I84 -> 0 | K91: ~~~~ | M91: SUBTOTAL | N91: =SUM(D91:E100,H91:I99,D104:E106,H104:I106,H101) -> 0 | P91: TAX - M|R|F | Q91: =PO!Q2 -> 0.1 | R91: =PO!Q4 -> 0.1 | S91: =PO!Q6 -> 0.1
C92: 2-100 LABOR | D92: =SUMIF($B$69:$B$87,C92,$I$69:$I$87) -> 0 | F92: 7-760 PER DIEM (WORK DAYS) | H92: =I85 -> 0 | K92: ~~~~ | M92: TAX ON MATERIALS | N92: =IFERROR(ROUND(IF(Q91=0,PO!$Q$2,Q91)*D91,2),0) -> 0 | P92: MARK UP % | R92: =IF(IFERROR(ROUND(SUM(R94/N96),2),0)>(-1),IFERROR(ROUND(SUM(R94/N96),2),0),0) -> 0
C93: 4-100 SUBCONTRACTOR | D93: =SUMIF($B$69:$B$87,C93,$I$69:$I$87) -> 0 | F93: 7-770 TRAVEL PAY | H93: =I86 -> 0 | K93: ~~~~ | M93: TAX ON RENTALS | N93: =IFERROR(ROUND(IF(R91=0,PO!$Q$4,R91)*H97,2),0) -> 0 | P93: GROSS PROFIT % | R93: =IFERROR(ROUND(SUM(R94/Q97),2),0) -> 0
C94: 7-100 AIRLINE EXPENSES | D94: =SUMIF($B$69:$B$87,C94,$I$69:$I$87) -> 0 | F94: 5-000 OTHER COSTS | K94: ~~~~ | M94: TAX ON FREIGHT | N94: =IFERROR(ROUND(IF(S91=0,PO!$Q$6,S91)*SUM(H95:H96),2),0) -> 0 | P94: MARK UP $ | R94: =Q97-N96 -> 0
C95: 7-200 HOTEL EXPENSES | D95: =SUMIF($B$69:$B$87,C95,$I$69:$I$87) -> 0 | F95: 5-100 FREIGHT | K95: ~~~~ | M95: WARRANTY MARKUP ( 0.7% ) | N95: =ROUND(Q97*0.007,2) -> 0 | P95: =IF(P96="","","BASE RECOMMENDED BID AMT") | R95: =IF(P96="","",ROUND(SUM(N91)*1.45+N92+N93+N94,0)+(ROUND(SUM(N91)*1.45+N92+N93+N94,0)*0.007))
C96: 7-300 AUTO RENTAL | D96: =SUMIF($B$69:$B$87,C96,$I$69:$I$87) -> 0 | F96: 5-100 RETURN FREIGHT | K96: ~~~~ | M96: TOTAL PROJECT COST | N96: =SUM(N91:N95)+IF(R96="",0,R96) -> 0 | P96: =IF(OR(INFO!D21="CA",INFO!I21="CA"),"CA LITIGATION FUND - 7.8%","") | R96: =IF(OR(INFO!$D$21="CA",INFO!$D$21="CA"),IF(D93=0,R95*0.078,""),"")
C97: 7-400 MILEAGE/FUEL EXPENSE | D97: =SUMIF($B$69:$B$87,C97,$I$69:$I$87) -> 0 | F97: 5-300 RENTALS | H97: =SUM(S69,S70, S71, S73) -> 0 | K97: ~~~~ | M97: ="CUSTOMER BID AMOUNT ("&TEXT(ROUND(SUM(N91)*1.45+N92+N93+N94,0)+(ROUND(SUM(N91)*1.45+N92+N93+N94,0)*0.007)+IF(R96="",0,R96),"$###,##0.00")&" Recommended)" -> CUSTOMER BID AMOUNT ($0.00 Recommended)
C98: 7-600 PARKING / TOLLS | D98: =SUMIF($B$69:$B$87,C98,$I$69:$I$87) -> 0 | F98: 5-400 TOOLS & SMALL EQUIPMENT | K98: ~~~~
C99: 5-500 CONSUMABLES SUPPLIES-BOX STORE | F99: 5-600 IN-HOUSE EQUIPMENT COST | K99: ~~~~ | M99: NOTES
C100: 5-550 PO CONSUMABLES SUPPLIES | F100: 5-900 MISC. EXPENSES | H100: =N94 -> 0 | K100: ~~~~
...

Sheet SGC
C1: ="Tax Rate on PO Tab: "&TEXT(PO!$Q$2,"##0.00#%")&" Material / "&TEXT(PO!$Q$4,"##0.00#%")&" Rental / "&TEXT(PO!$Q$6,"##0.00#%")&" Freight" -> Tax Rate on PO Tab: 10.00% Material / 10.00% Rental / 10.00% Freight
C2: **TO SELECT PRODUCTS - USE DROP DOWN MENU ON THE PRODUCT LINES AND SELECT MATERIAL, COLOR AND UOM
C3: **FOR ORDERS THAT HAVE QUOTES - ENTER IN QUOTED RATE INTO BLUE BOXES BELOW
B4: EPOXY/DECK COATINGS | C4: EPOXY/DECK COATINGS | L4: CRETE | M4: CRETE
B5: PROD # | C5: PRODUCT | D5: COLOR | E5: UOM | F5: QTY | G5: UNIT RATE | H5: QUOTED RATE | I5: EXTENSION | L5: PROD # | M5: PRODUCT | N5: COLOR | O5: UOM | P5: QTY | Q5: UNIT RATE | R5: QUOTED RATE | S5: EXTENSION
B6: =IF(C6="","",_xlfn.XLOOKUP(_xlfn.CONCAT(C6:E6),P!$J:$J,P!$I:$I,"UNAVAILABLE")) -> S-DEB-5 | C6: SGC DECK BASE COAT 308 | D6: =IFERROR(IF(C6="","","N/A"),"") -> N/A | E6: 5 GAL | G6: =IFERROR(VLOOKUP(B6,P!$X:$Z,3,FALSE),0) -> 396 | I6: =IF(RIOEPOXY[[#This Row],[QUOTED RATE]]="",RIOEPOXY[[#This Row],[UNIT RATE]]*RIOEPOXY[[#This Row],[QTY]],RIOEPOXY[[#This Row],[QUOTED RATE]]*RIOEPOXY[[#This Row],[QTY]]) -> 0 | L6: =IF(M6="","",_xlfn.XLOOKUP(_xlfn.CONCAT(M6:O6),P!$J:$J,P!$I:$I,"UNAVAILABLE")) -> S-GCA-5 | M6: SGC CRETE PART A | N6: N/A | O6: 5 GAL | P6: =IF($V$6>0,$V$6,0) -> 0 | Q6: =IFERROR(VLOOKUP(L6,P!$X:$Z,3,FALSE),0) -> 231 | S6: =IF(Table21[[#This Row],[QUOTED RATE]]="",Table21[[#This Row],[UNIT RATE]]*Table21[[#This Row],[QTY]],Table21[[#This Row],[QUOTED RATE]]*Table21[[#This Row],[QTY]]) -> 0 | U6: =ROUNDUP(SUM(U10:U18),0) -> 0 | V6: =MOD(_xlfn.CEILING.MATH(SUM(V10:V18),5)/5,10) -> 0
B7: =IF(C7="","",_xlfn.XLOOKUP(_xlfn.CONCAT(C7:E7),P!$J:$J,P!$I:$I,"UNAVAILABLE")) -> S-GPR-3 | C7: SGC SHIELD FLEX | D7: =IFERROR(IF(C7="","","N/A"),"") -> N/A | E7: 3 GAL | G7: =IFERROR(VLOOKUP(B7,P!$X:$Z,3,FALSE),0) -> 178.112 | I7: =IF(RIOEPOXY[[#This Row],[QUOTED RATE]]="",RIOEPOXY[[#This Row],[UNIT RATE]]*RIOEPOXY[[#This Row],[QTY]],RIOEPOXY[[#This Row],[QUOTED RATE]]*RIOEPOXY[[#This Row],[QTY]]) -> 0 | L7: =IF(M7="","",_xlfn.XLOOKUP(_xlfn.CONCAT(M7:O7),P!$J:$J,P!$I:$I,"UNAVAILABLE")) -> S-GCB-5 | M7: SGC CRETE PART B | N7: N/A | O7: 5 GAL | P7: =IF($V$6>0,$V$6,0) -> 0 | Q7: =IFERROR(VLOOKUP(L7,P!$X:$Z,3,FALSE),0) -> 231 | S7: =IF(Table21[[#This Row],[QUOTED RATE]]="",Table21[[#This Row],[UNIT RATE]]*Table21[[#This Row],[QTY]],Table21[[#This Row],[QUOTED RATE]]*Table21[[#This Row],[QTY]]) -> 0 | U7: =(SUM(U10:U18)) -> 0 | V7: =QUOTIENT(_xlfn.CEILING.MATH(SUM(V10:V18),5)/5,10) -> 0
B8: =IF(C8="","",_xlfn.XLOOKUP(_xlfn.CONCAT(C8:E8),P!$J:$J,P!$I:$I,"UNAVAILABLE")) -> FIBERTAPE | C8: FIBERGLASS TAPE | D8: =IFERROR(IF(C8="","","N/A"),"") -> N/A | E8: ROLL | G8: =IFERROR(VLOOKUP(B8,P!$X:$Z,3,FALSE),0) -> 33.1782 | I8: =IF(RIOEPOXY[[#This Row],[QUOTED RATE]]="",RIOEPOXY[[#This Row],[UNIT RATE]]*RIOEPOXY[[#This Row],[QTY]],RIOEPOXY[[#This Row],[QUOTED RATE]]*RIOEPOXY[[#This Row],[QTY]]) -> 0 | L8: =IF(M8="","",_xlfn.XLOOKUP(_xlfn.CONCAT(M8:O8),P!$J:$J,P!$I:$I,"UNAVAILABLE")) -> S-GCA-50 | M8: SGC CRETE PART A | N8: N/A | O8: 50 GAL | P8: =IF($V$7>0,$V$7,0) -> 0 | Q8: =IFERROR(VLOOKUP(L8,P!$X:$Z,3,FALSE),0) -> 2211 | S8: =IF(Table21[[#This Row],[QUOTED RATE]]="",Table21[[#This Row],[UNIT RATE]]*Table21[[#This Row],[QTY]],Table21[[#This Row],[QUOTED RATE]]*Table21[[#This Row],[QTY]]) -> 0 | U8: =COUNTIF($U$10:$U$18,">0") -> 0 | V8: =SUM(V10:V18)/5 -> 0
B9: =IF(C9="","",_xlfn.XLOOKUP(_xlfn.CONCAT(C9:E9),P!$J:$J,P!$I:$I,"UNAVAILABLE")) -> R-EPT-15 | C9: RIO COAT EPT | D9: =IFERROR(IF(C9="","","N/A"),"") -> N/A | E9: 15 GAL | G9: =IFERROR(VLOOKUP(B9,P!$X:$Z,3,FALSE),0) -> 825 | I9: =IF(RIOEPOXY[[#This Row],[QUOTED RATE]]="",RIOEPOXY[[#This Row],[UNIT RATE]]*RIOEPOXY[[#This Row],[QTY]],RIOEPOXY[[#This Row],[QUOTED RATE]]*RIOEPOXY[[#This Row],[QTY]]) -> 0 | L9: =IF(M9="","",_xlfn.XLOOKUP(_xlfn.CONCAT(M9:O9),P!$J:$J,P!$I:$I,"UNAVAILABLE")) -> S-GCB-50 | M9: SGC CRETE PART B | N9: N/A | O9: 50 GAL | P9: =IF($V$7>0,$V$7,0) -> 0 | Q9: =IFERROR(VLOOKUP(L9,P!$X:$Z,3,FALSE),0) -> 2211 | S9: =IF(Table21[[#This Row],[QUOTED RATE]]="",Table21[[#This Row],[UNIT RATE]]*Table21[[#This Row],[QTY]],Table21[[#This Row],[QUOTED RATE]]*Table21[[#This Row],[QTY]]) -> 0
B10: =IF(C10="","",_xlfn.XLOOKUP(_xlfn.CONCAT(C10:E10),P!$J:$J,P!$I:$I,"UNAVAILABLE")) -> ROAD10600 | C10: ROADWARE 10 MIN CONCRETE MENDER | D10: =IFERROR(IF(C10="","","N/A"),"") -> N/A | E10: 600ML | G10: =IFERROR(VLOOKUP(B10,P!$X:$Z,3,FALSE),0) -> 65.219 | I10: =IF(RIOEPOXY[[#This Row],[QUOTED RATE]]="",RIOEPOXY[[#This Row],[UNIT RATE]]*RIOEPOXY[[#This Row],[QTY]],RIOEPOXY[[#This Row],[QUOTED RATE]]*RIOEPOXY[[#This Row],[QTY]]) -> 0 | L10: =IF(M10="","",_xlfn.XLOOKUP(_xlfn.CONCAT(M10:O10),P!$J:$J,P!$I:$I,"UNAVAILABLE")) -> R-CSL-1 | M10: SL - PART C | N10: CLEAR | O10: KIT | Q10: =ROUND(IF(AND(U10<>"",U10>0),IFERROR(VLOOKUP(L10,P!$X:$Z,3,FALSE),0)+(IF(OR(U5=1,$U$6=SUM($U$10:$U$18)),$U$6,($U$6-SUM($U$10:$U$18))/$U$8)+$U10)/$P10*28.05,IFERROR(VLOOKUP(L10,P!$X:$Z,3,FALSE),0)),2) -> 8.34 | S10: =IF(Table21[[#This Row],[QUOTED RATE]]="",Table21[[#This Row],[UNIT RATE]]*Table21[[#This Row],[QTY]],Table21[[#This Row],[QUOTED RATE]]*Table21[[#This Row],[QTY]]) -> 0 | U10: =IF(AND(N10="PIGMENTED",IFERROR(FIND("SL",M10),FALSE),IFERROR(VLOOKUP(L10,P!$X:$Z,3,FALSE),0)<>0),(1/12*P10),IF(AND(N10="PIGMENTED",IFERROR(FIND("SL",M10),TRUE),IFERROR(VLOOKUP(L10,P!$X:$Z,3,FALSE),0)<>0),(1/4*P10),"")) | V10: =IF(P10="","",IF(IFERROR(FIND("CB",M10),FALSE),P10*0.25,P10*0.5))
B11: =IF(C11="","",_xlfn.XLOOKUP(_xlfn.CONCAT(C11:E11),P!$J:$J,P!$I:$I,"UNAVAILABLE")) -> R-EMP-15 | C11: RIO COAT EMP | D11: =IFERROR(IF(C11="","","N/A"),"") -> N/A | E11: 15 GAL | G11: =IFERROR(VLOOKUP(B11,P!$X:$Z,3,FALSE),0) -> 973.5 | I11: =IF(RIOEPOXY[[#This Row],[QUOTED RATE]]="",RIOEPOXY[[#This Row],[UNIT RATE]]*RIOEPOXY[[#This Row],[QTY]],RIOEPOXY[[#This Row],[QUOTED RATE]]*RIOEPOXY[[#This Row],[QTY]]) -> 0 | L11: =IF(M11="","",_xlfn.XLOOKUP(_xlfn.CONCAT(M11:O11),P!$J:$J,P!$I:$I,"UNAVAILABLE")) -> S-CSL-SB | M11: SL - PART C | N11: PIGMENTED | O11: KIT | Q11: =ROUND(IF(AND(U11<>"",U11>0),IFERROR(VLOOKUP(L11,P!$X:$Z,3,FALSE),0)+(IF(OR(U6=1,$U$6=SUM($U$10:$U$18)),$U$6,($U$6-SUM($U$10:$U$18))/U8)+U11)/P11*28.05,IFERROR(VLOOKUP(L11,P!$X:$Z,3,FALSE),0)),2) -> 8.34 | S11: =IF(Table21[[#This Row],[QUOTED RATE]]="",Table21[[#This Row],[UNIT RATE]]*Table21[[#This Row],[QTY]],Table21[[#This Row],[QUOTED RATE]]*Table21[[#This Row],[QTY]]) -> 0 | U11: =IF(AND(N11="PIGMENTED",IFERROR(FIND("SL",M11),FALSE),IFERROR(VLOOKUP(L11,P!$X:$Z,3,FALSE),0)<>0),(1/12*P11),IF(AND(N11="PIGMENTED",IFERROR(FIND("SL",M11),TRUE),IFERROR(VLOOKUP(L11,P!$X:$Z,3,FALSE),0)<>0),(1/4*P11),"")) -> 0 | V11: =IF(P11="","",IF(IFERROR(FIND("CB",M11),FALSE),P11*0.25,P11*0.5))
B12: =IF(C12="","",_xlfn.XLOOKUP(_xlfn.CONCAT(C12:E12),P!$J:$J,P!$I:$I,"UNAVAILABLE")) | D12: =IFERROR(IF(C12="","","N/A"),"") | G12: =IFERROR(VLOOKUP(B12,P!$X:$Z,3,FALSE),0) -> 0 | I12: =IF(RIOEPOXY[[#This Row],[QUOTED RATE]]="",RIOEPOXY[[#This Row],[UNIT RATE]]*RIOEPOXY[[#This Row],[QTY]],RIOEPOXY[[#This Row],[QUOTED RATE]]*RIOEPOXY[[#This Row],[QTY]]) -> 0 | L12: =IF(M12="","",_xlfn.XLOOKUP(_xlfn.CONCAT(M12:O12),P!$J:$J,P!$I:$I,"UNAVAILABLE")) -> R-CSF-1 | M12: SF - PART C | N12: N/A | O12: KIT | Q12: =ROUND(IF(AND(U12<>"",U12>0),IFERROR(VLOOKUP(L12,P!$X:$Z,3,FALSE),0)+(IF(OR(U7=1,$U$6=SUM($U$10:$U$18)),$U$6,($U$6-SUM($U$10:$U$18))/$U$8)+$U12)/$P12*28.05,IFERROR(VLOOKUP(L12,P!$X:$Z,3,FALSE),0)),2) -> 11.83 | S12: =IF(Table21[[#This Row],[QUOTED RATE]]="",Table21[[#This Row],[UNIT RATE]]*Table21[[#This Row],[QTY]],Table21[[#This Row],[QUOTED RATE]]*Table21[[#This Row],[QTY]]) -> 0 | U12: =IF(AND(N12="PIGMENTED",IFERROR(FIND("SL",M12),FALSE),IFERROR(VLOOKUP(L12,P!$X:$Z,3,FALSE),0)<>0),(1/12*P12),IF(AND(N12="PIGMENTED",IFERROR(FIND("SL",M12),TRUE),IFERROR(VLOOKUP(L12,P!$X:$Z,3,FALSE),0)<>0),(1/4*P12),"")) | V12: =IF(P12="","",IF(IFERROR(FIND("CB",M12),FALSE),P12*0.25,P12*0.5))
B13: =IF(C13="","",_xlfn.XLOOKUP(_xlfn.CONCAT(C13:E13),P!$J:$J,P!$I:$I,"UNAVAILABLE")) | D13: =IFERROR(IF(C13="","","N/A"),"") | G13: =IFERROR(VLOOKUP(B13,P!$X:$Z,3,FALSE),0) -> 0 | I13: =IF(RIOEPOXY[[#This Row],[QUOTED RATE]]="",RIOEPOXY[[#This Row],[UNIT RATE]]*RIOEPOXY[[#This Row],[QTY]],RIOEPOXY[[#This Row],[QUOTED RATE]]*RIOEPOXY[[#This Row],[QTY]]) -> 0 | L13: =IF(M13="","",_xlfn.XLOOKUP(_xlfn.CONCAT(M13:O13),P!$J:$J,P!$I:$I,"UNAVAILABLE")) -> R-CCB-1 | M13: CB - PART C | N13: PIGMENTED | O13: KIT | Q13: =ROUND(IF(AND(U13<>"",U13>0),IFERROR(VLOOKUP(L13,P!$X:$Z,3,FALSE),0)+(IF(OR(U8=1,$U$6=SUM($U$10:$U$18)),$U$6,($U$6-SUM($U$10:$U$18))/$U$8)+$U13)/$P13*28.05,IFERROR(VLOOKUP(L13,P!$X:$Z,3,FALSE),0)),2) -> 18.36 | S13: =IF(Table21[[#This Row],[QUOTED RATE]]="",Table21[[#This Row],[UNIT RATE]]*Table21[[#This Row],[QTY]],Table21[[#This Row],[QUOTED RATE]]*Table21[[#This Row],[QTY]]) -> 0 | U13: =IF(AND(N13="PIGMENTED",IFERROR(FIND("SL",M13),FALSE),IFERROR(VLOOKUP(L13,P!$X:$Z,3,FALSE),0)<>0),(1/12*P13),IF(AND(N13="PIGMENTED",IFERROR(FIND("SL",M13),TRUE),IFERROR(VLOOKUP(L13,P!$X:$Z,3,FALSE),0)<>0),(1/4*P13),"")) -> 0 | V13: =IF(P13="","",IF(IFERROR(FIND("CB",M13),FALSE),P13*0.25,P13*0.5))
B14: =IF(C14="","",_xlfn.XLOOKUP(_xlfn.CONCAT(C14:E14),P!$J:$J,P!$I:$I,"UNAVAILABLE")) | D14: =IFERROR(IF(C14="","","N/A"),"") | G14: =IFERROR(VLOOKUP(B14,P!$X:$Z,3,FALSE),0) -> 0 | I14: =IF(RIOEPOXY[[#This Row],[QUOTED RATE]]="",RIOEPOXY[[#This Row],[UNIT RATE]]*RIOEPOXY[[#This Row],[QTY]],RIOEPOXY[[#This Row],[QUOTED RATE]]*RIOEPOXY[[#This Row],[QTY]]) -> 0 | L14: =IF(M14="","",_xlfn.XLOOKUP(_xlfn.CONCAT(M14:O14),P!$J:$J,P!$I:$I,"UNAVAILABLE")) -> R-CTC-1 | M14: TC - PART C | N14: PIGMENTED | O14: KIT | Q14: =ROUND(IF(AND(U14<>"",U14>0),IFERROR(VLOOKUP(L14,P!$X:$Z,3,FALSE),0)+(IF(OR(U9=1,$U$6=SUM($U$10:$U$18)),$U$6,($U$6-SUM($U$10:$U$18))/$U$8)+$U14)/$P14*28.05,IFERROR(VLOOKUP(L14,P!$X:$Z,3,FALSE),0)),2) -> 11.22 | S14: =IF(Table21[[#This Row],[QUOTED RATE]]="",Table21[[#This Row],[UNIT RATE]]*Table21[[#This Row],[QTY]],Table21[[#This Row],[QUOTED RATE]]*Table21[[#This Row],[QTY]]) -> 0 | U14: =IF(AND(N14="PIGMENTED",IFERROR(FIND("SL",M14),FALSE),IFERROR(VLOOKUP(L14,P!$X:$Z,3,FALSE),0)<>0),(1/12*P14),IF(AND(N14="PIGMENTED",IFERROR(FIND("SL",M14),TRUE),IFERROR(VLOOKUP(L14,P!$X:$Z,3,FALSE),0)<>0),(1/4*P14),"")) -> 0 | V14: =IF(P14="","",IF(IFERROR(FIND("CB",M14),FALSE),P14*0.25,P14*0.5))
B15: =IF(C15="","",_xlfn.XLOOKUP(_xlfn.CONCAT(C15:E15),P!$J:$J,P!$I:$I,"UNAVAILABLE")) | D15: =IFERROR(IF(C15="","","N/A"),"") | G15: =IFERROR(VLOOKUP(B15,P!$X:$Z,3,FALSE),0) -> 0 | I15: =IF(RIOEPOXY[[#This Row],[QUOTED RATE]]="",RIOEPOXY[[#This Row],[UNIT RATE]]*RIOEPOXY[[#This Row],[QTY]],RIOEPOXY[[#This Row],[QUOTED RATE]]*RIOEPOXY[[#This Row],[QTY]]) -> 0 | L15: =IF(M15="","",_xlfn.XLOOKUP(_xlfn.CONCAT(M15:O15),P!$J:$J,P!$I:$I,"UNAVAILABLE")) -> S-SCS-1 | M15: SGC SPEED | N15: N/A | O15: 32 OZ | Q15: =ROUND(IF(AND(U15<>"",U15>0),IFERROR(VLOOKUP(L15,P!$X:$Z,3,FALSE),0)+(IF(OR(U10=1,$U$6=SUM($U$10:$U$18)),$U$6,($U$6-SUM($U$10:$U$18))/$U$8)+$U15)/$P15*28.05,IFERROR(VLOOKUP(L15,P!$X:$Z,3,FALSE),0)),2) -> 55 | S15: =IF(Table21[[#This Row],[QUOTED RATE]]="",Table21[[#This Row],[UNIT RATE]]*Table21[[#This Row],[QTY]],Table21[[#This Row],[QUOTED RATE]]*Table21[[#This Row],[QTY]]) -> 0 | U15: =IF(AND(N15="PIGMENTED",IFERROR(FIND("SL",M15),FALSE),IFERROR(VLOOKUP(L15,P!$X:$Z,3,FALSE),0)<>0),(1/12*P15),IF(AND(N15="PIGMENTED",IFERROR(FIND("SL",M15),TRUE),IFERROR(VLOOKUP(L15,P!$X:$Z,3,FALSE),0)<>0),(1/4*P15),"")) | V15: =IF(P15="","",IF(IFERROR(FIND("CB",M15),FALSE),P15*0.25,P15*0.5))
B16: =IF(C16="","",_xlfn.XLOOKUP(_xlfn.CONCAT(C16:E16),P!$J:$J,P!$I:$I,"UNAVAILABLE")) | D16: =IFERROR(IF(C16="","","N/A"),"") | G16: =IFERROR(VLOOKUP(B16,P!$X:$Z,3,FALSE),0) -> 0 | I16: =IF(RIOEPOXY[[#This Row],[QUOTED RATE]]="",RIOEPOXY[[#This Row],[UNIT RATE]]*RIOEPOXY[[#This Row],[QTY]],RIOEPOXY[[#This Row],[QUOTED RATE]]*RIOEPOXY[[#This Row],[QTY]]) -> 0 | L16: =IF(M16="","",_xlfn.XLOOKUP(_xlfn.CONCAT(M16:O16),P!$J:$J,P!$I:$I,"UNAVAILABLE")) | Q16: =ROUND(IF(AND(U16<>"",U16>0),IFERROR(VLOOKUP(L16,P!$X:$Z,3,FALSE),0)+(IF(OR(U11=1,$U$6=SUM($U$10:$U$18)),$U$6,($U$6-SUM($U$10:$U$18))/$U$8)+$U16)/$P16*28.05,IFERROR(VLOOKUP(L16,P!$X:$Z,3,FALSE),0)),2) -> 0 | S16: =IF(Table21[[#This Row],[QUOTED RATE]]="",Table21[[#This Row],[UNIT RATE]]*Table21[[#This Row],[QTY]],Table21[[#This Row],[QUOTED RATE]]*Table21[[#This Row],[QTY]]) -> 0 | U16: =IF(AND(N16="PIGMENTED",IFERROR(FIND("SL",M16),FALSE),IFERROR(VLOOKUP(L16,P!$X:$Z,3,FALSE),0)<>0),(1/12*P16),IF(AND(N16="PIGMENTED",IFERROR(FIND("SL",M16),TRUE),IFERROR(VLOOKUP(L16,P!$X:$Z,3,FALSE),0)<>0),(1/4*P16),"")) | V16: =IF(P16="","",IF(IFERROR(FIND("CB",M16),FALSE),P16*0.25,P16*0.5))
B17: =IF(C17="","",_xlfn.XLOOKUP(_xlfn.CONCAT(C17:E17),P!$J:$J,P!$I:$I,"UNAVAILABLE")) | D17: =IFERROR(IF(C17="","","N/A"),"") | G17: =IFERROR(VLOOKUP(B17,P!$X:$Z,3,FALSE),0) -> 0 | I17: =IF(RIOEPOXY[[#This Row],[QUOTED RATE]]="",RIOEPOXY[[#This Row],[UNIT RATE]]*RIOEPOXY[[#This Row],[QTY]],RIOEPOXY[[#This Row],[QUOTED RATE]]*RIOEPOXY[[#This Row],[QTY]]) -> 0 | L17: =IF(M17="","",_xlfn.XLOOKUP(_xlfn.CONCAT(M17:O17),P!$J:$J,P!$I:$I,"UNAVAILABLE")) -> R-CSF-1 | M17: SF - PART C | N17: N/A | O17: KIT | Q17: =ROUND(IF(AND(U17<>"",U17>0),IFERROR(VLOOKUP(L17,P!$X:$Z,3,FALSE),0)+(IF(OR(U12=1,$U$6=SUM($U$10:$U$18)),$U$6,($U$6-SUM($U$10:$U$18))/$U$8)+$U17)/$P17*28.05,IFERROR(VLOOKUP(L17,P!$X:$Z,3,FALSE),0)),2) -> 11.83 | S17: =IF(Table21[[#This Row],[QUOTED RATE]]="",Table21[[#This Row],[UNIT RATE]]*Table21[[#This Row],[QTY]],Table21[[#This Row],[QUOTED RATE]]*Table21[[#This Row],[QTY]]) -> 0 | U17: =IF(AND(N17="PIGMENTED",IFERROR(FIND("SL",M17),FALSE),IFERROR(VLOOKUP(L17,P!$X:$Z,3,FALSE),0)<>0),(1/12*P17),IF(AND(N17="PIGMENTED",IFERROR(FIND("SL",M17),TRUE),IFERROR(VLOOKUP(L17,P!$X:$Z,3,FALSE),0)<>0),(1/4*P17),"")) | V17: =IF(P17="","",IF(IFERROR(FIND("CB",M17),FALSE),P17*0.25,P17*0.5))
B18: =IF(C18="","",_xlfn.XLOOKUP(_xlfn.CONCAT(C18:E18),P!$J:$J,P!$I:$I,"UNAVAILABLE")) | D18: =IFERROR(IF(C18="","","N/A"),"") | G18: =IFERROR(VLOOKUP(B18,P!$X:$Z,3,FALSE),0) -> 0 | I18: =IF(RIOEPOXY[[#This Row],[QUOTED RATE]]="",RIOEPOXY[[#This Row],[UNIT RATE]]*RIOEPOXY[[#This Row],[QTY]],RIOEPOXY[[#This Row],[QUOTED RATE]]*RIOEPOXY[[#This Row],[QTY]]) -> 0 | L18: =IF(M18="","",_xlfn.XLOOKUP(_xlfn.CONCAT(M18:O18),P!$J:$J,P!$I:$I,"UNAVAILABLE")) | Q18: =ROUND(IF(AND(U18<>"",U18>0),IFERROR(VLOOKUP(L18,P!$X:$Z,3,FALSE),0)+(IF(OR(U13=1,$U$6=SUM($U$10:$U$18)),$U$6,($U$6-SUM($U$10:$U$18))/$U$8)+$U18)/$P18*28.05,IFERROR(VLOOKUP(L18,P!$X:$Z,3,FALSE),0)),2) -> 0 | S18: =IF(Table21[[#This Row],[QUOTED RATE]]="",Table21[[#This Row],[UNIT RATE]]*Table21[[#This Row],[QTY]],Table21[[#This Row],[QUOTED RATE]]*Table21[[#This Row],[QTY]]) -> 0 | U18: =IF(AND(N18="PIGMENTED",IFERROR(FIND("SL",M18),FALSE),IFERROR(VLOOKUP(L18,P!$X:$Z,3,FALSE),0)<>0),(1/12*P18),IF(AND(N18="PIGMENTED",IFERROR(FIND("SL",M18),TRUE),IFERROR(VLOOKUP(L18,P!$X:$Z,3,FALSE),0)<>0),(1/4*P18),"")) | V18: =IF(P18="","",IF(IFERROR(FIND("CB",M18),FALSE),P18*0.25,P18*0.5))
B19: Total | C19: Total | I19: =SUBTOTAL(109,RIOEPOXY[EXTENSION]) -> 0 | L19: Total | M19: Total | S19: =SUBTOTAL(109,Table21[EXTENSION]) -> 0
B21: COLORANT | C21: COLORANT | L21: AGGREGATES | M21: AGGREGATES
B22: PROD # | C22: PRODUCT | D22: COLOR | E22: UOM | F22: QTY | G22: UNIT RATE | H22: QUOTED RATE | I22: EXTENSION | L22: PROD # | M22: PRODUCT | N22: COLOR | O22: UOM | P22: QTY | Q22: UNIT RATE | R22: QUOTED RATE | S22: EXTENSION
B23: =IF(C23="","",_xlfn.XLOOKUP(_xlfn.CONCAT(C23:E23),P!$J:$J,P!$I:$I,"UNAVAILABLE")) -> S-CBG-1 | C23: POLYASPARTIC COLORANT | D23: BATTLESHIP GRAY | E23: PINT | G23: =IFERROR(VLOOKUP(B23,P!$X:$Z,3,FALSE),0) -> 56.43 | I23: =IF(RIOCOLOR[[#This Row],[QUOTED RATE]]="",RIOCOLOR[[#This Row],[UNIT RATE]]*RIOCOLOR[[#This Row],[QTY]],RIOCOLOR[[#This Row],[QUOTED RATE]]*RIOCOLOR[[#This Row],[QTY]]) -> 0 | L23: =IF(M23="","",_xlfn.XLOOKUP(_xlfn.CONCAT(M23:O23),P!$J:$J,P!$I:$I,"UNAVAILABLE")) -> S-QBS-1 | M23: FLAKE | N23: ASH | O23: 40LB | Q23: =IFERROR(VLOOKUP(L23,P!$X:$Z,3,FALSE),0) -> 198 | S23: =IF(Table22[[#This Row],[QUOTED RATE]]="",Table22[[#This Row],[UNIT RATE]]*Table22[[#This Row],[QTY]],Table22[[#This Row],[QUOTED RATE]]*Table22[[#This Row],[QTY]]) -> 0
B24: =IF(C24="","",_xlfn.XLOOKUP(_xlfn.CONCAT(C24:E24),P!$J:$J,P!$I:$I,"UNAVAILABLE")) -> R-CMG-1 | C24: CRETE COLORANT | D24: MEDIUM GRAY | E24: PINT | G24: =IFERROR(VLOOKUP(B24,P!$X:$Z,3,FALSE),0) -> 28.05 | I24: =IF(RIOCOLOR[[#This Row],[QUOTED RATE]]="",RIOCOLOR[[#This Row],[UNIT RATE]]*RIOCOLOR[[#This Row],[QTY]],RIOCOLOR[[#This Row],[QUOTED RATE]]*RIOCOLOR[[#This Row],[QTY]]) -> 0 | L24: =IF(M24="","",_xlfn.XLOOKUP(_xlfn.CONCAT(M24:O24),P!$J:$J,P!$I:$I,"UNAVAILABLE")) -> S-QMT-1 | M24: QUARTZ | N24: MALT | O24: 50LB | Q24: =IFERROR(VLOOKUP(L24,P!$X:$Z,3,FALSE),0) -> 33 | S24: =IF(Table22[[#This Row],[QUOTED RATE]]="",Table22[[#This Row],[UNIT RATE]]*Table22[[#This Row],[QTY]],Table22[[#This Row],[QUOTED RATE]]*Table22[[#This Row],[QTY]]) -> 0
B25: =IF(C25="","",_xlfn.XLOOKUP(_xlfn.CONCAT(C25:E25),P!$J:$J,P!$I:$I,"UNAVAILABLE")) -> R-CSB-25 | C25: CRETE COLORANT - LARGE | D25: SANDY BEIGE | E25: 25 PINTS | G25: =IFERROR(VLOOKUP(B25,P!$X:$Z,3,FALSE),0) -> 440 | I25: =IF(RIOCOLOR[[#This Row],[QUOTED RATE]]="",RIOCOLOR[[#This Row],[UNIT RATE]]*RIOCOLOR[[#This Row],[QTY]],RIOCOLOR[[#This Row],[QUOTED RATE]]*RIOCOLOR[[#This Row],[QTY]]) -> 0 | L25: =IF(M25="","",_xlfn.XLOOKUP(_xlfn.CONCAT(M25:O25),P!$J:$J,P!$I:$I,"UNAVAILABLE")) -> S-AST-1 | M25: TROWEL QUARTZ | N25: ASH | O25: 50LB | Q25: =IFERROR(VLOOKUP(L25,P!$X:$Z,3,FALSE),0) -> 33 | S25: =IF(Table22[[#This Row],[QUOTED RATE]]="",Table22[[#This Row],[UNIT RATE]]*Table22[[#This Row],[QTY]],Table22[[#This Row],[QUOTED RATE]]*Table22[[#This Row],[QTY]]) -> 0
B26: =IF(C26="","",_xlfn.XLOOKUP(_xlfn.CONCAT(C26:E26),P!$J:$J,P!$I:$I,"UNAVAILABLE")) | G26: =IFERROR(VLOOKUP(B26,P!$X:$Z,3,FALSE),0) -> 0 | I26: =IF(RIOCOLOR[[#This Row],[QUOTED RATE]]="",RIOCOLOR[[#This Row],[UNIT RATE]]*RIOCOLOR[[#This Row],[QTY]],RIOCOLOR[[#This Row],[QUOTED RATE]]*RIOCOLOR[[#This Row],[QTY]]) -> 0 | L26: =IF(M26="","",_xlfn.XLOOKUP(_xlfn.CONCAT(M26:O26),P!$J:$J,P!$I:$I,"UNAVAILABLE")) -> R-A60-1 | M26: ALUMINUM OXIDE | N26: 60# | O26: 50LB | Q26: =IFERROR(VLOOKUP(L26,P!$X:$Z,3,FALSE),0) -> 198 | S26: =IF(Table22[[#This Row],[QUOTED RATE]]="",Table22[[#This Row],[UNIT RATE]]*Table22[[#This Row],[QTY]],Table22[[#This Row],[QUOTED RATE]]*Table22[[#This Row],[QTY]]) -> 0
B27: =IF(C27="","",_xlfn.XLOOKUP(_xlfn.CONCAT(C27:E27),P!$J:$J,P!$I:$I,"UNAVAILABLE")) | G27: =IFERROR(VLOOKUP(B27,P!$X:$Z,3,FALSE),0) -> 0 | I27: =IF(RIOCOLOR[[#This Row],[QUOTED RATE]]="",RIOCOLOR[[#This Row],[UNIT RATE]]*RIOCOLOR[[#This Row],[QTY]],RIOCOLOR[[#This Row],[QUOTED RATE]]*RIOCOLOR[[#This Row],[QTY]]) -> 0 | L27: =IF(M27="","",_xlfn.XLOOKUP(_xlfn.CONCAT(M27:O27),P!$J:$J,P!$I:$I,"UNAVAILABLE")) | Q27: =IFERROR(VLOOKUP(L27,P!$X:$Z,3,FALSE),0) -> 0 | S27: =IF(Table22[[#This Row],[QUOTED RATE]]="",Table22[[#This Row],[UNIT RATE]]*Table22[[#This Row],[QTY]],Table22[[#This Row],[QUOTED RATE]]*Table22[[#This Row],[QTY]]) -> 0
B28: =IF(C28="","",_xlfn.XLOOKUP(_xlfn.CONCAT(C28:E28),P!$J:$J,P!$I:$I,"UNAVAILABLE")) | G28: =IFERROR(VLOOKUP(B28,P!$X:$Z,3,FALSE),0) -> 0 | I28: =IF(RIOCOLOR[[#This Row],[QUOTED RATE]]="",RIOCOLOR[[#This Row],[UNIT RATE]]*RIOCOLOR[[#This Row],[QTY]],RIOCOLOR[[#This Row],[QUOTED RATE]]*RIOCOLOR[[#This Row],[QTY]]) -> 0 | L28: =IF(M28="","",_xlfn.XLOOKUP(_xlfn.CONCAT(M28:O28),P!$J:$J,P!$I:$I,"UNAVAILABLE")) -> R-ETM-C50 | M28: RIO TROWEL CLAD SAND | N28: N/A | O28: 50LB | Q28: =IFERROR(VLOOKUP(L28,P!$X:$Z,3,FALSE),0) -> 19.8 | S28: =IF(Table22[[#This Row],[QUOTED RATE]]="",Table22[[#This Row],[UNIT RATE]]*Table22[[#This Row],[QTY]],Table22[[#This Row],[QUOTED RATE]]*Table22[[#This Row],[QTY]]) -> 0
B29: =IF(C29="","",_xlfn.XLOOKUP(_xlfn.CONCAT(C29:E29),P!$J:$J,P!$I:$I,"UNAVAILABLE")) | G29: =IFERROR(VLOOKUP(B29,P!$X:$Z,3,FALSE),0) -> 0 | I29: =IF(RIOCOLOR[[#This Row],[QUOTED RATE]]="",RIOCOLOR[[#This Row],[UNIT RATE]]*RIOCOLOR[[#This Row],[QTY]],RIOCOLOR[[#This Row],[QUOTED RATE]]*RIOCOLOR[[#This Row],[QTY]]) -> 0 | L29: =IF(M29="","",_xlfn.XLOOKUP(_xlfn.CONCAT(M29:O29),P!$J:$J,P!$I:$I,"UNAVAILABLE")) | Q29: =IFERROR(VLOOKUP(L29,P!$X:$Z,3,FALSE),0) -> 0 | S29: =IF(Table22[[#This Row],[QUOTED RATE]]="",Table22[[#This Row],[UNIT RATE]]*Table22[[#This Row],[QTY]],Table22[[#This Row],[QUOTED RATE]]*Table22[[#This Row],[QTY]]) -> 0
B30: =IF(C30="","",_xlfn.XLOOKUP(_xlfn.CONCAT(C30:E30),P!$J:$J,P!$I:$I,"UNAVAILABLE")) | G30: =IFERROR(VLOOKUP(B30,P!$X:$Z,3,FALSE),0) -> 0 | I30: =IF(RIOCOLOR[[#This Row],[QUOTED RATE]]="",RIOCOLOR[[#This Row],[UNIT RATE]]*RIOCOLOR[[#This Row],[QTY]],RIOCOLOR[[#This Row],[QUOTED RATE]]*RIOCOLOR[[#This Row],[QTY]]) -> 0 | L30: =IF(M30="","",_xlfn.XLOOKUP(_xlfn.CONCAT(M30:O30),P!$J:$J,P!$I:$I,"UNAVAILABLE")) | Q30: =IFERROR(VLOOKUP(L30,P!$X:$Z,3,FALSE),0) -> 0 | S30: =IF(Table22[[#This Row],[QUOTED RATE]]="",Table22[[#This Row],[UNIT RATE]]*Table22[[#This Row],[QTY]],Table22[[#This Row],[QUOTED RATE]]*Table22[[#This Row],[QTY]]) -> 0
